Workbook

Sheet WK21
B2: ALLEEN GEKLEURDE LETTERS EN CIJFERS INGEVEN!
P4: Overige
D5: Dagen | E5: Uren | F5: VAK | G5: ZIEK | H5: RV | I5: KV/C | J5: FD | L5: Enkel | M5: Totaal | O5: Bedrag km/ | P5: Extra | Q5: Totaal
C6: Contract | D6: ge- | E6: ge- | F6: Op- | G6: Op- | H6: Op- | I6: Door | J6: Door | K6: Netto | L6: Km woon- | M6: Km werk- | N6: Totaal | O6: brandstof | P6: Declaratie | Q6: Netto
B7: Werknemer | C7: Uren | D7: werkt | E7: werkt | F7: name | G7: name | H7: name | I7: bet. | J7: bet. | K7: bedrag | L7: werk pd | M7: werk | N7: Km | O7: bedrag | P7: vergoeding | Q7: Voorschot | R7: Opmerking | S7: Actueel project en KM's enkele reis
B8: =Periode!B8 -> Ruben Hellemons | C8: =Periode!G8 -> 124 (4wk) | D8: 4 | E8: 32 | F8: 8 | K8: =(Periode!BB8*E8/40)+((F8+H8+I8)*Periode!BD8/40)+(J8*Periode!BF8/40)+(G8*Periode!BE8/40) -> 717.44036 | Q8: =K8+O8+P8 -> 717.44036 | R8: MaV8 | S8: 1-VSV-81 met verklaring
B12: =Periode!B12 -> Andre Sintenie | C12: =Periode!G12 -> 32 (4wk) | D12: 2 | E12: 16 | G12: =8*0.95 -> 7.6 | K12: =(Periode!BB12*E12/40)+((F12+H12+I12)*Periode!BD12/40)+(J12*Periode!BF12/40)+(G12*Periode!BE12/40) -> 383.7948 | Q12: =K12+O12+P12 -> 383.7948 | R12: MaEZ DiZ8 95% VrE8 | S12: VV-204-L met verklaring
C13: =Periode!H13 -> 0 | Q13: =K13+O13+P13 -> 0
R14: 4 wekelijkse betaling
B15: =Periode!B15 -> Dennis Aarts | C15: =Periode!G15 -> 0 | K15: =(Periode!BB15*E15/40)+((F15+H15+I15)*Periode!BD15/40)+(J15*Periode!BF15/40)+(G15*Periode!BE15/40) -> 0 | Q15: =K15+O15+P15 -> 0 | R15: E40 | S15: 98-XH-DP Bijtelling
B17: =Periode!B17 -> Kay Sanders | L17: 69
K20: =(Periode!BB20*E20/40)+((F20+H20+I20)*Periode!BD20/40)+(J20*Periode!BF20/40)+(G20*Periode!BE20/40) -> 0 | Q20: =K20+O20+P20 -> 0
B23: =Periode!B23 -> Frank Stouthart | C23: =Periode!G23 -> 32 (4wk) | D23: 4 | E23: 32 | F23: 8 | K23: =(Periode!BB23*E23/40)+((F23+H23+I23)*Periode!BD23/40)+(J23*Periode!BF23/40)+(G23*Periode!BE23/40) -> 701.67964 | L23: 34 | N23: =(L23*D23*2)+M23 -> 272 | O23: =((L23*2*D23)+M23)*0.28 -> 76.16 | Q23: =K23+O23+P23 -> 777.83964 | R23: VrV8 | S23: Vredespaleis Den Haag 34km, Lantaarnvenster R'dam 29km, Kralingseweg 179 R'dam 22 km (schrijft zelf 23km); Voorstraat Voorburg 38 km (schrijft 37km); Petrus Pauluskerk Leidschendam 31km (schrijft 33km); Kerkstraat Voorburg 31km (schrijft 33k); Koninginnegracht Den Haag 33km (schrijft 27 als hij stukje meerijdt); Tiber, den Haag 27km; Rokin 112, amsterdam 71 km (schrijft 70km); Concertgebouw 73km;
B26: =Periode!B26 -> Roy Rubeling | C26: =Periode!G26 -> 0 | D26: 3 | E26: 24 | K26: =(Periode!BB26*E26/40)+((F26+H26+I26)*Periode!BD26/40)+(J26*Periode!BF26/40)+(G26*Periode!BE26/40) -> 450 | L26: 61 | M26: =20+20+20 -> 60 | N26: =(L26*D26*2)+M26 -> 426 | O26: =((L26*2*D26)+M26)*0.28 -> 119.28 | Q26: =K26+O26+P26 -> 569.28 | R26: MaE8 VrWAZO | S26: Akoestische maatregelen Schiphol 61km
R27: Week 19 dubbel betaald € -569,28 van de € 754,00
T31: €
B33: =Periode!B33 -> Marco Govers | C33: =Periode!G33 -> 32 (4wk) | D33: 5 | E33: 40 | K33: =(Periode!BB33*E33/40)+((F33+H33+I33)*Periode!BD33/40)+(J33*Periode!BF33/40)+(G33*Periode!BE33/40) -> 775.21 | L33: 39 | N33: =(L33*D33*2)+M33 -> 390 | O33: =((L33*2*D33)+M33)*0.28 -> 109.2 | Q33: =K33+O33+P33 -> 884.41 | S33: Het Groot Kwartier 39km (schrijft 40)
B35: =Periode!B35 -> Onno de Vries | C35: =Periode!G35 -> 124 (4wk) | D35: 5 | E35: 40 | K35: =(Periode!BB35*E35/40)+((F35+H35+I35)*Periode!BD35/40)+(J35*Periode!BF35/40)+(G35*Periode!BE35/40) -> 633.355 | L35: 10 | N35: =(L35*D35*2)+M35 -> 100 | O35: =((L35*2*D35)+M35)*0.28 -> 28 | Q35: =K35+O35+P35 -> 661.355 | S35: LP4 10 km (schrijft 11km)
B39: =Periode!B39 -> Jan Levering | C39: =Periode!G39 -> 32 (4wk) | K39: =(Periode!BB39*E39/40)+((F39+H39+I39)*Periode!BD39/40)+(J39*Periode!BF39/40)+(G39*Periode!BE39/40) -> 0 | P39: 143.37 | Q39: =K39+O39+P39 -> 143.37 | R39: Aanvulling ZW € 143,37 | S39: Verklaring 1-VXV-55
B42: =Periode!B42 -> Alex van der Laan | C42: =Periode!G42 -> 32 (wk) | D42: 5 | E42: 36 | K42: =(Periode!BB42*E42/40)+((F42+H42+I42)*Periode!BD42/40)+(J42*Periode!BF42/40)+(G42*Periode!BE42/40) -> 606.375 | Q42: =K42+O42+P42 -> 606.375 | R42: VrE4 | S42: Bijtelling 36-GNP-4
R43: Betalen Bewind:
R44: =K46 -> 463.94531 | S44: Bijtelling 78-RJ-BP
R45: Betalen Shafieq: | S45: Onkosten betalen op rekening Shafieq: NL65 ABNA 0128 6728 97
B46: =Periode!B46 -> Shafieq Asgarali | C46: =Periode!G46 -> 32 (4wk) | D46: 5 | E46: 37.5 | K46: =(Periode!BB46*E46/40)+((F46+H46+I46)*Periode!BD46/40)+(J46*Periode!BF46/40)+(G46*Periode!BE46/40) -> 463.94531 | P46: =(D46*Periode!AY46) -> 58.25 | Q46: =K46+O46+P46 -> 522.19531 | R46: =P46 -> 58.25 | S46: Loon betalen onder bewindvoering: NL93 ABNA 0128 6727 81
R47: Ma t/m VrZ7,4 - Restant loonbeslag:
B48: =Periode!B48 -> Sander van den Hoek | C48: =Periode!G48 -> 32 (wk) | G48: =(5*7.4)*0.9 -> 33.3 | K48: =(Periode!BB48*E48/40)+((F48+H48+I48)*Periode!BD48/40)+(J48*Periode!BF48/40)+(G48*Periode!BE48/40) -> 478.62506 | L48: 5 | N48: =(L48*D48*2)+M48 -> 0 | O48: =((L48*2*D48)+M48)*0.23 -> 0 | P48: =(D48*Periode!AY48) -> 0 | Q48: =K48+O48+P48+P49 -> 478.62506 | R48: =(1301*12/13)-K48 -> 722.29801 | S48: St. Martinuskerk Voorburg 11 km
R49: Betalen Sander: | S49: Loonbeslag Belastindienst NL89 INGB 000 000 4820
C50: =Periode!G50 -> 0 | R50: =Q48 -> 478.62506 | S50: t.n.v. S. van den Hoek 1735.64.781
B53: =Periode!B53 -> Ronald van Maanen | C53: =Periode!G53 -> 32 (4wk) | D53: 5 | E53: 38 | K53: =(Periode!BB53*E53/40)+((F53+H53+I53)*Periode!BD53/40)+(J53*Periode!BF53/40)+(G53*Periode!BE53/40) -> 696.5875 | L53: 49 | N53: =(L53*D53*2)+M53 -> 490 | O53: =((L53*2*D53)+M53)*0.28 -> 137.2 | Q53: =K53+O53+P53 -> 833.7875 | R53: VrE2 | S53: Nijmegen gemiddelde heen/terug 49km
C54: =Periode!H75 -> 0
C55: =Periode!H76 -> 0
B57: =Periode!B57 -> Erik Visser | C57: =Periode!G57 -> 32 (4wk) | D57: 5 | E57: 35 | K57: =(Periode!BB57*E57/40)+((F57+H57+I57)*Periode!BD57/40)+(J57*Periode!BF57/40)+(G57*Periode!BE57/40) -> 490.385 | L57: 14 | M57: =82+30+64+30+72 -> 278 | N57: =(L57*D57*2)+M57 -> 418 | O57: =((L57*2*D57))*0.23+(M57*0.28) -> 110.04 | Q57: =K57+O57+P57 -> 600.425 | R57: DiE5 | S57: Janssen de Jong OnderhoudPlus 14km
S58: wer-werk km € 0,28 (€ 0,32 naar de klant)
C59: =Periode!G59 -> 0 | K59: =(Periode!BB59*E59/40)+((F59+H59+I59)*Periode!BD59/40)+(J59*Periode!BF59/40)+(G59*Periode!BE59/40) -> 0 | Q59: =K59+O59+P59 -> 0
R60: Betalen Bewind:
R61: =K63 -> 463.94531
R62: Betalen Youri:
B63: =Periode!B63 -> Youri Nouwens | C63: =Periode!G63 -> 32 (4wk) | E63: 37.5 | K63: =(Periode!BB63*E63/40)+((F63+H63+I63)*Periode!BD63/40)+(J63*Periode!BF63/40)+(G63*Periode!BE63/40) -> 463.94531 | P63: =(D63*Periode!AY63) -> 0 | Q63: =K63+O63+P63 -> 463.94531 | R63: =P63 -> 0 | S63: Bijtelling 54-GDT-8
R64: Leegloop | S64: Loon overmaken naar Bewindvoerder: NL20 ABNA 0830 2655 89 - De Maas dienstverlening
S65: Onkosten overmaken naar Youri: NL21 INGB 0799 0333 59
L68: 52 | N68: =(L68*D68*2)+M68 -> 0 | Q68: =K68+O68+P68 -> 0
B70: =Periode!B70 -> Marco Booij | C70: =Periode!G70 -> 32 (4wk) | K70: =(Periode!BB70*E70/40)+((F70+H70+I70)*Periode!BD70/40)+(J70*Periode!BF70/40)+(G70*Periode!BE70/40) -> 0 | P70: 171.65 | Q70: =K70+O70+P70 -> 171.65 | R70: Aanvulling Z € 171,65 netto | S70: Bijtelling 52-LN-BT
L72: 50 | N72: =(L72*D72*2)+M72 -> 0 | Q72: =K72+O72+P72 -> 0 | S72: Voorschoterweg 8a, 50 km
B74: =Periode!B74 -> Kevin Schuiling | C74: =Periode!G74 -> 32 (4wk) | D74: 5 | E74: 40 | K74: =(Periode!BB74*E74/40)+((F74+H74+I74)*Periode!BD74/40)+(J74*Periode!BF74/40)+(G74*Periode!BE74/40) -> 600 | L74: 56 | M74: =-560+(4*56)+(6*57) -> 6 | N74: =(L74*D74*2)+M74 -> 566 | O74: =((L74*2*D74)+M74)*0.28 -> 158.48 | Q74: =K74+O74+P74 -> 758.48 | S74: Het Groot Kwartier 58km, Stadsschouwburg Nijmegen 18km, Kaatsheuvel 83km, Huis73 56km
B77: =Periode!B77 -> Steven Lamers | C77: =Periode!G77 -> 32 (4wk) | D77: 5 | E77: 40 | K77: =(Periode!BB77*E77/40)+((F77+H77+I77)*Periode!BD77/40)+(J77*Periode!BF77/40)+(G77*Periode!BE77/40) -> 663.32 | Q77: =K77+O77+P77 -> 663.32 | S77: Bijtelling 82-VZJ-2
C78: =Periode!H78 -> 0 | S78: Kredietbank Nederland NL48 BNGH 0285 0174 03 o.v.v. 6200559
C79: =Periode!H79 -> 0
B80: =Periode!B80 -> Leo van Doorn | C80: =Periode!G80 -> 0 | D80: 5 | E80: 40 | K80: =(Periode!BB80*E80/40)+((F80+H80+I80)*Periode!BD80/40)+(J80*Periode!BF80/40)+(G80*Periode!BE80/40) -> 711.76 | L80: 21 | N80: =(L80*D80*2)+M80 -> 210 | O80: =((L80*2*D80)+M80)*0.28 -> 58.8 | Q80: =K80+O80+P80 -> 770.56 | S80: Nijpelsplantsoen 21km
C81: =Periode!H81 -> 0
C82: =Periode!H82 -> 0
B83: =Periode!B83 -> Tobin van de Kuil | C83: =Periode!G83 -> 0 | D83: 4 | E83: 30 | K83: =(Periode!BB83*E83/40)+((F83+H83+I83)*Periode!BD83/40)+(J83*Periode!BF83/40)+(G83*Periode!BE83/40) -> 564.59625 | L83: 0 | M83: 324 | N83: =(L83*D83*2)+M83 -> 324 | O83: =((L83*2*D83)+M83)*0.28 -> 90.72 | P83: 28.28 | Q83: =K83+O83+P83 -> 683.59625 | R83: MaE1 DiE1 WoE8 | S83: Woonplus Schiedam
C84: =Periode!H84 -> 0 | R84: Teveel KM betaald 100km
C85: =Periode!H85 -> 0
C86: =Periode!H86 -> 0
B87: =Periode!B87 -> Carlo Peetoom | C87: =Periode!G87 -> 32 (4wk) | D87: 4 | E87: 32 | K87: =(Periode!BB87*E87/40)+((F87+H87+I87)*Periode!BD87/40)+(J87*Periode!BF87/40)+(G87*Periode!BE87/40) -> 672.54 | L87: 40 | N87: =(L87*D87*2)+M87 -> 320 | O87: =((L87*2*D87)+M87)*0.23 -> 73.6 | Q87: =K87+O87+P87 -> 746.14 | R87: VrE8 | S87: Westfries Museum 40km
C88: =Periode!H88 -> 0
C89: =Periode!H89 -> 0
B90: =Periode!B90 -> Aries Provence | C90: =Periode!G90 -> 0 | D90: 4 | E90: 32 | K90: =(Periode!BB90*E90/40)+((F90+H90+I90)*Periode!BD90/40)+(J90*Periode!BF90/40)+(G90*Periode!BE90/40) -> 480.276 | L90: 85 | N90: =(L90*D90*2)+M90 -> 680 | O90: =((L90*2*D90)+M90)*0.23 -> 156.4 | Q90: =K90+O90+P90 -> 636.676 | R90: WoE8 | S90: Het Groot Kwartier 85km
C91: =Periode!H91 -> 0
B92: =Periode!B92 -> Gregory de Graaf | C92: =Periode!G92 -> 0 | D92: 5 | E92: 35 | K92: =(Periode!BB92*E92/40)+((F92+H92+I92)*Periode!BD92/40)+(J92*Periode!BF92/40)+(G92*Periode!BE92/40) -> 645.75 | Q92: =K92+O92+P92 -> 645.75 | R92: 4 wekelijkse betaling | S92: Verklaring 34-LK-NH
C93: =Periode!H93 -> 0 | R93: DoE2 VrE3
C94: =Periode!H94 -> 0
C96: =Periode!H96 -> 0
C97: =Periode!H97 -> 0
B99: =Periode!B99 -> Eric de Jong | C99: =Periode!G99 -> 0 | D99: 5 | E99: 40 | K99: =(Periode!BB99*E99/40)+((F99+H99+I99)*Periode!BD99/40)+(J99*Periode!BF99/40)+(G99*Periode!BE99/40) -> 928.01 | L99: 47 | N99: =(L99*D99*2)+M99 -> 470 | O99: =((L99*2*D99)+M99)*0.23 -> 108.1 | Q99: =K99+O99+P99 -> 1036.11 | S99: LP4 47km
C103: =Periode!H103 -> 0
B104: =Periode!B104 -> Michel van der Mark | C104: =Periode!G104 -> 32 (4wk) | G104: =(4*8)*0.9 -> 28.8 | K104: =(Periode!BB104*E104/40)+((F104+H104+I104)*Periode!BD104/40)+(J104*Periode!BF104/40)+(G104*Periode!BE104/40) -> 491.17622 | Q104: =K104+O104+P104 -> 491.17622 | R104: MaEZ8 Di-VrZ8 | S104: Bijtelling GVR-35-D
C105: =Periode!H105 -> 0 | R105: 2e ziekmelding, omvang dienstverband 7,87
C106: =Periode!H106 -> 0
C108: =Periode!H108 -> 0
C109: =Periode!H109 -> 0
B110: =Periode!B110 -> Jan Harteveld | C110: =Periode!G110 -> 150 (4wk) | D110: 5 | E110: 35 | F110: 2.5 | K110: =(Periode!BB110*E110/40)+((F110+H110+I110)*Periode!BD110/40)+(J110*Periode!BF110/40)+(G110*Periode!BE110/40) -> 742.57059 | L110: 14 | N110: =(L110*D110*2)+M110 -> 140 | O110: =((L110*2*D110)+M110)*0.23 -> 32.2 | Q110: =K110+O110+P110 -> 774.77059 | R110: MaE1,5 DiE1 DoV2,5 | S110: LP4 14km (€ 0,23 gaat op de fiets)
C111: =Periode!H111 -> 0
C112: =Periode!H112 -> 0
C114: =Periode!H114 -> 0
C115: =Periode!H115 -> 0
B116: =Periode!B116 -> Asanty Raafenberg | C116: =Periode!G116 -> 0 | D116: 5 | E116: 40 | K116: =(Periode!BB116*E116/40)+((F116+H116+I116)*Periode!BD116/40)+(J116*Periode!BF116/40)+(G116*Periode!BE116/40) -> 660.28 | Q116: =K116+O116+P116 -> 660.28 | R116: 4 wekelijkse betaling | S116: Bijtelling 90-XB-JF
L117: 16
C118: =Periode!H118 -> 0
B119: =Periode!B119 -> Patrick Serlier | C119: =Periode!G119 -> 32 (4wk) | D119: 5 | E119: 40 | K119: =(Periode!BB119*E119/40)+((F119+H119+I119)*Periode!BD119/40)+(J119*Periode!BF119/40)+(G119*Periode!BE119/40) -> 675.47 | Q119: =K119+O119+P119 -> 675.47 | S119: Verklaring VLT-24-V
C120: =Periode!H120 -> 0
C121: =Periode!H121 -> 0
C122: =Periode!H122 -> 0
B123: =Periode!B123 -> Pieter van Houwelingen | C123: =Periode!G123 -> 32 (4wk) | D123: 5 | E123: 38 | K123: =(Periode!BB123*E123/40)+((F123+H123+I123)*Periode!BD123/40)+(J123*Periode!BF123/40)+(G123*Periode!BE123/40) -> 998.29325 | L123: 32.5 | N123: =(L123*D123*2)+M123 -> 325 | O123: =((L123*2*D123)+M123)*0.23 -> 74.75 | Q123: =K123+O123+P123 -> 1073.0433 | R123: VrE2 | S123: Uitvoering 32,5km (ochtend 29,5 en middag 34,5)
C124: =Periode!H124 -> 0
B125: =Periode!B125 -> John van der Wel | C125: =Periode!G125 -> 0 | D125: 4 | E125: 32 | K125: =(Periode!BB125*E125/40)+((F125+H125+I125)*Periode!BD125/40)+(J125*Periode!BF125/40)+(G125*Periode!BE125/40) -> 516.784 | P125: -65.06 | Q125: =K125+O125+P125 -> 451.724 | R125: VrE8 | S125: Bijtelling 04-SP-VN
R126: Inhouden boetes deel 1
C127: =Periode!H127 -> 0
C128: =Periode!H128 -> 0
B129: =Periode!B129 -> Marcel Spruijt | C129: =Periode!G129 -> 32 (4wk) | D129: 5 | E129: 40 | K129: =(Periode!BB129*E129/40)+((F129+H129+I129)*Periode!BD129/40)+(J129*Periode!BF129/40)+(G129*Periode!BE129/40) -> 751.94 | Q129: =K129+O129+P129 -> 751.94 | S129: Bijtelling 54-GVP-1
C130: =Periode!H130 -> 0
B131: =Periode!B131 -> Michael Windhorst | C131: =Periode!G131 -> 0 | D131: 5 | E131: 36 | K131: =(Periode!BB131*E131/40)+((F131+H131+I131)*Periode!BD131/40)+(J131*Periode!BF131/40)+(G131*Periode!BE131/40) -> 565.2 | Q131: =K131+O131+P131 -> 565.2 | R131: VrE4 | S131: Bijtelling V-695-HK
R132: Betalen Bewind:
C133: =Periode!H133 -> 0 | R133: =K134 -> 542.4925
B134: =Periode!B134 -> Remco van Doorne | C134: =Periode!G134 -> 0 | D134: 5 | E134: 40 | K134: =(Periode!BB134*E134/40)+((F134+H134+I134)*Periode!BD134/40)+(J134*Periode!BF134/40)+(G134*Periode!BE134/40) -> 542.4925 | P134: =(D134*Periode!AY134) -> 52.15 | Q134: =K134+O134+P134 -> 594.6425 | R134: Betalen Remco: | S134: Bijtelling 97-GFD-4
R135: =P134 -> 52.15 | S135: Onkosten betalen op rekening Remco: NL60 RABO 0102 064 024 t.n.v. R. van Doorne
C136: =Periode!H136 -> 0 | S136: Loon betalen onder bewindvoering: NL45 ABNA 0877 629 366 t.n.v. R. van Doorne e.o.
C137: =Periode!H137 -> 0
B138: =Periode!B138 -> Rob Valkenburg | C138: =Periode!G138 -> 0 | D138: 5 | E138: 39 | K138: =(Periode!BB138*E138/40)+((F138+H138+I138)*Periode!BD138/40)+(J138*Periode!BF138/40)+(G138*Periode!BE138/40) -> 713.61225 | L138: 35 | N138: =(L138*D138*2)+M138 -> 350 | O138: =((L138*2*D138)+M138)*0.28 -> 98 | Q138: =K138+O138+P138 -> 811.61225 | R138: DoE1 | S138: Huis te Manpad 35km
C139: =Periode!H139 -> 0
...

Sheet WK22
B2: ALLEEN GEKLEURDE LETTERS EN CIJFERS INGEVEN!
P4: Overige
D5: Dagen | E5: Uren | F5: VAK | G5: ZIEK | H5: RV | I5: KV/C | J5: FD | L5: Enkel | M5: Totaal | O5: Bedrag km/ | P5: Extra | Q5: Totaal
C6: Contract | D6: ge- | E6: ge- | F6: Op- | G6: Op- | H6: Op- | I6: Door | J6: Door | K6: Netto | L6: Km woon- | M6: Km werk- | N6: Totaal | O6: brandstof | P6: Declaratie/ | Q6: Netto
B7: Werknemer | C7: Uren | D7: werkt | E7: werkt | F7: name | G7: name | H7: name | I7: bet. | J7: bet. | K7: bedrag | L7: werk pd | M7: werk pd | N7: Km | O7: bedrag | P7: vergoeding | Q7: Voorschot | R7: Opmerking | S7: Actueel project en KM's enkele reis
B8: =Periode!B8 -> Ruben Hellemons | C8: =Periode!G8 -> 124 (4wk) | D8: 4 | E8: 32 | J8: 8 | K8: =(Periode!BB8*E8/40)+((F8+H8+I8)*Periode!BD8/40)+(J8*Periode!BF8/40)+(G8*Periode!BE8/40) -> 717.44036 | Q8: =K8+O8+P8 -> 717.44036 | R8: MaF8 | S8: 1-VSV-81 met verklaring
B12: =Periode!B12 -> Andre Sintenie | C12: =Periode!G12 -> 32 (4wk) | D12: 3 | E12: 24 | J12: 8 | K12: =(Periode!BB12*E12/40)+((F12+H12+I12)*Periode!BD12/40)+(J12*Periode!BF12/40)+(G12*Periode!BE12/40) -> 521.23368 | Q12: =K12+O12+P12 -> 521.23368 | R12: MaF8 VrE8 | S12: VV-204-L met verklaring
B13: =Periode!B13 -> 0 | C13: =Periode!H13 -> 0 | Q13: =K13+O13+P13 -> 0
B15: =Periode!B15 -> Dennis Aarts | C15: =Periode!G15 -> 0 | J15: 8 | K15: =(Periode!BB15*E15/40)+((F15+H15+I15)*Periode!BD15/40)+(J15*Periode!BF15/40)+(G15*Periode!BE15/40) -> 137.08728 | Q15: =K15+O15+P15 -> 137.08728 | R15: 4 wekelijkse betaling | S15: 98-XH-DP Bijtelling
R16: MaF8 E32
B17: =Periode!B17 -> Kay Sanders
K20: =(Periode!BB20*E20/40)+((F20+H20+I20)*Periode!BD20/40)+(J20*Periode!BF20/40)+(G20*Periode!BE20/40) -> 0 | Q20: =K20+O20+P20 -> 0
B23: =Periode!B23 -> Frank Stouthart | C23: =Periode!G23 -> 32 (4wk) | D23: 4 | E23: 30 | J23: 8 | K23: =(Periode!BB23*E23/40)+((F23+H23+I23)*Periode!BD23/40)+(J23*Periode!BF23/40)+(G23*Periode!BE23/40) -> 666.36564 | L23: 34 | M23: =-272+(6*34)+(2*37) -> 6 | N23: =(L23*D23*2)+M23 -> 278 | O23: =((L23*2*D23)+M23)*0.28 -> 77.84 | Q23: =K23+O23+P23 -> 744.20564 | R23: MaF8 | S23: Vredespaleis Den Haag 34km, Lantaarnvenster R'dam 29km, Kralingseweg 179 R'dam 22 km (schrijft zelf 23km); Voorstraat Voorburg 38 km (schrijft 37km); Petrus Pauluskerk Leidschendam 31km (schrijft 33km); Kerkstraat Voorburg 31km (schrijft 33k); Koninginnegracht Den Haag 33km (schrijft 27 als hij stukje meerijdt); Tiber, den Haag 27km; Rokin 112, amsterdam 71 km (schrijft 70km); Concertgebouw 73km;
B26: =Periode!B26 -> Roy Rubeling | C26: =Periode!G26 -> 0 | D26: 3 | E26: 24 | J26: 8 | K26: =(Periode!BB26*E26/40)+((F26+H26+I26)*Periode!BD26/40)+(J26*Periode!BF26/40)+(G26*Periode!BE26/40) -> 596.2626 | L26: 61 | M26: =20+20+20 -> 60 | N26: =(L26*D26*2)+M26 -> 426 | O26: =((L26*2*D26)+M26)*0.28 -> 119.28 | Q26: =K26+O26+P26 -> 715.5426 | R26: VrWAZO | S26: Akoestische maatregelen Schiphol 61km
R27: Week 19 dubbel betaald restant van € 754,00
T31: €
B33: =Periode!B33 -> Marco Govers | C33: =Periode!G33 -> 32 (4wk) | D33: 4 | E33: 30 | I33: 2 | J33: 8 | K33: =(Periode!BB33*E33/40)+((F33+H33+I33)*Periode!BD33/40)+(J33*Periode!BF33/40)+(G33*Periode!BE33/40) -> 770.47523 | L33: 39 | N33: =(L33*D33*2)+M33 -> 312 | O33: =((L33*2*D33)+M33)*0.28 -> 87.36 | Q33: =K33+O33+P33 -> 857.83523 | R33: MaF8 VrKV2 | S33: Het Groot Kwartier 39km (schrijft 40)
B35: =Periode!B35 -> Onno de Vries | C35: =Periode!G35 -> 124 (4wk) | D35: 4 | E35: 32 | J35: 8 | K35: =(Periode!BB35*E35/40)+((F35+H35+I35)*Periode!BD35/40)+(J35*Periode!BF35/40)+(G35*Periode!BE35/40) -> 629.85089 | L35: 10 | N35: =(L35*D35*2)+M35 -> 80 | O35: =((L35*2*D35)+M35)*0.28 -> 22.4 | Q35: =K35+O35+P35 -> 652.25089 | R35: MaF8 | S35: LP4 10 km (schrijft 11km)
B39: =Periode!B39 -> Jan Levering | C39: =Periode!G39 -> 32 (4wk) | K39: =(Periode!BB39*E39/40)+((F39+H39+I39)*Periode!BD39/40)+(J39*Periode!BF39/40)+(G39*Periode!BE39/40) -> 0 | P39: 143.37 | Q39: =K39+O39+P39 -> 143.37 | R39: Aanvulling ZW € 143,37 | S39: Verklaring 1-VXV-55
B42: =Periode!B42 -> Alex van der Laan | C42: =Periode!G42 -> 32 (wk) | F42: 24 | I42: 8 | J42: 8 | K42: =(Periode!BB42*E42/40)+((F42+H42+I42)*Periode!BD42/40)+(J42*Periode!BF42/40)+(G42*Periode!BE42/40) -> 655.8255 | Q42: =K42+O42+P42 -> 655.8255 | R42: MaF8 DiKV8 V24 | S42: Bijtelling 36-GNP-4
R43: Betalen Bewind:
R44: =K46 -> 463.94531 | S44: Bijtelling 78-RJ-BP
R45: MaF7,5 - Betalen Shafieq: | S45: Onkosten betalen op rekening Shafieq: NL65 ABNA 0128 6728 97
B46: =Periode!B46 -> Shafieq Asgarali | C46: =Periode!G46 -> 32 (4wk) | D46: 4 | E46: 30 | J46: 7.5 | K46: =(Periode!BB46*E46/40)+((F46+H46+I46)*Periode!BD46/40)+(J46*Periode!BF46/40)+(G46*Periode!BE46/40) -> 463.94531 | P46: =(D46*Periode!AY46) -> 46.6 | Q46: =K46+O46+P46 -> 510.54531 | R46: =P46 -> 46.6 | S46: Loon betalen onder bewindvoering: NL93 ABNA 0128 6727 81
R47: Restant loonbeslag:
B48: =Periode!B48 -> Sander van den Hoek | C48: =Periode!G48 -> 32 (wk) | G48: =(5*7.4)*0.9 -> 33.3 | K48: =(Periode!BB48*E48/40)+((F48+H48+I48)*Periode!BD48/40)+(J48*Periode!BF48/40)+(G48*Periode!BE48/40) -> 478.62506 | L48: 28 | N48: =(L48*D48*2)+M48 -> 0 | O48: =((L48*2*D48)+M48)*0.25 -> 0 | P48: =(D48*Periode!AY48) -> 0 | Q48: =K48+O48+P48+P49 -> 478.62506 | R48: ='WK21'!R48-K48 -> 243.67295 | S48: St. Martinuskerk Voorburg 11 km
R49: Z100% - Betalen Sander: | S49: Loonbeslag Belastindienst NL89 INGB 000 000 4820
B50: =Periode!B50 -> 0 | C50: =Periode!G50 -> 0 | R50: =Q48 -> 478.62506 | S50: t.n.v. S. van den Hoek 1735.64.781
B53: =Periode!B53 -> Ronald van Maanen | C53: =Periode!G53 -> 32 (4wk) | D53: 4 | E53: 32 | J53: 8 | K53: =(Periode!BB53*E53/40)+((F53+H53+I53)*Periode!BD53/40)+(J53*Periode!BF53/40)+(G53*Periode!BE53/40) -> 728.5957 | L53: 49 | N53: =(L53*D53*2)+M53 -> 392 | O53: =((L53*2*D53)+M53)*0.28 -> 109.76 | Q53: =K53+O53+P53 -> 838.3557 | R53: MaF8 | S53: Nijmegen gemiddelde heen/terug 49km
B54: =Periode!B75 -> 0 | C54: =Periode!H75 -> 0
B55: =Periode!B76 -> 0 | C55: =Periode!H76 -> 0
B57: =Periode!B57 -> Erik Visser | C57: =Periode!G57 -> 32 (4wk) | D57: 4 | E57: 29.5 | J57: 8 | K57: =(Periode!BB57*E57/40)+((F57+H57+I57)*Periode!BD57/40)+(J57*Periode!BF57/40)+(G57*Periode!BE57/40) -> 522.23242 | L57: 14 | M57: =70+70+70+30 -> 240 | N57: =(L57*D57*2)+M57 -> 352 | O57: =((L57*2*D57))*0.25+(M57*0.28) -> 95.2 | P57: =(140*0.02)+37.38 -> 40.18 | Q57: =K57+O57+P57 -> 657.61242 | R57: MaF8 DiE2,5 | S57: Janssen de Jong OnderhoudPlus 14km
R58: Declaratie materiaal €37,38 | S58: wer-werk km € 0,28 (€ 0,32 naar de klant)
B59: =Periode!B59 -> 0 | C59: =Periode!G59 -> 0 | K59: =(Periode!BB59*E59/40)+((F59+H59+I59)*Periode!BD59/40)+(J59*Periode!BF59/40)+(G59*Periode!BE59/40) -> 0 | Q59: =K59+O59+P59 -> 0
R60: Betalen Bewind:
B61: =Periode!B61 -> 0 | R61: =K63 -> 463.94531
B62: =Periode!B62 -> 0 | R62: Betalen Youri:
B63: =Periode!B63 -> Youri Nouwens | C63: =Periode!G63 -> 32 (4wk) | E63: 37.5 | K63: =(Periode!BB63*E63/40)+((F63+H63+I63)*Periode!BD63/40)+(J63*Periode!BF63/40)+(G63*Periode!BE63/40) -> 463.94531 | P63: =(D63*Periode!AY63) -> 0 | Q63: =K63+O63+P63 -> 463.94531 | R63: =P63 -> 0 | S63: Bijtelling 54-GDT-8
B64: =Periode!B64 -> 0 | R64: Leegloop | S64: Loon overmaken naar Bewindvoerder: NL20 ABNA 0830 2655 89 - De Maas dienstverlening
S65: Onkosten overmaken naar Youri: NL21 INGB 0799 0333 59
B68: =Periode!B68 -> 0 | L68: 52 | N68: =(L68*D68*2)+M68 -> 0 | Q68: =K68+O68+P68 -> 0
B69: =Periode!B69 -> 0
B70: =Periode!B70 -> Marco Booij | C70: =Periode!G70 -> 32 (4wk) | K70: =(Periode!BB70*E70/40)+((F70+H70+I70)*Periode!BD70/40)+(J70*Periode!BF70/40)+(G70*Periode!BE70/40) -> 0 | P70: 171.65 | Q70: =K70+O70+P70 -> 171.65 | R70: Aanvulling Z € 171,65 netto | S70: Bijtelling 52-LN-BT
L72: 50 | N72: =(L72*D72*2)+M72 -> 0 | Q72: =K72+O72+P72 -> 0 | S72: Voorschoterweg 8a, 50 km
B73: 0
B74: =Periode!B74 -> Kevin Schuiling | C74: =Periode!G74 -> 32 (4wk) | D74: 3 | E74: 24 | J74: 8 | K74: =(Periode!BB74*E74/40)+((F74+H74+I74)*Periode!BD74/40)+(J74*Periode!BF74/40)+(G74*Periode!BE74/40) -> 476.5626 | L74: 58 | N74: =(L74*D74*2)+M74 -> 348 | O74: =((L74*2*D74)+M74)*0.28 -> 97.44 | Q74: =K74+O74+P74 -> 574.0026 | R74: MaF8 DiE8 | S74: Stadsschouwburg Nijmegen 18km, Kaatsheuvel 83km, Huis73 56km, Groot kwartier 58km
B75: =Periode!B75 -> 0
B76: =Periode!B76 -> 0
B77: =Periode!B77 -> Steven Lamers | C77: =Periode!G77 -> 32 (4wk) | D77: 3 | E77: 24 | J77: 8 | K77: =(Periode!BB77*E77/40)+((F77+H77+I77)*Periode!BD77/40)+(J77*Periode!BF77/40)+(G77*Periode!BE77/40) -> 527.09196 | Q77: =K77+O77+P77 -> 527.09196 | R77: MaF8 DiE8 | S77: Bijtelling 82-VZJ-2
B78: =Periode!B78 -> 0 | C78: =Periode!H78 -> 0 | S78: Kredietbank Nederland NL48 BNGH 0285 0174 03 o.v.v. 6200559
B79: =Periode!B79 -> 0 | C79: =Periode!H79 -> 0
B80: =Periode!B80 -> Leo van Doorn | C80: =Periode!G80 -> 0 | D80: 4 | E80: 32 | J80: 8 | K80: =(Periode!BB80*E80/40)+((F80+H80+I80)*Periode!BD80/40)+(J80*Periode!BF80/40)+(G80*Periode!BE80/40) -> 708.09908 | L80: 21 | N80: =(L80*D80*2)+M80 -> 168 | O80: =((L80*2*D80)+M80)*0.28 -> 47.04 | Q80: =K80+O80+P80 -> 755.13908 | R80: MaF8 | S80: Nijpelsplantsoen 21km
B81: =Periode!B81 -> 0 | C81: =Periode!H81 -> 0
B82: =Periode!B82 -> 0 | C82: =Periode!H82 -> 0
B83: =Periode!B83 -> Tobin van de Kuil | C83: =Periode!G83 -> 0 | D83: 1 | E83: 8 | J83: 8 | K83: =(Periode!BB83*E83/40)+((F83+H83+I83)*Periode!BD83/40)+(J83*Periode!BF83/40)+(G83*Periode!BE83/40) -> 296.42461 | L83: 0 | M83: 80 | N83: =(L83*D83*2)+M83 -> 80 | O83: =((L83*2*D83)+M83)*0.28 -> 22.4 | P83: -28.28 | Q83: =K83+O83+P83 -> 290.54461 | R83: MaF8 Wo t/m Vr E24 | S83: Woonplus Schiedam
C84: =Periode!H84 -> 0 | R84: Correctie teveel km betaald week 21
B85: =Periode!B85 -> 0 | C85: =Periode!H85 -> 0
B86: =Periode!B86 -> 0 | C86: =Periode!H86 -> 0
B87: =Periode!B87 -> Carlo Peetoom | C87: =Periode!G87 -> 32 (4wk) | D87: 3 | E87: 24 | J87: 8 | K87: =(Periode!BB87*E87/40)+((F87+H87+I87)*Periode!BD87/40)+(J87*Periode!BF87/40)+(G87*Periode!BE87/40) -> 666.24525 | L87: 40 | N87: =(L87*D87*2)+M87 -> 240 | O87: =((L87*2*D87)+M87)*0.25 -> 60 | P87: ='WK21'!N87*0.02 -> 6.4 | Q87: =K87+O87+P87 -> 732.64525 | R87: MaF8 VrE8 | S87: Westfries Museum 40km
B88: =Periode!B88 -> 0 | C88: =Periode!H88 -> 0
B89: =Periode!B89 -> 0 | C89: =Periode!H89 -> 0
B90: =Periode!B90 -> Aries Provence | C90: =Periode!G90 -> 0 | D90: 4 | E90: 32 | J90: 8 | K90: =(Periode!BB90*E90/40)+((F90+H90+I90)*Periode!BD90/40)+(J90*Periode!BF90/40)+(G90*Periode!BE90/40) -> 596.90691 | L90: 85 | N90: =(L90*D90*2)+M90 -> 680 | O90: =((L90*2*D90)+M90)*0.25 -> 170 | P90: ='WK21'!N90*0.02 -> 13.6 | Q90: =K90+O90+P90 -> 780.50691 | R90: MaF8 | S90: Het Groot Kwartier 85km
B91: =Periode!B91 -> 0 | C91: =Periode!H91 -> 0
B92: =Periode!B92 -> Gregory de Graaf | C92: =Periode!G92 -> 0 | D92: 4 | E92: 27.5 | J92: 8 | K92: =(Periode!BB92*E92/40)+((F92+H92+I92)*Periode!BD92/40)+(J92*Periode!BF92/40)+(G92*Periode!BE92/40) -> 651.2616 | Q92: =K92+O92+P92 -> 651.2616 | R92: 4 wekelijkse betaling | S92: Verklaring 34-LK-NH
B93: =Periode!B93 -> 0 | C93: =Periode!H93 -> 0 | R93: MaF8 WoE0,5 DoE1 VrE3
B94: =Periode!B94 -> 0 | C94: =Periode!H94 -> 0
B96: =Periode!B96 -> 0 | C96: =Periode!H96 -> 0
B97: =Periode!B97 -> 0 | C97: =Periode!H97 -> 0
B99: =Periode!B99 -> Eric de Jong | C99: =Periode!G99 -> 0 | J99: 8 | K99: =(Periode!BB99*E99/40)+((F99+H99+I99)*Periode!BD99/40)+(J99*Periode!BF99/40)+(G99*Periode!BE99/40) -> 181.50858 | L99: 47 | N99: =(L99*D99*2)+M99 -> 0 | O99: =((L99*2*D99)+M99)*0.23 -> 0 | Q99: =K99+O99+P99 -> 181.50858 | R99: MaF8 E32 | S99: LP4 47km
B103: =Periode!B103 -> 0 | C103: =Periode!H103 -> 0
B104: =Periode!B104 -> Michel van der Mark | C104: =Periode!G104 -> 32 (4wk) | D104: 4 | E104: 32 | J104: 8 | K104: =(Periode!BB104*E104/40)+((F104+H104+I104)*Periode!BD104/40)+(J104*Periode!BF104/40)+(G104*Periode!BE104/40) -> 700.58184 | Q104: =K104+O104+P104 -> 700.58184 | R104: MaF8 | S104: Bijtelling GVR-35-D
B105: =Periode!B105 -> 0 | C105: =Periode!H105 -> 0
B106: =Periode!B106 -> 0 | C106: =Periode!H106 -> 0
B108: =Periode!B108 -> 0 | C108: =Periode!H108 -> 0
B109: =Periode!B109 -> 0 | C109: =Periode!H109 -> 0
B110: =Periode!B110 -> Jan Harteveld | C110: =Periode!G110 -> 150 (4wk) | D110: 4 | E110: 31 | J110: 6.5 | K110: =(Periode!BB110*E110/40)+((F110+H110+I110)*Periode!BD110/40)+(J110*Periode!BF110/40)+(G110*Periode!BE110/40) -> 740.65854 | L110: 14 | N110: =(L110*D110*2)+M110 -> 112 | O110: =((L110*2*D110)+M110)*0.25 -> 28 | P110: ='WK21'!N110*0.02 -> 2.8 | Q110: =K110+O110+P110 -> 771.45854 | R110: MaF6,5 | S110: LP4 14km (€ 0,25 gaat op de fiets)
B111: =Periode!B111 -> 0 | C111: =Periode!H111 -> 0
B112: =Periode!B112 -> 0 | C112: =Periode!H112 -> 0
B114: =Periode!B114 -> 0 | C114: =Periode!H114 -> 0
B115: =Periode!B115 -> 0 | C115: =Periode!H115 -> 0 | R115: 4 wekelijkse betaling
B116: =Periode!B116 -> Asanty Raafenberg | C116: =Periode!G116 -> 0 | J116: 8 | K116: =(Periode!BB116*E116/40)+((F116+H116+I116)*Periode!BD116/40)+(J116*Periode!BF116/40)+(G116*Periode!BE116/40) -> 128.49804 | P116: -80.82 | Q116: =K116+O116+P116 -> 47.67804 | R116: E32 - Inhouding parkeerboete d.d. 23-05 € 80,82 | S116: Bijtelling 90-XB-JF
B117: =Periode!B117 -> 0 | C117: =Periode!G117 -> 0 | L117: 16
B118: =Periode!B118 -> 0 | C118: =Periode!H118 -> 0
B119: =Periode!B119 -> Patrick Serlier | C119: =Periode!G119 -> 32 (4wk) | D119: 4 | E119: 32 | J119: 8 | K119: =(Periode!BB119*E119/40)+((F119+H119+I119)*Periode!BD119/40)+(J119*Periode!BF119/40)+(G119*Periode!BE119/40) -> 670.93126 | Q119: =K119+O119+P119 -> 670.93126 | R119: MaF8 | S119: Verklaring VLT-24-V
B120: =Periode!B120 -> 0 | C120: =Periode!H120 -> 0
B121: =Periode!B121 -> 0 | C121: =Periode!H121 -> 0
B122: =Periode!B122 -> 0 | C122: =Periode!H122 -> 0
B123: =Periode!B123 -> Pieter van Houwelingen | C123: =Periode!G123 -> 32 (4wk) | D123: 3 | E123: 24 | H123: 6 | J123: 8 | K123: =(Periode!BB123*E123/40)+((F123+H123+I123)*Periode!BD123/40)+(J123*Periode!BF123/40)+(G123*Periode!BE123/40) -> 990.69988 | L123: 32.5 | N123: =(L123*D123*2)+M123 -> 195 | O123: =((L123*2*D123)+M123)*0.25 -> 48.75 | P123: ='WK21'!N123*0.02 -> 6.5 | Q123: =K123+O123+P123 -> 1045.9499 | R123: MaF8 VrRV6 | S123: Uitvoering 32,5km (ochtend 29,5 en middag 34,5)
B124: =Periode!B124 -> 0 | C124: =Periode!H124 -> 0
B125: =Periode!B125 -> John van der Wel | C125: =Periode!G125 -> 0 | D125: 4 | E125: 32 | J125: 8 | K125: =(Periode!BB125*E125/40)+((F125+H125+I125)*Periode!BD125/40)+(J125*Periode!BF125/40)+(G125*Periode!BE125/40) -> 642.45064 | P125: -65.06 | Q125: =K125+O125+P125 -> 577.39064 | R125: MaF8 | S125: Bijtelling 04-SP-VN
R126: Inhouden boetes deel 2
B127: =Periode!B127 -> 0 | C127: =Periode!H127 -> 0
B128: =Periode!B128 -> 0 | C128: =Periode!H128 -> 0
B129: =Periode!B129 -> Marcel Spruijt | C129: =Periode!G129 -> 32 (4wk) | D129: 4 | E129: 32 | J129: 8 | K129: =(Periode!BB129*E129/40)+((F129+H129+I129)*Periode!BD129/40)+(J129*Periode!BF129/40)+(G129*Periode!BE129/40) -> 739.4578 | P129: =-(2*10.57) -> -21.14 | Q129: =K129+O129+P129 -> 718.3178 | R129: MaF8 - Inhouding onbetaalde eTol 2 x € 10,57 | S129: Bijtelling 54-GVP-1
B130: =Periode!B130 -> 0 | C130: =Periode!H130 -> 0
B131: =Periode!B131 -> Michael Windhorst | C131: =Periode!G131 -> 0 | D131: 2 | E131: 16 | F131: =(2*6.8*0.9) -> 12.24 | J131: 8 | K131: =(Periode!BB131*E131/40)+((F131+H131+I131)*Periode!BD131/40)+(J131*Periode!BF131/40)+(G131*Periode!BE131/40) -> 557.72519 | Q131: =K131+O131+P131 -> 557.72519 | R131: MaF8 DiWoV6,8 | S131: Bijtelling V-695-HK
R132: Betalen Bewind:
B133: =Periode!B133 -> 0 | C133: =Periode!H133 -> 0 | R133: =K134 -> 420.43169
B134: =Periode!B134 -> Remco van Doorne | C134: =Periode!G134 -> 0 | D134: 3 | E134: 23 | J134: 8 | K134: =(Periode!BB134*E134/40)+((F134+H134+I134)*Periode!BD134/40)+(J134*Periode!BF134/40)+(G134*Periode!BE134/40) -> 420.43169 | P134: =(D134*Periode!AY134) -> 31.29 | Q134: =K134+O134+P134 -> 451.72169 | R134: Betalen Remco: | S134: Bijtelling 97-GFD-4
R135: =P134 -> 31.29 | S135: Onkosten betalen op rekening Remco: NL60 RABO 0102 064 024 t.n.v. R. van Doorne
...

Sheet WK23
B2: ALLEEN GEKLEURDE LETTERS EN CIJFERS INGEVEN!
P4: Overige
D5: Dagen | E5: Uren | F5: VAK | G5: ZIEK | H5: RV | I5: KV/C | J5: FD | L5: Enkel | M5: Totaal | O5: Bedrag km/ | P5: Extra | Q5: Totaal
C6: Contract | D6: ge- | E6: ge- | F6: Op- | G6: Op- | H6: Op- | I6: Door | J6: Door | K6: Netto | L6: Km woon- | M6: Km werk- | N6: Totaal | O6: brandstof | P6: Declaratie | Q6: Netto
B7: Werknemer | C7: Uren | D7: werkt | E7: werkt | F7: name | G7: name | H7: name | I7: bet. | J7: bet. | K7: bedrag | L7: werk pd | M7: werk pd | N7: Km | O7: bedrag | P7: vergoeding | Q7: Voorschot | R7: Opmerking | S7: Actueel project en KM's enkele reis
B8: =Periode!B8 -> Ruben Hellemons | C8: =Periode!G8 -> 124 (4wk) | D8: 5 | E8: 40 | K8: =(Periode!BB8*E8/40)+((F8+H8+I8)*Periode!BD8/40)+(J8*Periode!BF8/40)+(G8*Periode!BE8/40) -> 721.12 | Q8: =K8+O8+P8 -> 721.12 | S8: 1-VSV-81 met verklaring
B12: =Periode!B12 -> Andre Sintenie | C12: =Periode!G12 -> 32 (4wk) | D12: 4 | E12: 32 | K12: =(Periode!BB12*E12/40)+((F12+H12+I12)*Periode!BD12/40)+(J12*Periode!BF12/40)+(G12*Periode!BE12/40) -> 524.128 | Q12: =K12+O12+P12 -> 524.128 | R12: VrE8 | S12: VV-204-L met verklaring
B13: =Periode!B13 -> 0 | C13: =Periode!H13 -> 0 | Q13: =K13+O13+P13 -> 0
B15: =Periode!B15 -> Dennis Aarts | C15: =Periode!G15 -> 0 | I15: 32 | K15: =(Periode!BB15*E15/40)+((F15+H15+I15)*Periode!BD15/40)+(J15*Periode!BF15/40)+(G15*Periode!BE15/40) -> 548.34912 | Q15: =K15+O15+P15 -> 548.34912 | R15: 4 wekelijkse betaling | S15: 98-XH-DP Bijtelling
R16: 1 dag cursus 3 dagen leegloop
B17: =Periode!B17 -> Kay Sanders
B23: =Periode!B23 -> Frank Stouthart | C23: =Periode!G23 -> 32 (4wk) | D23: 5 | E23: 40 | K23: =(Periode!BB23*E23/40)+((F23+H23+I23)*Periode!BD23/40)+(J23*Periode!BF23/40)+(G23*Periode!BE23/40) -> 706.28 | L23: 34 | N23: =(L23*D23*2)+M23 -> 340 | O23: =((L23*2*D23)+M23)*0.28 -> 95.2 | Q23: =K23+O23+P23 -> 801.48 | S23: Vredespaleis Den Haag 34km, Lantaarnvenster R'dam 29km, Kralingseweg 179 R'dam 22 km (schrijft zelf 23km); Voorstraat Voorburg 38 km (schrijft 37km); Petrus Pauluskerk Leidschendam 31km (schrijft 33km); Kerkstraat Voorburg 31km (schrijft 33k); Koninginnegracht Den Haag 33km (schrijft 27 als hij stukje meerijdt); Tiber, den Haag 27km; Rokin 112, amsterdam 71 km (schrijft 70km); Concertgebouw 73km;
B26: =Periode!B26 -> Roy Rubeling | C26: =Periode!G26 -> 0 | D26: 4 | E26: 32 | K26: =(Periode!BB26*E26/40)+((F26+H26+I26)*Periode!BD26/40)+(J26*Periode!BF26/40)+(G26*Periode!BE26/40) -> 600 | L26: 61 | M26: =20*4 -> 80 | N26: =(L26*D26*2)+M26 -> 568 | O26: =((L26*2*D26)+M26)*0.28 -> 159.04 | Q26: =K26+O26+P26 -> 759.04 | R26: VrWAZO | S26: Akoestische maatregelen Schiphol 61km
T31: €
B33: =Periode!B33 -> Marco Govers | C33: =Periode!G33 -> 32 (4wk) | D33: 5 | E33: 40 | K33: =(Periode!BB33*E33/40)+((F33+H33+I33)*Periode!BD33/40)+(J33*Periode!BF33/40)+(G33*Periode!BE33/40) -> 775.21 | L33: 39 | N33: =(L33*D33*2)+M33 -> 390 | O33: =((L33*2*D33)+M33)*0.28 -> 109.2 | Q33: =K33+O33+P33 -> 884.41 | S33: Het Groot Kwartier 39km (schrijft 40)
B35: =Periode!B35 -> Onno de Vries | C35: =Periode!G35 -> 124 (4wk) | D35: 5 | E35: 40 | K35: =(Periode!BB35*E35/40)+((F35+H35+I35)*Periode!BD35/40)+(J35*Periode!BF35/40)+(G35*Periode!BE35/40) -> 633.355 | L35: 10 | N35: =(L35*D35*2)+M35 -> 100 | O35: =((L35*2*D35)+M35)*0.28 -> 28 | Q35: =K35+O35+P35 -> 661.355 | S35: LP4 10 km (schrijft 11km)
B39: =Periode!B39 -> Jan Levering | C39: =Periode!G39 -> 32 (4wk) | K39: =(Periode!BB39*E39/40)+((F39+H39+I39)*Periode!BD39/40)+(J39*Periode!BF39/40)+(G39*Periode!BE39/40) -> 0 | P39: 143.37 | Q39: =K39+O39+P39 -> 143.37 | R39: Aanvulling ZW € 143,37 | S39: Verklaring 1-VXV-55
B42: =Periode!B42 -> Alex van der Laan | C42: =Periode!G42 -> 32 (wk) | F42: 40 | K42: =(Periode!BB42*E42/40)+((F42+H42+I42)*Periode!BD42/40)+(J42*Periode!BF42/40)+(G42*Periode!BE42/40) -> 655.8255 | Q42: =K42+O42+P42 -> 655.8255 | R42: V40 | S42: Bijtelling 36-GNP-4
R43: VrE4 - Betalen Bewind:
R44: =K46 -> 414.45781 | S44: Bijtelling 78-RJ-BP
R45: Betalen Shafieq: | S45: Onkosten betalen op rekening Shafieq: NL65 ABNA 0128 6728 97
B46: =Periode!B46 -> Shafieq Asgarali | C46: =Periode!G46 -> 32 (4wk) | D46: 5 | E46: 33.5 | K46: =(Periode!BB46*E46/40)+((F46+H46+I46)*Periode!BD46/40)+(J46*Periode!BF46/40)+(G46*Periode!BE46/40) -> 414.45781 | P46: =(D46*Periode!AY46) -> 58.25 | Q46: =K46+O46+P46 -> 472.70781 | R46: =P46 -> 58.25 | S46: Loon betalen onder bewindvoering: NL93 ABNA 0128 6727 81
R47: Betalen loonbeslag:
B48: =Periode!B48 -> Sander van den Hoek | C48: =Periode!G48 -> 32 (wk) | D48: 5 | E48: 38 | K48: =(Periode!BB48*E48/40)+((F48+H48+I48)*Periode!BD48/40)+(J48*Periode!BF48/40)+(G48*Periode!BE48/40) -> 546.17875 | L48: 28 | N48: =(L48*D48*2)+M48 -> 280 | O48: =((L48*2*D48)+M48)*0.25 -> 70 | P48: =(D48*Periode!AY48) -> 56.8 | Q48: =K48+O48+P48+P49 -> 672.97875 | R48: =Q48-R50 -> 302.5058 | S48: Bellevoystraat Rotterdam 28km
R49: Betalen Sander: | S49: Loonbeslag Belastindienst NL89 INGB 000 000 4820
B50: =Periode!B50 -> 0 | C50: =Periode!G50 -> 0 | R50: ='WK22'!R48+O48+P48 -> 370.47295 | S50: t.n.v. S. van den Hoek 1735.64.781
R51: WoE2
B53: =Periode!B53 -> Ronald van Maanen | C53: =Periode!G53 -> 32 (4wk) | D53: 5 | E53: 40 | K53: =(Periode!BB53*E53/40)+((F53+H53+I53)*Periode!BD53/40)+(J53*Periode!BF53/40)+(G53*Periode!BE53/40) -> 733.25 | L53: 49 | N53: =(L53*D53*2)+M53 -> 490 | O53: =((L53*2*D53)+M53)*0.28 -> 137.2 | Q53: =K53+O53+P53 -> 870.45 | S53: Nijmegen gemiddelde heen/terug 49km
B54: =Periode!B75 -> 0 | C54: =Periode!H75 -> 0
B55: =Periode!B76 -> 0 | C55: =Periode!H76 -> 0
B57: =Periode!B57 -> Erik Visser | C57: =Periode!G57 -> 32 (4wk) | D57: 4 | E57: 32 | F57: 8 | K57: =(Periode!BB57*E57/40)+((F57+H57+I57)*Periode!BD57/40)+(J57*Periode!BF57/40)+(G57*Periode!BE57/40) -> 557.25992 | L57: 14 | M57: =32+48 -> 80 | N57: =(L57*D57*2)+M57 -> 192 | O57: =((L57*2*D57))*0.25+(M57*0.28) -> 50.4 | Q57: =K57+O57+P57 -> 607.65992 | R57: DiV8 - vraag erom via whatsapp | S57: Janssen de Jong OnderhoudPlus 14km
S58: wer-werk km € 0,28 (€ 0,32 naar de klant)
B59: =Periode!B59 -> 0 | C59: =Periode!G59 -> 0 | K59: =(Periode!BB59*E59/40)+((F59+H59+I59)*Periode!BD59/40)+(J59*Periode!BF59/40)+(G59*Periode!BE59/40) -> 0 | Q59: =K59+O59+P59 -> 0
R60: Betalen Bewind:
B61: =Periode!B61 -> 0 | R61: =K63 -> 463.94531
B62: =Periode!B62 -> 0 | R62: Betalen Youri:
B63: =Periode!B63 -> Youri Nouwens | C63: =Periode!G63 -> 32 (4wk) | E63: 37.5 | K63: =(Periode!BB63*E63/40)+((F63+H63+I63)*Periode!BD63/40)+(J63*Periode!BF63/40)+(G63*Periode!BE63/40) -> 463.94531 | P63: =(D63*Periode!AY63) -> 0 | Q63: =K63+O63+P63 -> 463.94531 | R63: =P63 -> 0 | S63: Bijtelling 54-GDT-8
B64: =Periode!B64 -> 0 | R64: Leegloop | S64: Loon overmaken naar Bewindvoerder: NL20 ABNA 0830 2655 89 - De Maas dienstverlening
S65: Onkosten overmaken naar Youri: NL21 INGB 0799 0333 59
B68: =Periode!B68 -> 0 | L68: 52 | N68: =(L68*D68*2)+M68 -> 0 | Q68: =K68+O68+P68 -> 0 | S68: Staalstraat Velsen-Noord 52km
B69: =Periode!B69 -> 0
B70: =Periode!B70 -> Marco Booij | C70: =Periode!G70 -> 32 (4wk) | K70: =(Periode!BB70*E70/40)+((F70+H70+I70)*Periode!BD70/40)+(J70*Periode!BF70/40)+(G70*Periode!BE70/40) -> 0 | P70: 171.65 | Q70: =K70+O70+P70 -> 171.65 | R70: Aanvulling Z € 171,65 netto | S70: Bijtelling 52-LN-BT
L72: 50 | N72: =(L72*D72*2)+M72 -> 0 | Q72: =K72+O72+P72 -> 0 | S72: Voorschoterweg 8a, 50 km
B73: 0
B74: =Periode!B74 -> Kevin Schuiling | C74: =Periode!G74 -> 32 (4wk) | D74: 5 | E74: 35.5 | K74: =(Periode!BB74*E74/40)+((F74+H74+I74)*Periode!BD74/40)+(J74*Periode!BF74/40)+(G74*Periode!BE74/40) -> 532.5 | L74: 58 | N74: =(L74*D74*2)+M74 -> 580 | O74: =((L74*2*D74)+M74)*0.28 -> 162.4 | Q74: =K74+O74+P74 -> 694.9 | R74: DoE4,5 | S74: Heilige Hartkerk Vught 58km, Stadsschouwburg Nijmegen 18km, Kaatsheuvel 83km, Huis73 56km
B75: =Periode!B75 -> 0
B76: =Periode!B76 -> 0
B77: =Periode!B77 -> Steven Lamers | C77: =Periode!G77 -> 32 (4wk) | D77: 5 | E77: 35.5 | K77: =(Periode!BB77*E77/40)+((F77+H77+I77)*Periode!BD77/40)+(J77*Periode!BF77/40)+(G77*Periode!BE77/40) -> 588.6965 | P77: -139 | Q77: =K77+O77+P77 -> 449.6965 | R77: inhouden CJIB d.d. 20-05-2026 | S77: Bijtelling 82-VZJ-2
B78: =Periode!B78 -> 0 | C78: =Periode!H78 -> 0 | R78: DoE4,5 | S78: Kredietbank Nederland NL48 BNGH 0285 0174 03 o.v.v. 6200559
B79: =Periode!B79 -> 0 | C79: =Periode!H79 -> 0
B80: =Periode!B80 -> Leo van Doorn | C80: =Periode!G80 -> 0 | D80: 5 | E80: 40 | K80: =(Periode!BB80*E80/40)+((F80+H80+I80)*Periode!BD80/40)+(J80*Periode!BF80/40)+(G80*Periode!BE80/40) -> 711.76 | L80: 21 | N80: =(L80*D80*2)+M80 -> 210 | O80: =((L80*2*D80)+M80)*0.28 -> 58.8 | Q80: =K80+O80+P80 -> 770.56 | S80: Nijpelsplantsoen 21km
B81: =Periode!B81 -> 0 | C81: =Periode!H81 -> 0
B82: =Periode!B82 -> 0 | C82: =Periode!H82 -> 0
B83: =Periode!B83 -> Tobin van de Kuil | C83: =Periode!G83 -> 0 | K83: =(Periode!BB83*E83/40)+((F83+H83+I83)*Periode!BD83/40)+(J83*Periode!BF83/40)+(G83*Periode!BE83/40) -> 0 | L83: 0 | N83: =(L83*D83*2)+M83 -> 0 | O83: =((L83*2*D83)+M83)*0.28 -> 0 | Q83: =K83+O83+P83 -> 0 | R83: E40 | S83: Woonplus Schiedam
C84: =Periode!H84 -> 0
B85: =Periode!B85 -> 0 | C85: =Periode!H85 -> 0
B86: =Periode!B86 -> 0 | C86: =Periode!H86 -> 0
B87: =Periode!B87 -> Carlo Peetoom | C87: =Periode!G87 -> 32 (4wk) | D87: 4 | E87: 32 | K87: =(Periode!BB87*E87/40)+((F87+H87+I87)*Periode!BD87/40)+(J87*Periode!BF87/40)+(G87*Periode!BE87/40) -> 672.54 | L87: 40 | N87: =(L87*D87*2)+M87 -> 320 | O87: =((L87*2*D87)+M87)*0.25 -> 80 | P87: 106.55 | Q87: =K87+O87+P87 -> 859.09 | R87: VrE8 | S87: Westfries Museum 40km
B88: =Periode!B88 -> 0 | C88: =Periode!H88 -> 0 | R88: €106,55 parkeervergunning
B89: =Periode!B89 -> 0 | C89: =Periode!H89 -> 0
B90: =Periode!B90 -> Aries Provence | C90: =Periode!G90 -> 0 | D90: 5 | E90: 40 | K90: =(Periode!BB90*E90/40)+((F90+H90+I90)*Periode!BD90/40)+(J90*Periode!BF90/40)+(G90*Periode!BE90/40) -> 600.345 | L90: 85 | N90: =(L90*D90*2)+M90 -> 850 | O90: =((L90*2*D90)+M90)*0.25 -> 212.5 | Q90: =K90+O90+P90 -> 812.845 | S90: Het Groot Kwartier 85km
B91: =Periode!B91 -> 0 | C91: =Periode!H91 -> 0
B92: =Periode!B92 -> Gregory de Graaf | C92: =Periode!G92 -> 0 | D92: 5 | E92: 37 | K92: =(Periode!BB92*E92/40)+((F92+H92+I92)*Periode!BD92/40)+(J92*Periode!BF92/40)+(G92*Periode!BE92/40) -> 682.65 | Q92: =K92+O92+P92 -> 682.65 | R92: 4 wekelijkse betaling | S92: Verklaring 34-LK-NH
B93: =Periode!B93 -> 0 | C93: =Periode!H93 -> 0 | R93: VrE3
B94: =Periode!B94 -> 0 | C94: =Periode!H94 -> 0
B96: =Periode!B96 -> 0 | C96: =Periode!H96 -> 0
B97: =Periode!B97 -> 0 | C97: =Periode!H97 -> 0
B99: =Periode!B99 -> Eric de Jong | C99: =Periode!G99 -> 0 | D99: 5 | E99: 40 | K99: =(Periode!BB99*E99/40)+((F99+H99+I99)*Periode!BD99/40)+(J99*Periode!BF99/40)+(G99*Periode!BE99/40) -> 928.01 | L99: 47 | N99: =(L99*D99*2)+M99 -> 470 | O99: =((L99*2*D99)+M99)*0.23 -> 108.1 | Q99: =K99+O99+P99 -> 1036.11 | R99: Parkeerkosten € 45,00 via FA | S99: LP4 47km
B103: =Periode!B103 -> 0 | C103: =Periode!H103 -> 0
B104: =Periode!B104 -> Michel van der Mark | C104: =Periode!G104 -> 32 (4wk) | D104: 5 | E104: 40 | K104: =(Periode!BB104*E104/40)+((F104+H104+I104)*Periode!BD104/40)+(J104*Periode!BF104/40)+(G104*Periode!BE104/40) -> 705.18 | Q104: =K104+O104+P104 -> 705.18 | S104: Bijtelling GVR-35-D
B105: =Periode!B105 -> 0 | C105: =Periode!H105 -> 0
B106: =Periode!B106 -> 0 | C106: =Periode!H106 -> 0
B108: =Periode!B108 -> 0 | C108: =Periode!H108 -> 0
B109: =Periode!B109 -> 0 | C109: =Periode!H109 -> 0
B110: =Periode!B110 -> Jan Harteveld | C110: =Periode!G110 -> 150 (4wk) | D110: 5 | E110: 37.5 | K110: =(Periode!BB110*E110/40)+((F110+H110+I110)*Periode!BD110/40)+(J110*Periode!BF110/40)+(G110*Periode!BE110/40) -> 743.76562 | L110: 14 | N110: =(L110*D110*2)+M110 -> 140 | O110: =((L110*2*D110)+M110)*0.25 -> 35 | Q110: =K110+O110+P110 -> 778.76562 | R110: MaE1,5 DiE1 | S110: LP4 14km (€ 0,25 gaat op de fiets)
B111: =Periode!B111 -> 0 | C111: =Periode!H111 -> 0
B112: =Periode!B112 -> 0 | C112: =Periode!H112 -> 0
B114: =Periode!B114 -> 0 | C114: =Periode!H114 -> 0
B115: =Periode!B115 -> 0 | C115: =Periode!H115 -> 0
B116: =Periode!B116 -> Asanty Raafenberg | C116: =Periode!G116 -> 0 | D116: 5 | E116: 40 | K116: =(Periode!BB116*E116/40)+((F116+H116+I116)*Periode!BD116/40)+(J116*Periode!BF116/40)+(G116*Periode!BE116/40) -> 660.28 | Q116: =K116+O116+P116 -> 660.28 | R116: 4 wekelijkse betaling | S116: Bijtelling 90-XB-JF
L117: 16
B118: =Periode!B118 -> 0 | C118: =Periode!H118 -> 0
B119: =Periode!B119 -> Patrick Serlier | C119: =Periode!G119 -> 32 (4wk) | D119: 5 | E119: 40 | K119: =(Periode!BB119*E119/40)+((F119+H119+I119)*Periode!BD119/40)+(J119*Periode!BF119/40)+(G119*Periode!BE119/40) -> 675.47 | Q119: =K119+O119+P119 -> 675.47 | S119: Verklaring VLT-24-V
B120: =Periode!B120 -> 0 | C120: =Periode!H120 -> 0
B121: =Periode!B121 -> 0 | C121: =Periode!H121 -> 0
B122: =Periode!B122 -> 0 | C122: =Periode!H122 -> 0
B123: =Periode!B123 -> Pieter van Houwelingen | C123: =Periode!G123 -> 32 (4wk) | D123: 5 | E123: 38 | K123: =(Periode!BB123*E123/40)+((F123+H123+I123)*Periode!BD123/40)+(J123*Periode!BF123/40)+(G123*Periode!BE123/40) -> 998.29325 | L123: 32.5 | N123: =(L123*D123*2)+M123 -> 325 | O123: =((L123*2*D123)+M123)*0.25 -> 81.25 | Q123: =K123+O123+P123 -> 1079.5433 | R123: VrE2 | S123: Uitvoering 32,5km (ochtend 29,5 en middag 34,5)
B124: =Periode!B124 -> 0 | C124: =Periode!H124 -> 0
B125: =Periode!B125 -> John van der Wel | C125: =Periode!G125 -> 0 | D125: 5 | E125: 37.5 | K125: =(Periode!BB125*E125/40)+((F125+H125+I125)*Periode!BD125/40)+(J125*Periode!BF125/40)+(G125*Periode!BE125/40) -> 605.60625 | P125: -65.06 | Q125: =K125+O125+P125 -> 540.54625 | R125: WoE2,5 | S125: Bijtelling 04-SP-VN
R126: Inhouden boetes deel 3
B127: =Periode!B127 -> 0 | C127: =Periode!H127 -> 0
B128: =Periode!B128 -> 0 | C128: =Periode!H128 -> 0
B129: =Periode!B129 -> Marcel Spruijt | C129: =Periode!G129 -> 32 (4wk) | D129: 5 | E129: 40 | K129: =(Periode!BB129*E129/40)+((F129+H129+I129)*Periode!BD129/40)+(J129*Periode!BF129/40)+(G129*Periode!BE129/40) -> 751.94 | Q129: =K129+O129+P129 -> 751.94 | S129: Bijtelling 54-GVP-1
B130: =Periode!B130 -> 0 | C130: =Periode!H130 -> 0
B131: =Periode!B131 -> Michael Windhorst | C131: =Periode!G131 -> 0 | D131: 5 | E131: 40 | K131: =(Periode!BB131*E131/40)+((F131+H131+I131)*Periode!BD131/40)+(J131*Periode!BF131/40)+(G131*Periode!BE131/40) -> 628 | Q131: =K131+O131+P131 -> 628 | S131: Bijtelling V-695-HK
R132: Betalen Bewind:
B133: =Periode!B133 -> 0 | C133: =Periode!H133 -> 0 | R133: =K134 -> 542.4925
B134: =Periode!B134 -> Remco van Doorne | C134: =Periode!G134 -> 0 | D134: 5 | E134: 40 | K134: =(Periode!BB134*E134/40)+((F134+H134+I134)*Periode!BD134/40)+(J134*Periode!BF134/40)+(G134*Periode!BE134/40) -> 542.4925 | P134: =(D134*Periode!AY134) -> 52.15 | Q134: =K134+O134+P134 -> 594.6425 | R134: Betalen Remco: | S134: Bijtelling 97-GFD-4
R135: =P134 -> 52.15 | S135: Onkosten betalen op rekening Remco: NL60 RABO 0102 064 024 t.n.v. R. van Doorne
B136: =Periode!B136 -> 0 | C136: =Periode!H136 -> 0 | S136: Loon betalen onder bewindvoering: NL45 ABNA 0877 629 366 t.n.v. R. van Doorne e.o.
...

Sheet WK24
B2: ALLEEN GEKLEURDE LETTERS EN CIJFERS INGEVEN!
P4: Overige
D5: Dagen | E5: Uren | F5: VAK | G5: ZIEK | H5: RV | I5: KV/C | J5: FD | L5: Enkel | M5: Totaal | O5: Bedrag km/ | P5: Extra | Q5: Totaal
C6: Contract | D6: ge- | E6: ge- | F6: Op- | G6: Op- | H6: Op- | I6: Door | J6: Door | K6: Netto | L6: Km woon- | M6: Km werk- | N6: Totaal | O6: brandstof | P6: Declaratie | Q6: Netto
B7: Werknemer | C7: Uren | D7: werkt | E7: werkt | F7: name | G7: name | H7: name | I7: bet. | J7: bet. | K7: bedrag | L7: werk pd | M7: werk pd | N7: Km | O7: bedrag | P7: vergoeding | Q7: Voorschot | S7: Actueel project en KM's enkele reis
B8: =Periode!B8 -> Ruben Hellemons | C8: =Periode!G8 -> 124 (4wk) | D8: 5 | E8: 40 | K8: =(Periode!BB8*E8/40)+((F8+H8+I8)*Periode!BD8/40)+(J8*Periode!BF8/40)+(G8*Periode!BE8/40) -> 721.12 | Q8: =K8+O8+P8 -> 721.12 | S8: 1-VSV-81 met verklaring
B12: =Periode!B12 -> Andre Sintenie | C12: =Periode!G12 -> 32 (4wk) | D12: 4 | E12: 32 | K12: =(Periode!BB12*E12/40)+((F12+H12+I12)*Periode!BD12/40)+(J12*Periode!BF12/40)+(G12*Periode!BE12/40) -> 524.128 | Q12: =K12+O12+P12 -> 524.128 | R12: VrE8 | S12: VV-204-L met verklaring
B13: =Periode!B13 -> 0 | C13: =Periode!H13 -> 0 | K13: =(Periode!BB13*E13/40)+((F13+G13+H13+I13)*Periode!BD13/40)+(J13*Periode!BF13/40) -> 0 | Q13: =K13+O13+P13 -> 0
P14: Tabelvoordeel: | Q14: 121.76 | R14: 4 wekelijkse betaling
B15: =Periode!B15 -> Dennis Aarts | C15: =Periode!G15 -> 0 | D15: 4 | E15: 32 | K15: =(Periode!BB15*E15/40)+((F15+H15+I15)*Periode!BD15/40)+(J15*Periode!BF15/40)+(G15*Periode!BE15/40) -> 562.928 | Q15: =(K15+O15+P15)+'WK23'!Q15+'WK22'!Q15+'WK21'!Q15 -> 1248.3644 | R15: WoE8 | S15: 98-XH-DP Bijtelling
R16: Dagloon € 114,94 bruto
B17: =Periode!B17 -> Kay Sanders | C17: =Periode!G17 -> 0 | K17: =(Periode!BB17*E17/40)+((I17)*Periode!BD17/40)+(J17*Periode!BF17/40)+(G17*Periode!BE17/40) -> 0 | L17: 69 | N17: =(L17*D17*2)+M17 -> 0 | P17: 296.04 | Q17: =K17+O17+P17 -> 296.04 | R17: Ziekte aanvulling 20% | S17: De Munt 69km
R18: Netto € 296,04
B23: =Periode!B23 -> Frank Stouthart | C23: =Periode!G23 -> 32 (4wk) | D23: 5 | E23: 39 | K23: =(Periode!BB23*E23/40)+((F23+H23+I23)*Periode!BD23/40)+(J23*Periode!BF23/40)+(G23*Periode!BE23/40) -> 688.623 | L23: 34 | M23: =-340+(6*34)+(4*36) -> 8 | N23: =(L23*D23*2)+M23 -> 348 | O23: =((L23*2*D23)+M23)*0.28 -> 97.44 | Q23: =K23+O23+P23 -> 786.063 | R23: DoE1 | S23: Beelden aan Zee 36km, Vredespaleis Den Haag 34km, Lantaarnvenster R'dam 29km, Kralingseweg 179 R'dam 22 km (schrijft zelf 23km); Voorstraat Voorburg 38 km (schrijft 37km); Petrus Pauluskerk Leidschendam 31km (schrijft 33km); Kerkstraat Voorburg 31km (schrijft 33k); Koninginnegracht Den Haag 33km (schrijft 27 als hij stukje meerijdt); Tiber, den Haag 27km; Rokin 112, amsterdam 71 km (schrijft 70km); Concertgebouw 73km;
B26: =Periode!B26 -> Roy Rubeling | C26: =Periode!G26 -> 0 | D26: 4 | E26: 32 | K26: =(Periode!BB26*E26/40)+((F26+H26+I26)*Periode!BD26/40)+(J26*Periode!BF26/40)+(G26*Periode!BE26/40) -> 600 | L26: 61 | M26: 80 | N26: =(L26*D26*2)+M26 -> 568 | O26: =((L26*2*D26)+M26)*0.28 -> 159.04 | P26: 283.62 | Q26: =K26+O26+P26 -> 1042.66 | R26: WAZO nog nabetalen 4 * 8 uur | S26: Akoestische maatregelen Schiphol 61km
R27: € 283,62 WAZO
T31: €
B33: =Periode!B33 -> Marco Govers | C33: =Periode!G33 -> 32 (4wk) | D33: 5 | E33: 38.5 | I33: 1.5 | K33: =(Periode!BB33*E33/40)+((F33+H33+I33)*Periode!BD33/40)+(J33*Periode!BF33/40)+(G33*Periode!BE33/40) -> 774.49978 | L33: 39 | N33: =(L33*D33*2)+M33 -> 390 | O33: =((L33*2*D33)+M33)*0.28 -> 109.2 | Q33: =K33+O33+P33 -> 883.69978 | R33: DoKV1,5 | S33: Het Groot Kwartier 39km (schrijft 40)
P34: Tabelvoordeel: | Q34: 13.59
B35: =Periode!B35 -> Onno de Vries | C35: =Periode!G35 -> 124 (4wk) | D35: 5 | E35: 40 | K35: =(Periode!BB35*E35/40)+((F35+H35+I35)*Periode!BD35/40)+(J35*Periode!BF35/40)+(G35*Periode!BE35/40) -> 633.355 | L35: 10 | N35: =(L35*D35*2)+M35 -> 100 | O35: =((L35*2*D35)+M35)*0.28 -> 28 | Q35: =K35+O35+P35 -> 661.355 | S35: LP4 10 km (schrijft 11km)
B39: =Periode!B39 -> Jan Levering | C39: =Periode!G39 -> 32 (4wk) | K39: =(Periode!BB39*E39/40)+((F39+H39+I39)*Periode!BD39/40)+(J39*Periode!BF39/40)+(G39*Periode!BE39/40) -> 0 | P39: 143.37 | Q39: =K39+O39+P39 -> 143.37 | R39: Aanvulling ZW € 143,37 | S39: Verklaring 1-VXV-55
B42: =Periode!B42 -> Alex van der Laan | C42: =Periode!G42 -> 32 (wk) | D42: 2 | E42: 16 | H42: 24 | K42: =(Periode!BB42*E42/40)+((F42+H42+I42)*Periode!BD42/40)+(J42*Periode!BF42/40)+(G42*Periode!BE42/40) -> 662.9953 | Q42: =K42+O42+P42 -> 662.9953 | R42: Ma t/m Wo V24 | S42: Bijtelling 36-GNP-4
R43: Betalen Bewind:
R44: =K46+Q45 -> 595.12531 | S44: Bijtelling 78-RJ-BP
P45: Tabelvoordeel: | Q45: 131.18 | R45: Betalen Shafieq: | S45: Onkosten betalen op rekening Shafieq: NL65 ABNA 0128 6728 97
B46: =Periode!B46 -> Shafieq Asgarali | C46: =Periode!G46 -> 32 (4wk) | D46: 5 | E46: 37.5 | K46: =(Periode!BB46*E46/40)+((F46+H46+I46)*Periode!BD46/40)+(J46*Periode!BF46/40)+(G46*Periode!BE46/40) -> 463.94531 | P46: =(D46*Periode!AY46) -> 58.25 | Q46: =K46+O46+P46 -> 522.19531 | R46: =P46 -> 58.25 | S46: Loon betalen onder bewindvoering: NL93 ABNA 0128 6727 81
P47: Tabelvoordeel: | Q47: 153.62 | R47: Betalen loonbeslag:
B48: =Periode!B48 -> Sander van den Hoek | C48: =Periode!G48 -> 32 (wk) | D48: 5 | E48: 38 | K48: =(Periode!BB48*E48/40)+((F48+H48+I48)*Periode!BD48/40)+(J48*Periode!BF48/40)+(G48*Periode!BE48/40) -> 546.17875 | L48: 28 | N48: =(L48*D48*2)+M48 -> 280 | O48: =((L48*2*D48)+M48)*0.25 -> 70 | P48: =(D48*Periode!AY48) -> 56.8 | Q48: =K48+O48+P48+P49 -> 672.97875 | R48: =K48+Q47 -> 699.79875 | S48: Bellevoystraat Rotterdam 28km
R49: Betalen Sander: | S49: Loonbeslag Belastindienst NL89 INGB 000 000 4820
B50: =Periode!B50 -> 0 | C50: =Periode!G50 -> 0 | R50: =O48+P48 -> 126.8 | S50: t.n.v. S. van den Hoek 1735.64.781
R51: WoE2
B53: =Periode!B53 -> Ronald van Maanen | C53: =Periode!G53 -> 32 (4wk) | D53: 5 | E53: 39.5 | K53: =(Periode!BB53*E53/40)+((F53+H53+I53)*Periode!BD53/40)+(J53*Periode!BF53/40)+(G53*Periode!BE53/40) -> 724.08438 | L53: 49 | N53: =(L53*D53*2)+M53 -> 490 | O53: =((L53*2*D53)+M53)*0.28 -> 137.2 | Q53: =K53+O53+P53 -> 861.28438 | R53: DoE0,5 | S53: Nijmegen gemiddelde heen/terug 49km
B54: =Periode!B75 -> 0 | C54: =Periode!H75 -> 0
B55: =Periode!B76 -> 0 | C55: =Periode!H76 -> 0
P56: Tabelvoordeel: | Q56: 60.63
B57: =Periode!B57 -> Erik Visser | C57: =Periode!G57 -> 32 (4wk) | D57: 4 | E57: 29 | F57: 8 | K57: =(Periode!BB57*E57/40)+((F57+H57+I57)*Periode!BD57/40)+(J57*Periode!BF57/40)+(G57*Periode!BE57/40) -> 515.22692 | L57: 14 | M57: =74+62+32 -> 168 | N57: =(L57*D57*2)+M57 -> 280 | O57: =((L57*2*D57))*0.25+(M57*0.28) -> 75.04 | P57: 60.8 | Q57: =K57+O57+P57 -> 651.06692 | R57: DiE3 WoV8 | S57: Janssen de Jong OnderhoudPlus 14km
R58: Erik heeft erom gevraagd via whatsapp | S58: wer-werk km € 0,28 (€ 0,32 naar de klant)
R59: Nabetaling km P01 t/m P05 € 60,80
R60: Betalen Bewind:
B61: =Periode!B61 -> 0 | R61: =K63+Q62 -> 587.76531
B62: =Periode!B62 -> 0 | P62: Tabelvoordeel: | Q62: 123.82 | R62: Betalen Youri:
B63: =Periode!B63 -> Youri Nouwens | C63: =Periode!G63 -> 32 (4wk) | E63: 37.5 | K63: =(Periode!BB63*E63/40)+((F63+H63+I63)*Periode!BD63/40)+(J63*Periode!BF63/40)+(G63*Periode!BE63/40) -> 463.94531 | P63: =(D63*Periode!AY63) -> 0 | Q63: =K63+O63+P63 -> 463.94531 | R63: =P63 -> 0 | S63: Bijtelling 54-GDT-8
B64: =Periode!B64 -> 0 | R64: Leegloop | S64: Loon overmaken naar Bewindvoerder: NL20 ABNA 0830 2655 89 - De Maas dienstverlening
S65: Onkosten overmaken naar Youri: NL21 INGB 0799 0333 59
B68: =Periode!B68 -> 0 | K68: =(Periode!BB68*E68/40)+((F68+G68+H68+I68)*Periode!BD68/40)+(J68*Periode!BF68/40) -> 0 | L68: 52 | N68: =(L68*D68*2)+M68 -> 0 | Q68: =K68+O68+P68 -> 0
B69: =Periode!B69 -> 0
B70: =Periode!B70 -> Marco Booij | C70: =Periode!G70 -> 32 (4wk) | K70: =(Periode!BB70*E70/40)+((F70+H70+I70)*Periode!BD70/40)+(J70*Periode!BF70/40)+(G70*Periode!BE70/40) -> 0 | P70: 171.65 | Q70: =K70+O70+P70 -> 171.65 | R70: Aanvulling Z € 171,65 netto | S70: Bijtelling 52-LN-BT
K72: =(Periode!BB72*E72/40)+((F72+G72+H72+I72)*Periode!BD72/40)+(J72*Periode!BF72/40) -> 0 | L72: 50 | N72: =(L72*D72*2)+M72 -> 0 | Q72: =K72+O72+P72 -> 0 | S72: Voorschoterweg 8a, 50 km
B73: 0
B74: =Periode!B74 -> Kevin Schuiling | C74: =Periode!G74 -> 32 (4wk) | D74: 5 | E74: 40 | K74: =(Periode!BB74*E74/40)+((F74+H74+I74)*Periode!BD74/40)+(J74*Periode!BF74/40)+(G74*Periode!BE74/40) -> 600 | L74: 58 | N74: =(L74*D74*2)+M74 -> 580 | O74: =((L74*2*D74)+M74)*0.28 -> 162.4 | Q74: =K74+O74+P74 -> 762.4 | S74: Heilige Hartkerk Vught 58km, Stadsschouwburg Nijmegen 18km, Kaatsheuvel 83km, Huis73 56km
B75: =Periode!B75 -> 0
B76: =Periode!B76 -> 0 | P76: Tabelvoordeel: | Q76: 60.43
B77: =Periode!B77 -> Steven Lamers | C77: =Periode!G77 -> 32 (4wk) | D77: 5 | E77: 40 | K77: =(Periode!BB77*E77/40)+((F77+H77+I77)*Periode!BD77/40)+(J77*Periode!BF77/40)+(G77*Periode!BE77/40) -> 663.32 | P77: =-2*139 -> -278 | Q77: =(K77+O77+P77) -> 385.32 | R77: Inhouding CJIB d.d. 21-05-2026 + 22-05-2026 | S77: Bijtelling 82-VZJ-2
B78: =Periode!B78 -> 0 | C78: =Periode!H78 -> 0 | S78: Kredietbank Nederland NL48 BNGH 0285 0174 03 o.v.v. 6200559
B79: =Periode!B79 -> 0 | C79: =Periode!H79 -> 0
B80: =Periode!B80 -> Leo van Doorn | C80: =Periode!G80 -> 0 | D80: 5 | E80: 40 | K80: =(Periode!BB80*E80/40)+((F80+H80+I80)*Periode!BD80/40)+(J80*Periode!BF80/40)+(G80*Periode!BE80/40) -> 711.76 | L80: 21 | N80: =(L80*D80*2)+M80 -> 210 | O80: =((L80*2*D80)+M80)*0.28 -> 58.8 | Q80: =K80+O80+P80 -> 770.56 | S80: Nijpelsplantsoen 21km
B81: =Periode!B81 -> 0 | C81: =Periode!H81 -> 0
B82: =Periode!B82 -> 0 | C82: =Periode!H82 -> 0 | P82: Tabelvoordeel: | Q82: 46.36
B83: =Periode!B83 -> Tobin van de Kuil | C83: =Periode!G83 -> 0 | D83: 4 | E83: 31 | F83: 7.5 | K83: =(Periode!BB83*E83/40)+((F83+H83+I83)*Periode!BD83/40)+(J83*Periode!BF83/40)+(G83*Periode!BE83/40) -> 720.16513 | L83: 0 | M83: 364 | N83: =(L83*D83*2)+M83 -> 364 | O83: =((L83*2*D83)+M83)*0.28 -> 101.92 | Q83: =K83+O83+P83 -> 822.08513 | R83: MaE1 WoV7,5E0,5 | S83: Woonplus Schiedam
C84: =Periode!H84 -> 0
B85: =Periode!B85 -> 0 | C85: =Periode!H85 -> 0
B86: =Periode!B86 -> 0 | C86: =Periode!H86 -> 0
B87: =Periode!B87 -> Carlo Peetoom | C87: =Periode!G87 -> 32 (4wk) | D87: 4 | E87: 32 | K87: =(Periode!BB87*E87/40)+((F87+H87+I87)*Periode!BD87/40)+(J87*Periode!BF87/40)+(G87*Periode!BE87/40) -> 672.54 | L87: 40 | N87: =(L87*D87*2)+M87 -> 320 | O87: =((L87*2*D87)+M87)*0.25 -> 80 | Q87: =K87+O87+P87 -> 752.54 | R87: VrE8 | S87: Westfries Museum 40km
B88: =Periode!B88 -> 0 | C88: =Periode!H88 -> 0
B89: =Periode!B89 -> 0 | C89: =Periode!H89 -> 0
B90: =Periode!B90 -> Aries Provence | C90: =Periode!G90 -> 0 | D90: 5 | E90: 40 | K90: =(Periode!BB90*E90/40)+((F90+H90+I90)*Periode!BD90/40)+(J90*Periode!BF90/40)+(G90*Periode!BE90/40) -> 600.345 | L90: 85 | N90: =(L90*D90*2)+M90 -> 850 | O90: =((L90*2*D90)+M90)*0.25 -> 212.5 | Q90: =K90+O90+P90 -> 812.845 | S90: Het Groot Kwartier 85km
B91: =Periode!B91 -> 0 | C91: =Periode!H91 -> 0
B92: =Periode!B92 -> Gregory de Graaf | C92: =Periode!G92 -> 0 | D92: 4 | E92: 29 | I92: 4 | K92: =(Periode!BB92*E92/40)+((F92+H92+I92)*Periode!BD92/40)+(J92*Periode!BF92/40)+(G92*Periode!BE92/40) -> 606.9933 | Q92: =(K92+O92+P92)+'WK21'!Q92+'WK22'!Q92+'WK23'!Q92 -> 2586.6549 | R92: 4 wekelijkse betaling | S92: Verklaring 34-LK-NH
B93: =Periode!B93 -> 0 | C93: =Periode!H93 -> 0 | R93: WoKV4 VrE3
B94: =Periode!B94 -> 0 | C94: =Periode!H94 -> 0 | R94: conform afspraak Remco = ziekenhuisbezoek meerdere afspraken
B96: =Periode!B96 -> 0 | C96: =Periode!H96 -> 0
B97: =Periode!B97 -> 0 | C97: =Periode!H97 -> 0
B99: =Periode!B99 -> Eric de Jong | C99: =Periode!G99 -> 0 | D99: 5 | E99: 36.5 | K99: =(Periode!BB99*E99/40)+((F99+H99+I99)*Periode!BD99/40)+(J99*Periode!BF99/40)+(G99*Periode!BE99/40) -> 846.80912 | L99: 47 | N99: =(L99*D99*2)+M99 -> 470 | O99: =((L99*2*D99)+M99)*0.23 -> 108.1 | Q99: =K99+O99+P99 -> 954.90913 | R99: DiE3,5 | S99: LP4 47km
B103: =Periode!B103 -> 0 | C103: =Periode!H103 -> 0
B104: =Periode!B104 -> Michel van der Mark | C104: =Periode!G104 -> 32 (4wk) | D104: 5 | E104: 40 | K104: =(Periode!BB104*E104/40)+((F104+H104+I104)*Periode!BD104/40)+(J104*Periode!BF104/40)+(G104*Periode!BE104/40) -> 705.18 | Q104: =K104+O104+P104 -> 705.18 | S104: Bijtelling GVR-35-D
B105: =Periode!B105 -> 0 | C105: =Periode!H105 -> 0
B106: =Periode!B106 -> 0 | C106: =Periode!H106 -> 0
B108: =Periode!B108 -> 0 | C108: =Periode!H108 -> 0
B109: =Periode!B109 -> 0 | C109: =Periode!H109 -> 0
B110: =Periode!B110 -> Jan Harteveld | C110: =Periode!G110 -> 150 (4wk) | D110: 5 | E110: 37.5 | K110: =(Periode!BB110*E110/40)+((F110+H110+I110)*Periode!BD110/40)+(J110*Periode!BF110/40)+(G110*Periode!BE110/40) -> 743.76562 | L110: 14 | N110: =(L110*D110*2)+M110 -> 140 | O110: =((L110*2*D110)+M110)*0.25 -> 35 | Q110: =K110+O110+P110 -> 778.76562 | R110: MaE1,5 DiE1 | S110: LP4 14km (€ 0,25 gaat op de fiets)
B111: =Periode!B111 -> 0 | C111: =Periode!H111 -> 0
B112: =Periode!B112 -> 0 | C112: =Periode!H112 -> 0
B114: =Periode!B114 -> 0 | C114: =Periode!H114 -> 0
B115: =Periode!B115 -> 0 | C115: =Periode!H115 -> 0
B116: =Periode!B116 -> Asanty Raafenberg | C116: =Periode!G116 -> 0 | D116: 5 | E116: 40 | K116: =(Periode!BB116*E116/40)+((F116+H116+I116)*Periode!BD116/40)+(J116*Periode!BF116/40)+(G116*Periode!BE116/40) -> 660.28 | Q116: =(K116+O116+P116)+'WK21'!Q116+'WK22'!Q116+'WK23'!Q116 -> 2028.518 | R116: 4 wekelijkse betaling | S116: Bijtelling 90-XB-JF
B117: =Periode!B117 -> 0 | C117: =Periode!G117 -> 0 | L117: 16 | N117: =(L117*D117*2)+M117 -> 0
B118: =Periode!B118 -> 0 | C118: =Periode!H118 -> 0
B119: =Periode!B119 -> Patrick Serlier | C119: =Periode!G119 -> 32 (4wk) | D119: 5 | E119: 39 | K119: =(Periode!BB119*E119/40)+((F119+H119+I119)*Periode!BD119/40)+(J119*Periode!BF119/40)+(G119*Periode!BE119/40) -> 658.58325 | Q119: =K119+O119+P119 -> 658.58325 | R119: VrE1 | S119: Verklaring VLT-24-V
B120: =Periode!B120 -> 0 | C120: =Periode!H120 -> 0
B121: =Periode!B121 -> 0 | C121: =Periode!H121 -> 0
B122: =Periode!B122 -> 0 | C122: =Periode!H122 -> 0
B123: =Periode!B123 -> Pieter van Houwelingen | C123: =Periode!G123 -> 32 (4wk) | D123: 5 | E123: 38 | K123: =(Periode!BB123*E123/40)+((F123+H123+I123)*Periode!BD123/40)+(J123*Periode!BF123/40)+(G123*Periode!BE123/40) -> 998.29325 | L123: 32.5 | N123: =(L123*D123*2)+M123 -> 325 | O123: =((L123*2*D123)+M123)*0.25 -> 81.25 | Q123: =K123+O123+P123 -> 1079.5433 | R123: VrE2 | S123: Uitvoering 32,5km (ochtend 29,5 en middag 34,5)
B124: =Periode!B124 -> 0 | C124: =Periode!H124 -> 0
B125: =Periode!B125 -> John van der Wel | C125: =Periode!G125 -> 0 | D125: 5 | E125: 40 | K125: =(Periode!BB125*E125/40)+((F125+H125+I125)*Periode!BD125/40)+(J125*Periode!BF125/40)+(G125*Periode!BE125/40) -> 645.98 | P125: -65.06 | Q125: =K125+O125+P125 -> 580.92 | S125: Bijtelling 04-SP-VN
R126: Inhouden boetes deel 4
B127: =Periode!B127 -> 0 | C127: =Periode!H127 -> 0
B128: =Periode!B128 -> 0 | C128: =Periode!H128 -> 0
B129: =Periode!B129 -> Marcel Spruijt | C129: =Periode!G129 -> 32 (4wk) | D129: 5 | E129: 40 | K129: =(Periode!BB129*E129/40)+((F129+H129+I129)*Periode!BD129/40)+(J129*Periode!BF129/40)+(G129*Periode!BE129/40) -> 751.94 | Q129: =K129+O129+P129 -> 751.94 | S129: Bijtelling 54-GVP-1
B131: =Periode!B131 -> Michael Windhorst | C131: =Periode!G131 -> 0 | D131: 5 | E131: 40 | K131: =(Periode!BB131*E131/40)+((F131+H131+I131)*Periode!BD131/40)+(J131*Periode!BF131/40)+(G131*Periode!BE131/40) -> 628 | Q131: =K131+O131+P131 -> 628 | S131: Bijtelling V-695-HK
R132: Betalen Bewind:
...

Sheet Periode
B2: Legenda: | D2: ALLEEN GEKLEURDE letters en cijfers ingeven, ZWART zijn formules of vaste gegevens
D3: Een Geel gemarkeertde cel betreft een uitzondering in formule, getal of eenheid | BB3: 229 dagen 40uur | BC3: 229 dagen 40 uur | BF3: 7 dagen | BG3: Opmerking
AK4: Vergoeding | AM4: Bovm. loon | AO4: Bovenmatige | BB4: Netto afspraak | BC4: Netto SL | BD4: Vak RV RVS KV | BE4: Ziekte | BF4: Feestdagen
M5: uta/niv | T5: Reservering | V5: Reservering | W5: Reservering | Y5: TSF | Z5: Vak.geld | AA5: RV | AC5: Compensatie | AD5: Compensatie | AE5: Compensatie | AH5: Penisoen | AI5: Compensatie | AM5: per dag | AO5: sal.niv | AS5: WKR | AT5: GV | AU5: WKR | AV5: GV | AW5: WKR | AX5: IK | BB5: Incl. | BC5: incl: cao verg | BD5: incl. comp: RV | BF5: kaal loon
G6: Contract | L6: Bruto | M6: bovenm. | N6: Bruto | Q6: 0.08 | T6: VAK | V6: ADV/RV | W6: RVS/RVB | Z6: Reserv. | AA6: Reserv. | AC6: BWV | AD6: ADV/RV | AE6: RVS/RVB | AH6: compensatie | AI6: duurzame | AK6: Zorgverz. | AM6: Reisuur: | AN6: 18.95 | AO6: premie p/u | AQ6: Totaal | AS6: bovenm. | AT6: cao/gereeds. | AU6: cao/gereeds. | AV6: laarzen | AW6: Kleding | AX6: wasgeld | AY6: TOTAAL | AZ6: Auto/ | BB6: bovenm verg. | BC6: reisuren | BD6: RVS, bov.wetdg
B7: Werknemer | D7: Keuzebudget | E7: Fase | F7: Pensioen | G7: Uren | H7: CAO | I7: Recht op dagen | J7: Inregeling | K7: Functie | L7: FL | M7: Bruto | N7: Totaal | P7: RG | Q7: Vgeld | T7: dagen | U7: % | V7: dagen | W7: dagen | X7: % | Y7: dagen | Z7: 0.45 | AA7: 0.45 | AC7: dagen | AD7: dagen | AE7: dagen | AF7: % | AG7: % | AH7: p/u | AI7: inzetbaarheid | AK7: p/4wk | AM7: Bedrag | AN7: per dag | AO7: 229dg | AQ7: bruto | AS7: verg. | AT7: verg. | AU7: verg. | AV7: verg. | AW7: verg. | AX7: verg. | AY7: NETTO/dg | AZ7: reiskosten | BC7: vaste afspraken
B8: Ruben Hellemons | D8: =1895.27+14.96-847.69 -> 1062.54 | E8: Fase 4 | F8: BPF UTA | G8: 124 (4wk) | H8: UTA | I8: 25v 15rv 5rvb | J8: T4.9 FL1 FN3 SN1 | K8: Assistent Uitvoerder | L8: 19.19 | N8: =L8+M8 -> 19.19 | P8: =N8+O8 -> 19.19 | T8: 25 | U8: =T8/'Grondslag bouw & infra'!$B$50 -> 0.095785441 | V8: 15 | W8: 5 | X8: =(V8+W8)/'Grondslag bouw & infra'!$B$50 -> 0.076628352 | AC8: 0 | AD8: 0 | AE8: 0 | AF8: =(AC8+AD8+AE8)/'Grondslag bouw & infra'!$B$50 -> 0 | AI8: 0.023 | AM8: =$AN$6*AN8 -> 0 | AQ8: =(P8*(AF8+AI8)+P8) -> 19.63137 | AV8: 0.68 | AW8: 1.1 | AX8: 0.48 | AY8: =SUM(AS8:AX8) -> 2.26 | AZ8: 1-VSV-81 | BB8: =657.14+15.56+48.42 -> 721.12 | BC8: =2516.24/4 -> 629.06 | BD8: =(BB8-(AY8*5))*(1-1%) -> 702.7218 | BE8: =BD8 -> 702.7218 | BF8: =BD8 -> 702.7218
B12: Andre Sintenie | D12: =149.27+75.73 -> 225 | E12: Fase 3 | F12: Stipp Plus | G12: 32 (4wk) | H12: SAVG | I12: 25v 7atv 8rvb | J12: B.02.1 Aanloopschaal 2e jr | K12: Timmerkracht 1 | L12: 14.71 | M12: 1.28 | N12: =L12+M12 -> 15.99 | P12: =N12+O12 -> 15.99 | T12: 25 | U12: =T12/'Grondslag bouw & infra'!$B$50 -> 0.095785441 | V12: 0 | W12: 0 | X12: 0 | AC12: 0 | AD12: 0 | AE12: 0 | AF12: =(AC12+AD12+AE12)/'Grondslag bouw & infra'!$B$50 -> 0 | AM12: =$AN$6*AN12 -> 0 | AW12: 1.6 | AY12: =SUM(AS12:AX12) -> 1.6 | AZ12: VV-204-L | BB12: =627.22+2.83+20+5.11 -> 655.16 | BC12: =2232.35/4 -> 558.0875 | BD12: =(BB12-(AY12*5))*(1-1%) -> 640.6884 | BE12: =BD12 -> 640.6884 | BF12: =BD12 -> 640.6884
B15: Dennis Aarts | D15: =-542.79+1051.64+223.9 -> 732.75 | E15: Fase 1-2 | F15: BPF UTA | G15: 0 | H15: UTA | I15: 25v 15rv | J15: T4.9 FL1 FN3 SN1 | K15: Assistent uitvoerder | L15: 19.19 | N15: =L15+M15 -> 19.19 | P15: =N15+O15 -> 19.19 | T15: 25 | U15: =T15/'Grondslag bouw & infra'!$B$50 -> 0.095785441 | V15: 15 | W15: 0 | X15: =(V15+W15)/'Grondslag bouw & infra'!$B$50 -> 0.057471264 | AC15: 0 | AD15: 0 | AE15: 0 | AF15: =(AC15+AD15+AE15)/'Grondslag bouw & infra'!$B$50 -> 0 | AI15: 0.023 | AM15: =$AN$6*AN15 -> 0 | AQ15: =(P15*(AF15+AI15)+P15) -> 19.63137 | AV15: 0.68 | AW15: 1.1 | AX15: 0.48 | AY15: =SUM(AS15:AX15) -> 2.26 | AZ15: 98-XH-DP | BB15: =645+10.22+48.44 -> 703.66 | BC15: =2472.26/4 -> 618.065 | BD15: =(BB15-(AY15*5))*(1-1%) -> 685.4364 | BE15: =BD15 -> 685.4364 | BF15: =BD15 -> 685.4364
H16: Schilder | I16: 25v 7rv | O16: =N16*1.16% -> 0 | AS16: 0.26
B17: Kay Sanders | E17: Fase 1-2 | F17: Stipp basis | G17: 0 | H17: Bouw | I17: 25v 20rv | J17: T4.2 FG.A | K17: Bouwvakhelper | L17: 18.95 | N17: =L17+M17 -> 18.95 | P17: =N17+O17 -> 18.95 | Q17: Inclusief | T17: 20 | V17: 0 | W17: 0 | AC17: 5 | AD17: 20 | AE17: 0 | AF17: =(AC17+AD17+AE17)/'Grondslag bouw & infra'!$B$50 -> 0.095785441 | AI17: 0.0365 | AM17: =$AN$6*AN17 -> 0 | AV17: 0.08 | AW17: 0.13 | AX17: 0.06 | AY17: =SUM(AS17:AX17) -> 0.27 | AZ17: 0.32 | BB17: =(650/4)*5 -> 812.5 | BG17: Incl. vakantiegeld en VAKANTIEDAGEN, elke week max aanvullen!
BG18: claimt geen ziek
B20: Eric Snepvangers | D20: =-130.18-265.83-60.75-70.23-104.12-60.12+13.26-312.97-106-60.7+895.55+164.7+486.09+629 -> 1017.7 | E20: Fase 3.2 | F20: BPF Bouw | G20: 32 (4wk) | H20: Bouw | I20: 25v 20rv 8rvs | J20: T4.2 FG.A | K20: Bouwvakhelper | L20: 18.95 | N20: =L20+M20 -> 18.95 | P20: =N20+O20 -> 18.95 | T20: 20 | U20: =T20/'Grondslag bouw & infra'!$B$50 -> 0.076628352 | V20: 20 | W20: 8 | X20: =(V20+W20)/'Grondslag bouw & infra'!$B$50 -> 0.10727969 | AC20: 5 | AD20: 0 | AE20: 0 | AF20: =(AC20+AD20+AE20)/'Grondslag bouw & infra'!$B$50 -> 0.019157088 | AI20: 0.0365 | AK20: ='Grondslag bouw & infra'!C31 -> 20.667692 | AM20: =$AN$6*AN20 -> 0 | AQ20: =(P20*(AF20+AI20)+P20) -> 20.004702 | AV20: nvt | AW20: 1.1 | AX20: 0.48 | AY20: =SUM(AS20:AX20) -> 1.58 | AZ20: V-699-NT | BB20: =(525+15.12+35+8.25+7.49)/32*40 -> 738.575 | BC20: =(((2298.89)/4)*5)/4 -> 718.40312 | BD20: =(BB20-(AY20*5))*(1-1%) -> 723.36825 | BE20: =BD20 -> 723.36825 | BF20: =BD20 -> 723.36825 | BG20: 32 uur per week
B23: Frank Stouthart | D23: =1131.65+679.8-114.64-1172.79+422.97-793.6+429.31+396.89-255.37 -> 724.22 | E23: Fase 3 | F23: BPF Bouw | G23: 32 (4wk) | H23: Bouw | I23: 25v 20rv 9rvs | J23: T4.2 FG.B | K23: Timmerman II | L23: 20.02 | N23: =L23+M23 -> 20.02 | P23: =N23+O23 -> 20.02 | T23: 20 | U23: =T23/'Grondslag bouw & infra'!$B$50 -> 0.076628352 | V23: 20 | W23: 9 | X23: =(V23+W23)/'Grondslag bouw & infra'!$B$50 -> 0.11111111 | AC23: 5 | AD23: 0 | AE23: 0 | AF23: =(AC23+AD23+AE23)/'Grondslag bouw & infra'!$B$50 -> 0.019157088 | AI23: 0.0365 | AK23: ='Grondslag bouw & infra'!C31 -> 20.667692 | AM23: =$AN$6*AN23 -> 0 | AQ23: =(P23*(AF23+AI23)+P23) -> 21.134255 | AT23: 0.96 | AV23: 0.68 | AW23: 1.1 | AX23: 0.48 | AY23: =SUM(AS23:AX23) -> 3.22 | AZ23: 0.32 | BB23: =535.83+12.5+6.62+20.09+20.06+10.22+17+4.55+11.22+6.94+5.16+18.2+12.32+2.11+12.21+11.25 -> 706.28 | BC23: =2688.91/4 -> 672.2275 | BD23: =(BB23-(AY23*5))*(1-1%) -> 683.2782 | BE23: =BD23 -> 683.2782 | BF23: =BD23 -> 683.2782
B26: Roy Rubeling | E26: Fase 1-2 | F26: Stipp Basis | G26: 0 | H26: Bouw | I26: 25v 20rv | J26: T4.5 Starttabel 1e halfjaar | K26: Bouwvakhelper | L26: 15.77 | N26: =L26+M26 -> 15.77 | P26: =N26+O26 -> 15.77 | Q26: Inclusief | T26: 20 | U26: =T26/'Grondslag bouw & infra'!$B$50 -> 0.076628352 | V26: 0 | W26: 0 | X26: =(V26+W26)/'Grondslag bouw & infra'!$B$50 -> 0 | AC26: 5 | AD26: 20 | AE26: 0 | AF26: =(AC26+AD26+AE26)/'Grondslag bouw & infra'!$B$50 -> 0.095785441 | AH26: =(AQ26-'Grondslag bouw & infra'!$B$46)*'Grondslag bouw & infra'!$B$43 -> 0.23420396 | AI26: 0.0365 | AM26: =$AN$6*AN26 -> 0 | AQ26: =(P26*(AF26+AI26)+P26) -> 17.856141 | AV26: 0.68 | AW26: 1.1 | AX26: 0.48 | AY26: =SUM(AS26:AX26) -> 2.26 | AZ26: 0.32 | BB26: 750 | BC26: =2549.25/4 -> 637.3125 | BD26: =(BB26-(AY26*5))*(1-1%) -> 731.313 | BE26: =BD26 -> 731.313 | BF26: =BD26 -> 731.313
B33: Marco Govers | E33: Fase 3 | F33: BPF UTA | G33: 32 (4wk) | H33: UTA | I33: 25v 15rv 10rvb | J33: T4.9 FL1 FN3 SN1 | K33: Assistent Uitvoerder | L33: 19.19 | N33: =L33+M33 -> 19.19 | P33: =N33+O33 -> 19.19 | Q33: Inclusief | T33: 20 | U33: =T33/'Grondslag bouw & infra'!$B$50 -> 0.076628352 | V33: 0 | W33: 10 | X33: =(V33+W33)/'Grondslag bouw & infra'!$B$50 -> 0.038314176 | AC33: 5 | AD33: 15 | AE33: 0 | AF33: =(AC33+AD33+AE33)/'Grondslag bouw & infra'!$B$50 -> 0.076628352 | AI33: 0.023 | AK33: ='Grondslag bouw & infra'!C31 -> 20.667692 | AM33: =$AN$6*AN33 -> 0 | AQ33: =(P33*(AF33+AI33)+P33) -> 21.101868 | AV33: 0.68 | AW33: 1.1 | AX33: 0.48 | AY33: =SUM(AS33:AX33) -> 2.26 | AZ33: 0.32 | BB33: =750+25.21 -> 775.21 | BC33: =2793.4/4 -> 698.35 | BD33: =(BB33-(AY33*5))*(1-1%) -> 756.2709 | BE33: =BD33 -> 756.2709 | BF33: =BD33 -> 756.2709
B35: Onno de Vries | D35: =262.82+141.72+12.29+40+132.47+597.84 -> 1187.14 | E35: Fase 4 | F35: BPF bouw | G35: 124 (4wk) | H35: Bouw | I35: 25v 10rv 10tsf | J35: T4.2 FG.A | K35: Bouwvakhelper | L35: 18.95 | N35: =L35+M35 -> 18.95 | P35: =N35+O35 -> 18.95 | T35: 25 | U35: =T35/'Grondslag bouw & infra'!$B$50 -> 0.095785441 | V35: 10 | W35: 0 | X35: =(V35+W35)/'Grondslag bouw & infra'!$B$50 -> 0.038314176 | Y35: 10 | Z35: =8%*0.45 -> 0.036 | AA35: =(Y35*0.4%)*0.45 -> 0.018 | AC35: 0 | AD35: 0 | AE35: 0 | AF35: =(AC35+AD35+AE35)/'Grondslag bouw & infra'!$B$50 -> 0 | AI35: 0.0365 | AM35: =$AN$6*AN35 -> 0 | AQ35: =(P35*(AF35+AI35)+P35) -> 19.641675 | AV35: 0.68 | AW35: 1.1 | AX35: 0.48 | AY35: =SUM(AS35:AX35) -> 2.26 | AZ35: 0.32 | BB35: =BC35 -> 633.355 | BC35: =2533.42/4 -> 633.355 | BD35: =(BB35-(AY35*5))*(1-1%) -> 615.83445 | BE35: =BD35 -> 615.83445 | BF35: =BD35 -> 615.83445 | BG35: TSF
B39: Jan Levering | D39: =274.46+100-33.16-194.32-139.89-110-49-44.45-770.58+838.07-55.5+362.08+110.7-470.25+506.46 -> 324.62 | E39: Fase 3 | F39: BPF UTA | G39: 32 (4wk) | H39: UTA | I39: 25v 15rv 7rvs | J39: T4.9 FL23 FN1 SN2 (104%) | K39: Intern onderhoudsmedewerker | L39: 15.77 | M39: 2.45 | N39: =L39+M39 -> 18.22 | P39: =N39+O39 -> 18.22 | T39: 20 | U39: =T39/'Grondslag bouw & infra'!$B$50 -> 0.076628352 | V39: 15 | W39: 7 | X39: =(V39+W39)/'Grondslag bouw & infra'!$B$50 -> 0.084291188 | AC39: 5 | AD39: 0 | AE39: 0 | AF39: =(AC39+AD39+AE39)/'Grondslag bouw & infra'!$B$50 -> 0.019157088 | AI39: 0.023 | AK39: ='Grondslag bouw & infra'!C31 -> 20.667692 | AM39: =$AN$6*AN39 -> 0 | AQ39: =(P39*(AF39+AI39)+P39) -> 18.988102 | AV39: 0.68 | AW39: 1.1 | AX39: 0.48 | AY39: =SUM(AS39:AX39) -> 2.26 | AZ39: 1-VXV-55 | BB39: =615+2.1+8.54+5.25+7.12+68.1 -> 706.11 | BC39: =2466.24/4 -> 616.56 | BD39: =(BB39-(AY39*5))*(1-1%) -> 687.8619 | BE39: =BD39 -> 687.8619 | BF39: =BD39 -> 687.8619 | BG39: werkt 128 uur per 4 weken
B42: Alex van der Laan | D42: =-223.64+228.7-236.63-38-79.66-126.55-166.02-103.65+567.94-55.17+503.89-116.84-82.72-54.97-132.63-54.35+926.65-149.3 -> 607.05 | E42: Fase 4 | F42: BPF UTA | G42: 32 (wk) | H42: UTA | I42: 25v 15rv | J42: T4.9 FL1 FN3 116% | K42: Assistent uitvoerder | L42: =19.19*1.16 -> 22.2604 | N42: =L42+M42 -> 22.2604 | P42: =N42+O42 -> 22.2604 | T42: 25 | U42: =T42/'Grondslag bouw & infra'!$B$50 -> 0.095785441 | V42: 15 | W42: 0 | X42: =(V42+W42)/'Grondslag bouw & infra'!$B$50 -> 0.057471264 | Z42: =8%*0.45 -> 0.036 | AC42: 0 | AD42: 0 | AE42: 0 | AF42: =(AC42+AD42+AE42)/'Grondslag bouw & infra'!$B$50 -> 0 | AI42: 0.023 | AK42: ='Grondslag bouw & infra'!C31 -> 20.667692 | AM42: =$AN$6*AN42 -> 0 | AQ42: =(P42*(AF42+AI42)+P42) -> 22.772389 | AV42: 0.68 | AW42: 1.1 | AX42: 0.48 | AY42: =SUM(AS42:AX42) -> 2.26 | AZ42: 36-GNP-4 | BB42: =BC42 -> 673.75 | BC42: =2695/4 -> 673.75 | BD42: =(BB42-(AY42*5))*(1-1%) -> 655.8255 | BE42: =BD42 -> 655.8255 | BF42: =BD42 -> 655.8255 | BG42: TSF
D44: =1-1+5.5+2.5+4.5 -> 12.5
B46: Shafieq Asgarali | D46: =537.66-(72*1.8)-(29*1.8) -> 355.86 | E46: Fase 3 | F46: Stipp Plus | G46: 32 (4wk) | H46: SAVG | I46: 25v 7atv | J46: LG.01 Aanloopschaal 1e jaar | L46: 14.71 | M46: 0.02 | N46: =L46+M46 -> 14.73 | P46: =N46+O46 -> 14.73 | T46: 25 | U46: =T46/'Grondslag bouw & infra'!$B$50 -> 0.095785441 | V46: 0 | W46: 0 | X46: =(V46+W46)/'Grondslag bouw & infra'!$B$50 -> 0 | AC46: 0 | AD46: 0 | AE46: 0 | AF46: =(AC46+AD46+AE46)/'Grondslag bouw & infra'!$B$50 -> 0 | AM46: =$AN$6*AN46 -> 0 | AS46: =(7.5*1.34) -> 10.05 | AW46: 1.6 | AY46: =SUM(AS46+AW46) -> 11.65 | AZ46: 78-RJ-BP | BB46: =BC46-(5*AY46) -> 494.875 | BC46: =2212.5/4 -> 553.125 | BD46: =BB46 -> 494.875 | BE46: =BD46 -> 494.875 | BF46: =BD46 -> 494.875 | BG46: Proforma gedraaid op 150 uur
B48: Sander van den Hoek | D48: =-64.45-203.93-62.94-262.8-98.76+429.51 -> -263.37 | E48: Fase 3 | F48: BPF UTA | G48: 32 (wk) | H48: UTA | I48: 25v 15rv | J48: T4.9 FL8 FN1 SN1 | K48: Aanvoerder beheer materieel | L48: 15.77 | N48: =L48+M48 -> 15.77 | P48: =N48+O48 -> 15.77 | Q48: Inclusief | T48: 25 | U48: =T48/'Grondslag bouw & infra'!$B$50 -> 0.095785441 | V48: 15 | W48: 0 | X48: =(V48+W48)/'Grondslag bouw & infra'!$B$50 -> 0.057471264 | AB48: 0 | AC48: 0 | AD48: 0 | AE48: 0 | AF48: =(AC48+AD48+AE48)/'Grondslag bouw & infra'!$B$50 -> 0 | AI48: 0.023 | AM48: =$AN$6*AN48 -> 0 | AQ48: =(P48*(AF48+AI48)+P48) -> 16.13271 | AS48: 9.1 | AV48: 0.68 | AW48: 1.1 | AX48: 0.48 | AY48: =SUM(AS48:AX48) -> 11.36 | AZ48: 0.25 | BB48: =BC48-(5*AY48) -> 574.925 | BC48: =2526.9/4 -> 631.725 | BD48: =BB48 -> 574.925 | BE48: =BD48 -> 574.925 | BF48: =BD48 -> 574.925
B51: Marcel van Zandwijk | E51: Fase 3 | F51: BPF UTA | G51: 32 (4wk) | H51: UTA | I51: 25v 15rv | J51: T4.9 FL1 FN4 SN1 | K51: Uitvoering | L51: 21.7 | N51: =L51+M51 -> 21.7 | P51: =N51+O51 -> 21.7 | Q51: Inclusief | T51: 20 | U51: =T51/'Grondslag bouw & infra'!$B$50 -> 0.076628352 | V51: 0 | W51: 0 | X51: =(V51+W51)/'Grondslag bouw & infra'!$B$50 -> 0 | AC51: 5 | AD51: 15 | AE51: 0 | AF51: =(AC51+AD51+AE51)/'Grondslag bouw & infra'!$B$50 -> 0.076628352 | AI51: 0.023 | AM51: =2*AN6 -> 37.9 | AN51: 2 | AV51: 0.68 | AX51: 0.48 | AY51: 0.27 | BB51: =937.5-17+5.21+7.52 -> 933.23 | BC51: =2962.53/4 -> 740.6325 | BD51: =(BB51-(AY51*5))*(1-1%) -> 922.5612 | BE51: =BD51 -> 922.5612 | BF51: =BD51 -> 922.5612 | BG51: Netto incl. vakantiegeld, -9,48 bijtelling
B53: Ronald van Maanen | D53: =91.95 -> 91.95 | E53: Fase 3 | F53: BPF bouw | G53: 32 (4wk) | H53: Bouw | I53: 25v 20rv | J53: T4.2 FG.B | K53: Timmerman II | L53: 20.02 | N53: =L53+M53 -> 20.02 | P53: =N53+O53 -> 20.02 | T53: 20 | U53: =T53/'Grondslag bouw & infra'!$B$50 -> 0.076628352 | V53: 9 | W53: 0 | X53: =(V53+W53)/'Grondslag bouw & infra'!$B$50 -> 0.034482759 | AC53: 5 | AD53: 11 | AE53: 0 | AF53: =(AC53+AD53+AE53)/'Grondslag bouw & infra'!$B$50 -> 0.061302682 | AI53: 0.0365 | AM53: =$AN$6*AN53 -> 0 | AU53: 0.96 | AV53: 0.68 | AW53: 1.1 | AX53: 0.48 | AY53: =SUM(AS53:AX53) -> 3.22 | AZ53: 0.32 | BB53: =605.03+25.1+9.25+17.2+15+3.5+25+11.21+21.96 -> 733.25 | BC53: =2750.23/4 -> 687.5575 | BD53: =(BB53-(AY53*5))*(1-1%) -> 709.9785 | BE53: =BD53 -> 709.9785 | BF53: =BD53 -> 709.9785
AI56: Reserveren
B57: Erik Visser | D57: =1330.2-74-128-112.39-149.58-82.6-111.69-120-148.42-270-139.63-20.62+1859.46-150-575+25.07+50.13-900+722.47+314.5-59.92-91.89-1440+303.2+1548.29-90.99-126.45 -> 1362.14 | E57: Fase 3 | F57: BPF UTA | G57: 32 (4wk) | H57: UTA | I57: 25v 15rv 3rvb | J57: T4.9 FL15 FN1 SN2 104% | K57: Werkterminal administrateur | L57: =15.77 -> 15.77 | M57: 1.04 | N57: =L57*M57 -> 16.4008 | P57: =N57+O57 -> 16.4008 | T57: 25 | U57: =T57/'Grondslag bouw & infra'!$B$50 -> 0.095785441 | V57: 15 | W57: 3 | X57: =(V57+W57)/'Grondslag bouw & infra'!$B$50 -> 0.068965517 | AC57: 0 | AD57: 0 | AE57: 0 | AF57: =(AC57+AD57+AE57)/'Grondslag bouw & infra'!$B$50 -> 0 | AI57: 0.023 | AM57: =$AN$6*AN57 -> 0 | AQ57: =(P57*(AF57+AI57)+P57) -> 16.778018 | AS57: =(0.08+0.12+0.06)*8 -> 2.08 | AY57: =SUM(AS57:AX57) -> 2.08 | AZ57: 0.25 | BB57: =BC57 -> 560.44 | BC57: =2241.76/4 -> 560.44 | BD57: =(BB57-(AY57*5))*(1-1%) -> 544.5396 | BE57: =BD57 -> 544.5396 | BF57: =BD57 -> 544.5396
B60: Dirk Nouwens | D60: =20.15+215.8 -> 235.95 | E60: Fase 1-2 | F60: AOW | G60: 0 | H60: UTA | I60: 25v 15rv 9rvs | J60: T4.11 starttabel 2e halfjaar | K60: Aanvoerder | L60: 15.24 | N60: =L60+M60 -> 15.24 | P60: =N60+O60 -> 15.24 | Q60: Inclusief | T60: 25 | U60: =T60/'Grondslag bouw & infra'!$B$50 -> 0.095785441 | V60: 15 | W60: 9 | X60: =(V60+W60)/'Grondslag bouw & infra'!$B$50 -> 0.091954023 | AB60: 0 | AC60: 0 | AD60: 0 | AE60: 0 | AF60: =(AC60+AD60+AE60)/'Grondslag bouw & infra'!$B$50 -> 0 | AI60: 0.023 | AM60: =$AN$6*AN60 -> 0 | AQ60: =(P60*(AF60+AI60)+P60) -> 15.59052 | AV60: 0.68 | AW60: 1.1 | AX60: 0.48 | AY60: =SUM(AS60:AX60) -> 2.26 | AZ60: 0.25 | BB60: =677.84 -> 677.84 | BC60: =2606.28/4 -> 651.57 | BD60: =(BB60-(AY60*5))*(1-1%) -> 659.8746 | BE60: =BD60 -> 659.8746 | BF60: =BD60 -> 659.8746
B63: Youri Nouwens | D63: =298.99+304.75-898+294.26-438.63+1541-1014.88 -> 87.49 | E63: Fase 3 | F63: Stipp Plus | G63: 32 (4wk) | H63: SAVG | I63: 25v 7atv | J63: B.01.1 Aanloop 2e jaar | K63: Hulpkracht | L63: 14.71 | M63: 0.02 | N63: =L63+M63 -> 14.73 | P63: =N63+O63 -> 14.73 | T63: 25 | U63: =T63/'Grondslag bouw & infra'!$B$50 -> 0.095785441 | V63: 0 | W63: 0 | X63: =(V63+W63)/'Grondslag bouw & infra'!$B$50 -> 0 | AC63: 0 | AD63: 0 | AE63: 0 | AF63: =(AC63+AD63+AE63)/'Grondslag bouw & infra'!$B$50 -> 0 | AM63: =$AN$6*AN63 -> 0 | AS63: =7.5*1.34 -> 10.05 | AW63: 1.6 | AY63: =SUM(AS63+AW63) -> 11.65 | AZ63: 54-GDT-8 | BB63: =BC63-(5*AY63) -> 494.875 | BC63: =2212.5/4 -> 553.125 | BD63: =BB63 -> 494.875 | BE63: =BD63 -> 494.875 | BF63: =BD63 -> 494.875
D69: =(163-150)+(144-135)-22 -> 0
B70: Marco Booij | D70: =1185-102.84-612.6-18.59-326.6+819-943.37 -> 0 | E70: Fase 3.2 | F70: Stipp Plus | G70: 32 (4wk) | H70: Schilder | I70: 25v 7atv | J70: S.02.1 LG 02.02 | K70: Schilder 1 | L70: 18.93 | N70: =L70+M70 -> 18.93 | P70: =N70+O70 -> 18.93 | T70: 20 | U70: =T70/'Grondslag bouw & infra'!$B$50 -> 0.076628352 | V70: 0 | W70: 0 | X70: =(V70+W70)/'Grondslag bouw & infra'!$B$50 -> 0 | AC70: 5 | AD70: 0 | AE70: 0 | AF70: =(AC70+AD70+AE70)/'Grondslag bouw & infra'!$B$50 -> 0.019157088 | AM70: =$AN$6*AN70 -> 0 | AW70: 1.6 | AY70: =SUM(AS70:AX70) -> 1.6 | AZ70: 52-LN-BT | BB70: =660+10.4+15.2+26.52+8.1 -> 720.22 | BD70: =(BB70-(AY70*5))*(1-1%) -> 705.0978 | BF70: =BD70 -> 705.0978
B74: Kevin Schuiling | D74: =162.2 -> 162.2 | E74: Fase 3 | F74: BPF Bouw | G74: 32 (4wk) | H74: Bouw | I74: 25v 20rv | J74: T4.2 FG.A | K74: Bouwvakhelper | L74: 18.95 | N74: =L74+M74 -> 18.95 | P74: =N74+O74 -> 18.95 | Q74: Inclusief | T74: 25 | U74: =T74/'Grondslag bouw & infra'!$B$50 -> 0.095785441 | V74: 20 | W74: 0 | X74: =(V74+W74)/'Grondslag bouw & infra'!$B$50 -> 0.076628352 | AC74: 0 | AD74: 0 | AE74: 0 | AF74: =(AC74+AD74+AE74)/'Grondslag bouw & infra'!$B$50 -> 0 | AI74: 0.0365 | AM74: 0 | AQ74: =(P74*(AF74+AI74)+P74) -> 19.641675 | AV74: 0.68 | AW74: 1.1 | AX74: 0.48 | AY74: =SUM(AS74:AX74) -> 2.26 | AZ74: 0.32 | BB74: =600 -> 600 | BC74: =2674.32/4 -> 668.58 | BD74: =(BB74-(AY74*5))*(1-1%) -> 582.813 | BE74: =BD74 -> 582.813 | BF74: =BD74 -> 582.813
B77: Steven Lamers | D77: =217.02 -> 217.02 | E77: Fase 3 | F77: BPF Bouw | G77: 32 (4wk) | H77: Bouw | I77: 25v 20rv | J77: T4.2 FG.A | K77: Bouwvakhelper | L77: 18.95 | N77: =L77+M77 -> 18.95 | P77: =N77+O77 -> 18.95 | Q77: Inclusief | T77: 25 | U77: =T77/'Grondslag bouw & infra'!$B$50 -> 0.095785441 | V77: 20 | W77: 0 | X77: =(V77+W77)/'Grondslag bouw & infra'!$B$50 -> 0.076628352 | AC77: 0 | AD77: 0 | AE77: 0 | AF77: =(AC77+AD77+AE77)/'Grondslag bouw & infra'!$B$50 -> 0 | AI77: 0.0365 | AM77: 0 | AQ77: =(P77*(AF77+AI77)+P77) -> 19.641675 | AV77: 0.68 | AW77: 1.1 | AX77: 0.48 | AY77: =SUM(AS77:AX77) -> 2.26 | AZ77: 82-VZJ-2 | BB77: =BC77 -> 663.32 | BC77: =2653.28/4 -> 663.32 | BD77: =(BB77-(AY77*5))*(1-1%) -> 645.4998 | BE77: =BD77 -> 645.4998 | BF77: =BD77 -> 645.4998
B80: Leo van Doorn | D80: 1122.03 | E80: Fase 1 -2 | F80: BPF UTA | G80: 0 | H80: UTA | I80: 25v 15rv 5rvS | J80: T4.9 FL1 FN3 SN1 | K80: Assistent Uitvoerder | L80: 19.19 | M80: 0.51 | N80: =L80+M80 -> 19.7 | P80: =N80+O80 -> 19.7 | T80: 20 | U80: =T80/'Grondslag bouw & infra'!$B$50 -> 0.076628352 | V80: 8 | W80: 0 | X80: =(V80+W80)/'Grondslag bouw & infra'!$B$50 -> 0.030651341 | AC80: 5 | AD80: 7 | AE80: 5 | AF80: =(AC80+AD80+AE80)/'Grondslag bouw & infra'!$B$50 -> 0.0651341 | AI80: 0.023 | AM80: 0 | AV80: 0.68 | AW80: 1.1 | AX80: 0.48 | AY80: =SUM(AS80:AX80) -> 2.26 | AZ80: 0.32 | BB80: =700.56+11.2 -> 711.76 | BC80: =2657.58/4 -> 664.395 | BD80: =(BB80-(AY80*5))*(1-1%) -> 693.4554 | BE80: =BD80 -> 693.4554 | BF80: =BD80 -> 693.4554
B83: Tobin van de Kuil | E83: Fase 1-2 | F83: StiPP | G83: 0 | H83: Bouw | I83: 25v 20rv | J83: T4.2 FG.B | K83: Timmerman II | L83: 20.02 | N83: =L83+M83 -> 20.02 | P83: =N83+O83 -> 20.02 | Q83: Inclusief | T83: 20 | U83: =T83/'Grondslag bouw & infra'!$B$50 -> 0.076628352 | V83: 0 | W83: 0 | X83: =(V83+W83)/'Grondslag bouw & infra'!$B$50 -> 0 | AC83: 5 | AD83: 20 | AE83: 0 | AF83: =(AC83+AD83+AE83)/'Grondslag bouw & infra'!$B$50 -> 0.095785441 | AH83: =(AQ83-'Grondslag bouw & infra'!$B$46)*'Grondslag bouw & infra'!$B$43 -> 0.36500953 | AI83: 0.0365 | AM83: 0 | AQ83: =(P83*(AF83+AI83)+P83) -> 22.668355 | AU83: 0.96 | AV83: 0.68 | AW83: 1.1 | AX83: 0.48 | AY83: =SUM(AS83:AX83) -> 3.22 | AZ83: 0.32 | BB83: =BC83 -> 752.795 | BC83: =3011.18/4 -> 752.795 | BD83: =(BB83-(AY83*5))*(1-1%) -> 729.32805 | BE83: =BD83 -> 729.32805 | BF83: =BD83 -> 729.32805
B87: Carlo Peetoom | D87: =89.02-89.02 -> 0 | E87: Fase 3 | F87: BPF UTA | G87: 32 (4wk) | H87: UTA | I87: 25v 15rv | J87: T4.9 FL1 FN3 SN1 | K87: Assistent Uitvoerder | L87: 19.19 | N87: =L87+M87 -> 19.19 | P87: =N87+O87 -> 19.19 | Q87: Inclusief | T87: 20 | U87: =T87/'Grondslag bouw & infra'!$B$50 -> 0.076628352 | V87: 10 | W87: 0 | X87: =(V87+W87)/'Grondslag bouw & infra'!$B$50 -> 0.038314176 | AC87: 5 | AD87: 5 | AE87: 0 | AF87: =(AC87+AD87+AE87)/'Grondslag bouw & infra'!$B$50 -> 0.038314176 | AI87: 0.023 | AM87: =$AN$6*AN87 -> 0 | AQ87: =(P87*(AF87+AI87)+P87) -> 20.366619 | AS87: 2.4 | AV87: 0.68 | AW87: 1.1 | AX87: 0.48 | AY87: =SUM(AS87:AX87) -> 4.66 | AZ87: 0.25 | BB87: =(650+11.23+11.31)/32*40 -> 840.675 | BC87: =2786.94/4 -> 696.735 | BD87: =(BB87-(AY87*5))*(1-1%) -> 809.20125 | BE87: =BD87 -> 809.20125 | BF87: =BD87 -> 809.20125
B90: Aries Provence | E90: Fase 1-2 | F90: AOW | G90: 0 | H90: UTA | I90: 25v 15rv 11rvs | J90: T4.11 Starttabel 1st halfjaar | K90: Assistent Uitvoerder | L90: 14.98 | N90: =L90+M90 -> 14.98 | P90: =N90+O90 -> 14.98 | Q90: Inclusief | T90: 25 | U90: =T90/'Grondslag bouw & infra'!$B$50 -> 0.095785441 | V90: 15 | W90: 11 | X90: =(V90+W90)/'Grondslag bouw & infra'!$B$50 -> 0.099616858 | AC90: 0 | AD90: 0 | AE90: 0 | AF90: =(AC90+AD90+AE90)/'Grondslag bouw & infra'!$B$50 -> 0 | AH90: AOW | AI90: 0.023 | AM90: =$AN$6*AN90 -> 0 | AQ90: =(P90*(AF90+AI90)+P90) -> 15.32454 | AV90: 0.68 | AW90: 1.1 | AX90: 0.48 | AY90: =SUM(AS90:AX90) -> 2.26 | AZ90: 0.25 | BB90: =2401.38/4 -> 600.345 | BC90: =2217.18/4 -> 554.295 | BD90: =(BB90-(AY90*5))*(1-1%) -> 583.15455 | BE90: =BD90 -> 583.15455 | BF90: =BD90 -> 583.15455
BB91: =BB90-(BC90-BC91) -> 470.1375 | BC91: =1696.35/4 -> 424.0875
B92: Gregory de Graaf | E92: Fase 1-2 | F92: Stipp | G92: 0 | H92: Bouw | I92: 25v 20rv | J92: T4.5 starttabel 1st halfjaar | K92: Bouwvakhelper | L92: 15.77 | N92: =L92+M92 -> 15.77 | P92: =N92 -> 15.77 | Q92: Inclusief | T92: 20 | U92: =T92/'Grondslag bouw & infra'!$B$50 -> 0.076628352 | V92: 5 | W92: 0 | X92: =(V92+W92)/'Grondslag bouw & infra'!$B$50 -> 0.019157088 | AC92: 5 | AD92: 15 | AE92: 0 | AF92: =(AC92+AD92+AE92)/'Grondslag bouw & infra'!$B$50 -> 0.076628352 | AH92: =(AQ92-'Grondslag bouw & infra'!$B$46)*'Grondslag bouw & infra'!$B$43 -> 0.22599208 | AI92: 0.0365 | AM92: 0 | AQ92: =(P92*(AF92+AI92)+P92) -> 17.554034 | AV92: 0.68 | AW92: 1.1 | AX92: 0.48 | AY92: =SUM(AS92:AX92) -> 2.26 | AZ92: 34-LK-NH | BB92: 738 | BC92: =2517.42/4 -> 629.355 | BD92: =(BB92-(AY92*5))*(1-1%) -> 719.433 | BE92: =BD92 -> 719.433 | BF92: =BD92 -> 719.433
B95: Joey Cuperus
B99: Eric de Jong | E99: Fase 1-2 | F99: Stipp | G99: 0 | H99: UTA | I99: 25v 15rv | J99: T4.9 FL1 FN3 SN1 | K99: Assistent Uitvoerder | L99: 19.19 | N99: =L99+M99 -> 19.19 | P99: =N99+O99 -> 19.19 | Q99: Inclusief | T99: 20 | U99: =T99/'Grondslag bouw & infra'!$B$50 -> 0.076628352 | V99: 0 | W99: 0 | X99: =(V99+W99)/'Grondslag bouw & infra'!$B$50 -> 0 | AC99: 5 | AD99: 15 | AE99: 0 | AF99: =(AC99+AD99+AE99)/'Grondslag bouw & infra'!$B$50 -> 0.076628352 | AH99: =(AQ99-'Grondslag bouw & infra'!$B$46)*'Grondslag bouw & infra'!$B$44 -> 0.17313583 | AI99: 0.023 | AM99: =$AN$6*AN99 -> 0 | AQ99: =(P99*(AF99+AI99)+P99) -> 21.101868 | AV99: 0.68 | AW99: 1.1 | AX99: 0.48 | AY99: =SUM(AS99:AX99) -> 2.26 | AZ99: 0.23 | BB99: =1036.11-108.1 -> 928.01 | BC99: =2852.16/4 -> 713.04 | BD99: =(BB99-(AY99*5))*(1-1%) -> 907.5429 | BE99: =BD99 -> 907.5429 | BF99: =BD99 -> 907.5429
B104: Michel van der Mark | D104: =240.67 -> 240.67 | E104: Fase 3 | F104: BPF Bouw | G104: 32 (4wk) | H104: Bouw | I104: 25v 20rv | J104: T4.2 FG.A | K104: Bouwvakhelper | L104: 18.95 | N104: =L104+M104 -> 18.95 | P104: =N104+O104 -> 18.95 | T104: 20 | U104: =T104/'Grondslag bouw & infra'!$B$50 -> 0.076628352 | V104: 20 | W104: 0 | X104: =(V104+W104)/'Grondslag bouw & infra'!$B$50 -> 0.076628352 | AC104: 5 | AD104: 0 | AE104: 0 | AF104: =(AC104+AD104+AE104)/'Grondslag bouw & infra'!$B$50 -> 0.019157088 | AI104: 0.0365 | AM104: =$AN$6*AN104 -> 0 | AQ104: =(P104*(AF104+AI104)+P104) -> 20.004702 | AT104: 0.96 | AV104: 0.68 | AW104: 1.1 | AX104: 0.48 | AY104: =SUM(AS104:AX104) -> 3.22 | AZ104: GVR-35-D | BB104: =687.5+7.78+9.9 -> 705.18 | BC104: =2556.05/4 -> 639.0125 | BD104: =(BB104-(AY104*5))*(1-1%) -> 682.1892 | BE104: =BD104 -> 682.1892 | BF104: =BD104 -> 682.1892
B110: Jan Harteveld | E110: Fase 3 | F110: BPF Bouw | G110: 150 (4wk) | H110: Bouw | I110: 25v 20rv | J110: T4.2 FG.A | K110: Bouwvakhelper | L110: 18.95 | M110: 0.6 | N110: =L110+M110 -> 19.55 | P110: =N110+O110 -> 19.55 | Q110: Inclusief | T110: 20 | U110: =T110/'Grondslag bouw & infra'!$B$50 -> 0.076628352 | V110: 0 | W110: 0 | X110: =(V110+W110)/'Grondslag bouw & infra'!$B$50 -> 0 | AC110: 5 | AD110: 20 | AE110: 0 | AF110: =(AC110+AD110+AE110)/'Grondslag bouw & infra'!$B$50 -> 0.095785441 | AI110: 0.0365 | AM110: =$AN$6*AN110 -> 0 | AV110: 0.68 | AW110: 1.1 | AX110: 0.48 | AY110: =SUM(AS110:AX110) -> 2.26 | AZ110: 0,25 Fiets | BB110: =777.78+8.89+6.68 -> 793.35 | BC110: =2803.28/4 -> 700.82 | BD110: =(BB110-(AY110*5))*(1-1%) -> 774.2295 | BE110: =BD110 -> 774.2295 | BF110: =BD110 -> 774.2295
BG111: Werkt 144 uur p/4weken
B116: Asanty Raafenberg | E116: Fase 1-2 | F116: Stipp Basis | G116: 0 | H116: Bouw | I116: 25v 20rv | J116: T4.5 Starttabel 2e halfjaar | K116: Bouwvakhelper | L116: 16.83 | N116: =L116+M116 -> 16.83 | P116: =N116+O116 -> 16.83 | T116: 20 | U116: =T116/'Grondslag bouw & infra'!$B$50 -> 0.076628352 | V116: 14 | W116: 0 | X116: =(V116+W116)/'Grondslag bouw & infra'!$B$50 -> 0.053639847 | AC116: 5 | AD116: 6 | AE116: 0 | AF116: =(AC116+AD116+AE116)/'Grondslag bouw & infra'!$B$50 -> 0.042145594 | AH116: =(AQ116-'Grondslag bouw & infra'!$B$46)*'Grondslag bouw & infra'!$B$43 -> 0.24228962 | AI116: 0.0365 | AM116: =$AN$6*AN116 -> 0 | AQ116: =(P116*(AF116+AI116)+P116) -> 18.153605 | AV116: 0.68 | AW116: 1.1 | AX116: 0.48 | AY116: =SUM(AS116:AX116) -> 2.26 | AZ116: 90-XB-JF | BB116: =660+7.22-6.94 -> 660.28 | BC116: =2420.87/4 -> 605.2175 | BD116: =(BB116-(AY116*5))*(1-1%) -> 642.4902 | BE116: =BD116 -> 642.4902 | BF116: =BD116 -> 642.4902
B119: Patrick Serlier | D119: =853.55 -> 853.55 | E119: Fase 3 | F119: BPF Bouw | G119: 32 (4wk) | H119: Bouw | I119: 25v 20rv | J119: T4.2 FG.B | K119: Timmerman II | L119: 20.02 | N119: =L119+M119 -> 20.02 | P119: =N119+O119 -> 20.02 | T119: 20 | U119: =T119/'Grondslag bouw & infra'!$B$50 -> 0.076628352 | V119: 20 | W119: 0 | X119: =(V119+W119)/'Grondslag bouw & infra'!$B$50 -> 0.076628352 | AC119: 5 | AD119: 0 | AE119: 0 | AF119: =(AC119+AD119+AE119)/'Grondslag bouw & infra'!$B$50 -> 0.019157088 | AI119: 0.0365 | AM119: =$AN$6*AN119 -> 0 | AQ119: =(P119*(AF119+AI119)+P119) -> 21.134255 | AT119: 0.96 | AV119: 0.68 | AW119: 1.1 | AX119: 0.48 | AY119: =SUM(AS119:AX119) -> 3.22 | AZ119: VLT-24-V | BB119: =646+17.92+3.33+8.22 -> 675.47 | BC119: =2677.26/4 -> 669.315 | BD119: =(BB119-(AY119*5))*(1-1%) -> 652.7763 | BE119: =BD119 -> 652.7763 | BF119: =BD119 -> 652.7763
B123: Pieter van Houwelingen | D123: =111.89 -> 111.89 | E123: Fase 3 | F123: BPF UTA | G123: 32 (4wk) | H123: UTA | I123: 25v 15rv | J123: T4.9 FL1 FN4 SN2 (104%) | K123: Uitvoerder | L123: 23 | N123: =L123+M123 -> 23 | P123: =N123+O123 -> 23 | Q123: Inclusief | T123: 25 | U123: =T123/'Grondslag bouw & infra'!$B$50 -> 0.095785441 | V123: 8 | W123: 0 | X123: =(V123+W123)/'Grondslag bouw & infra'!$B$50 -> 0.030651341 | AC123: 0 | AD123: 7 | AE123: 0 | AF123: =(AC123+AD123+AE123)/'Grondslag bouw & infra'!$B$50 -> 0.026819923 | AI123: 0.023 | AK123: ='Grondslag bouw & infra'!C31 -> 20.667692 | AM123: =$AN$6*AN123 -> 0 | AQ123: =(P123*(AF123+AI123)+P123) -> 24.145858 | AV123: 0.68 | AW123: 1.1 | AX123: 0.48 | AY123: =SUM(AS123:AX123) -> 2.26 | AZ123: 0.25 | BB123: =((4104.12+101.22)/4)-74.75+25.15+49.1 -> 1050.835 | BC123: =3030.58/4 -> 757.645 | BD123: =(BB123-(AY123*5))*(1-1%) -> 1029.1397 | BE123: =BD123 -> 1029.1397 | BF123: =BD123 -> 1029.1397 | BG123: Incl. vakantiegeld, nettoafspraak is inclusief reiskosten
BG124: 32,5km enkele reis = 32,5*10*€ 0,23 = € 74,75
B125: John van der Wel | E125: Fase 1-2 | F125: Stipp | G125: 0 | H125: Bouw | I125: 25v 20rv | J125: T4.5 starttabel 1st halfjaar | K125: Bouwvakhelper | L125: 15.77 | N125: =L125+M125 -> 15.77 | P125: =N125 -> 15.77 | Q125: Inclusief | T125: 20 | U125: =T125/'Grondslag bouw & infra'!$B$50 -> 0.076628352 | V125: 5 | W125: 0 | X125: =(V125+W125)/'Grondslag bouw & infra'!$B$50 -> 0.019157088 | AC125: 5 | AD125: 15 | AE125: 0 | AF125: =(AC125+AD125+AE125)/'Grondslag bouw & infra'!$B$50 -> 0.076628352 | AH125: =(AQ125-'Grondslag bouw & infra'!$B$46)*'Grondslag bouw & infra'!$B$43 -> 0.22599208 | AI125: 0.0365 | AM125: 0 | AQ125: =(P125*(AF125+AI125)+P125) -> 17.554034 | AV125: 0.68 | AW125: 1.1 | AX125: 0.48 | AY125: =SUM(AS125:AX125) -> 2.26 | AZ125: 04-SP-VN | BB125: =628.48+17.5 -> 645.98 | BC125: =2500.6/4 -> 625.15 | BD125: =(BB125-(AY125*5))*(1-1%) -> 628.3332 | BE125: =BD125 -> 628.3332 | BF125: =BD125 -> 628.3332
B129: Marcel Spruijt | E129: Fase 3 | F129: BPF UTA | G129: 32 (4wk) | H129: UTA | I129: 25v 15rv | J129: T4.9 FL23 FN1 SN1 | K129: Intern onderhoudsmedewerker | L129: 15.77 | N129: =L129+M129 -> 15.77 | P129: =N129+O129 -> 15.77 | Q129: Inclusief | T129: 20 | U129: =T129/'Grondslag bouw & infra'!$B$50 -> 0.076628352 | V129: 5 | W129: 0 | X129: =(V129+W129)/'Grondslag bouw & infra'!$B$50 -> 0.019157088 | AC129: 5 | AD129: 10 | AE129: 0 | AF129: =(AC129+AD129+AE129)/'Grondslag bouw & infra'!$B$50 -> 0.057471264 | AI129: 0.023 | AM129: =$AN$6*AN129 -> 0 | AV129: 0.68 | AW129: 1.1 | AX129: 0.48 | AY129: =SUM(AS129:AX129) -> 2.26 | AZ129: 54-GVP-1 | BB129: =726.25+7.58+18.11 -> 751.94 | BC129: =2405.74/4 -> 601.435 | BD129: =BB129*0.917 -> 689.52898 | BE129: =BD129 -> 689.52898 | BF129: =BD129 -> 689.52898
B131: Michael Windhorst | E131: Fase 1-2 | F131: StiPP | G131: 0 | H131: Bouw | I131: 25v 20rv | J131: T4.2 FG.B | K131: Timmerman II | L131: 20.02 | N131: 20.02 | P131: 20.02 | Q131: Inclusief | T131: 20 | U131: 0.076628352 | V131: 0 | W131: 0 | X131: =(V131+W131)/'Grondslag bouw & infra'!$B$50 -> 0 | AC131: 5 | AD131: 20 | AE131: 0 | AF131: 0.038314176 | AH131: =(AQ131-'Grondslag bouw & infra'!$B$46)*'Grondslag bouw & infra'!$B$43 -> 0.33373461 | AI131: 0.0365 | AM131: 0 | AQ131: 21.51778 | AT131: 0.96 | AV131: 0.68 | AW131: 1.1 | AX131: 0.48 | AY131: 3.22 | AZ131: V-695-HK | BB131: 628 | BC131: =2418.99/4 -> 604.7475 | BD131: =(BB131-(AY131*5))*(1-1%) -> 605.781 | BE131: =BD131 -> 605.781 | BF131: =BD131 -> 605.781 | BG131: Bijtelling 22%
B134: Remco van Doorne | E134: Fase 1-2 | F134: Stipp | G134: 0 | H134: Bouw | I134: 25v 20rv | J134: T4.5 starttabel 1st halfjaar | K134: Bouwvakhelper | L134: 15.77 | N134: =L134+M134 -> 15.77 | P134: =N134 -> 15.77 | Q134: Inclusief | T134: 25 | U134: =T134/'Grondslag bouw & infra'!$B$50 -> 0.095785441 | V134: 20 | W134: 0 | X134: =(V134+W134)/'Grondslag bouw & infra'!$B$50 -> 0.076628352 | AC134: 0 | AD134: 0 | AE134: 0 | AF134: =(AC134+AD134+AE134)/'Grondslag bouw & infra'!$B$50 -> 0 | AH134: 0.23 | AI134: 0.0365 | AM134: 0 | AQ134: =(P134*(AF134+AI134)+P134) -> 16.345605 | AS134: 8.17 | AV134: 0.68 | AW134: 1.1 | AX134: 0.48 | AY134: =SUM(AS134:AX134) -> 10.43 | AZ134: 97-GFD-4 | BB134: =BC134-(5*AY134) -> 542.4925 | BC134: =2378.57/4 -> 594.6425 | BD134: =BB134 -> 542.4925 | BE134: =BD134 -> 542.4925 | BF134: =BD134 -> 542.4925
AI135: Reserveren
B138: Rob Valkenburg | D138: =147.34 -> 147.34 | E138: Fase 1-2 | F138: StiPP | G138: 0 | H138: Bouw | I138: 25v 20rv 7rvs | J138: T4.2 FG.B | K138: Timmerman II | L138: 20.02 | N138: =L138+M138 -> 20.02 | P138: =N138+O138 -> 20.02 | T138: 20 | U138: =T138/'Grondslag bouw & infra'!$B$50 -> 0.076628352 | V138: 15 | W138: 0 | X138: =(V138+W138)/'Grondslag bouw & infra'!$B$50 -> 0.057471264 | AC138: 5 | AD138: 5 | AE138: 7 | AF138: =(AC138+AD138+AE138)/'Grondslag bouw & infra'!$B$50 -> 0.0651341 | AH138: =(AQ138-'Grondslag bouw & infra'!$B$46)*'Grondslag bouw & infra'!$B$43 -> 0.34832957 | AI138: 0.0365 | AM138: =$AN$6*AN138 -> 0 | AQ138: =(P138*(AF138+AI138)+P138) -> 22.054715 | AT138: 0.96 | AV138: 0.68 | AW138: 1.1 | AX138: 0.48 | AY138: =SUM(AS138:AX138) -> 3.22 | AZ138: 0.32 | BB138: =724.8+7.11 -> 731.91 | BC138: =2809.26/4 -> 702.315 | BD138: =(BB138-(AY138*5))*(1-1%) -> 708.6519 | BE138: =BD138 -> 708.6519 | BF138: =BD138 -> 708.6519
B141: Herman Vos | E141: Fase 1-2 | F141: Stipp | G141: 0 | H141: Bouw | I141: 25v 20rv 10rvs | J141: T4.5 starttabel 1st halfjaar | K141: Bouwvakhelper | L141: 15.77 | N141: =L141+M141 -> 15.77 | P141: =N141+O141 -> 15.77 | Q141: Inclusief | T141: 20 | U141: =T141/'Grondslag bouw & infra'!$B$50 -> 0.076628352 | V141: 10 | W141: 0 | X141: =(V141+W141)/'Grondslag bouw & infra'!$B$50 -> 0.038314176 | AC141: 5 | AD141: 10 | AE141: 10 | AF141: 0.0728 | AH141: =(AQ141-'Grondslag bouw & infra'!$B$46)*'Grondslag bouw & infra'!$B$43 -> 0.22435101 | AI141: 0.0365 | AM141: 0 | AQ141: =(P141*(AF141+AI141)+P141) -> 17.493661 | AV141: 0.68 | AW141: 1.1 | AX141: 0.48 | AY141: =SUM(AS141:AX141) -> 2.26 | AZ141: V-210-JR | BB141: 750 | BC141: =2524.05/4 -> 631.0125 | BD141: =(BB141-(AY141*5))*(1-1%) -> 731.313 | BE141: =BD141 -> 731.313 | BF141: =BD141 -> 731.313 | BG141: € 1,44 per gewerkt uur lease bedrijfsauto
B143: Remco Groenendaal | E143: Fase 3 | F143: BPF Bouw | G143: 32 (4wk) | H143: Bouw | I143: 25v 20rv | J143: T4.2 FG.B | K143: Timmerman II | L143: 20.02 | N143: =L143+M143 -> 20.02 | P143: =N143+O143 -> 20.02 | T143: 20 | U143: =T143/'Grondslag bouw & infra'!$B$50 -> 0.076628352 | V143: 7 | W143: 0 | X143: =(V143+W143)/'Grondslag bouw & infra'!$B$50 -> 0.026819923 | AC143: 5 | AD143: 13 | AE143: 0 | AF143: =(AC143+AD143+AE143)/'Grondslag bouw & infra'!$B$50 -> 0.068965517 | AI143: 0.0365 | AM143: =$AN$6*AN143 -> 0 | AT143: 0.96 | AV143: 0.68 | AW143: 1.1 | AX143: 0.48 | AY143: =SUM(AS143:AX143) -> 3.22 | AZ143: 0.32 | BB143: =650+8.77+63.25 -> 722.02 | BC143: =2718.28/4 -> 679.57 | BD143: =(BB143-(AY143*5))*(1-1%) -> 698.8608 | BE143: =BD143 -> 698.8608 | BF143: =BD143 -> 698.8608
B147: Fred Termonen | E147: Fase 3 | F147: AOW | G147: 32 (4wk) | H147: UTA | I147: 25v 15rv 9rvs | J147: T4.9 FL23 FN1 SN1 | K147: Intern onderhoudsmedewerker | L147: 15.77 | N147: =L147+M147 -> 15.77 | P147: =N147+O147 -> 15.77 | T147: 20 | U147: =T147/'Grondslag bouw & infra'!$B$50 -> 0.076628352 | V147: 10 | W147: 0 | X147: =(V147+W147)/'Grondslag bouw & infra'!$B$50 -> 0.038314176 | AC147: 5 | AD147: 5 | AE147: 9 | AF147: =(AC147+AD147+AE147)/'Grondslag bouw & infra'!$B$50 -> 0.072796935 | AI147: 0.023 | AM147: =$AN$6*AN147 -> 0 | AV147: 0.68 | AW147: 1.1 | AX147: 0.48 | AY147: =SUM(AS147:AX147) -> 2.26 | AZ147: VBS-24-V | BB147: =(450/3*5)+11.12 -> 761.12 | BC147: =2795.59/4 -> 698.8975 | BD147: =(BB147-(AY147*5))*(1-1%) -> 742.3218 | BE147: =BD147 -> 742.3218 | BF147: =BD147 -> 742.3218
B149: Arnold Verstraten | D149: =202.45 -> 202.45 | E149: Fase 3 | F149: BPF Bouw | G149: 32 (4wk) | H149: Bouw | I149: 25v 20rv 6rvs | J149: T4.2 FG.A | K149: Bouwvakhelper | L149: 18.95 | N149: =L149+M149 -> 18.95 | P149: =N149+O149 -> 18.95 | T149: 20 | U149: =T149/'Grondslag bouw & infra'!$B$50 -> 0.076628352 | V149: 13 | W149: 6 | X149: =(V149+W149)/'Grondslag bouw & infra'!$B$50 -> 0.072796935 | AC149: 5 | AD149: 7 | AE149: 0 | AF149: =(AC149+AD149+AE149)/'Grondslag bouw & infra'!$B$50 -> 0.045977011 | AI149: 0.0365 | AM149: =$AN$6*AN149 -> 0 | AQ149: =(P149*(AF149+AI149)+P149) -> 20.512939 | AV149: 0.68 | AW149: 1.1 | AX149: 0.48 | AY149: =SUM(AS149:AX149) -> 2.26 | AZ149: 0.32 | BB149: =680+6.21+14.21 -> 700.42 | BC149: =2609.92/4 -> 652.48 | BD149: =(BB149-(AY149*5))*(1-1%) -> 682.2288 | BE149: =BD149 -> 682.2288 | BF149: =BD149 -> 682.2288

Sheet Loonstrook
B2: NIETS AAN VERANDEREN !!!
F3: Totaal | G3: Totaal | H3: Totaal | I3: Totaal | J3: Totaal
D4: Totaal | E4: Totaal | F4: uren | G4: uren | H4: uren | I4: uren | J4: uren | K4: Totaal | L4: Totaal | M4: Totaal wk 1-3 | N4: Totaal wk 4
D5: Dagen | E5: Uren | F5: VAK | G5: Ziek | H5: RV | I5: KV/C | J5: FD | K5: kilometers | L5: Extra | M5: reeds ontvangen | N5: nog te ontvangen
D6: ge- | E6: ge- | F6: Op- | G6: uren | H6: uren | I6: Door | J6: Door | K6: brandstof | L6: Decl. | M6: Netto | N6: Netto | O6: Te verrekenen | Q6: Alleen WKR telt mee; €185p/4wk
B7: Werknemer | C7: CAO | D7: werkt | E7: werkt | F7: name | I7: bet. | J7: bet. | K7: bedrag | L7: verg. overuur | M7: Voorschot | N7: Loon | O7: totaal 4 weken | P7: Opmerking | Q7: WKR vergoedingen | R7: Loonvoorschot strook
A8: 1 | B8: =Periode!B8 -> Ruben Hellemons | C8: =Periode!H8 -> UTA | D8: ='WK22'!D8+'WK21'!D8+'WK23'!D8+'WK24'!D8 -> 18 | E8: ='WK22'!E8+'WK21'!E8+'WK23'!E8+'WK24'!E8 -> 144 | F8: ='WK22'!F8+'WK21'!F8+'WK23'!F8+'WK24'!F8 -> 8 | G8: ='WK22'!G8+'WK21'!G8+'WK23'!G8+'WK24'!G8 -> 0 | H8: ='WK22'!H8+'WK21'!H8+'WK23'!H8+'WK24'!H8 -> 0 | I8: ='WK22'!I8+'WK21'!I8+'WK23'!I8+'WK24'!I8 -> 0 | J8: ='WK22'!J8+'WK21'!J8+'WK23'!J8+'WK24'!J8 -> 8 | K8: ='WK22'!N8+'WK21'!N8+'WK23'!N8+'WK24'!N8 -> 0 | L8: ='WK22'!P8+'WK21'!P8+'WK23'!P8+'WK24'!P8 -> 0 | M8: ='WK22'!Q8+'WK21'!Q8+'WK23'!Q8 -> 2156.0007 | N8: ='WK24'!Q8 -> 721.12 | O8: =M8+N8 -> 2877.1207 | Q8: =(378.99+11)+(194.1+22)+(168.21+16.5)+(175.41+16.5)+(169.29+15.4)+(152.21+19.8) -> 1339.41
A12: 2 | B12: =Periode!$B$12 -> Andre Sintenie | C12: =Periode!$H$12 -> SAVG | D12: ='WK22'!$D$12+'WK21'!$D$12+'WK23'!$D$12+'WK24'!$D$12 -> 13 | E12: ='WK22'!$E$12+'WK21'!$E$12+'WK23'!$E$12+'WK24'!$E$12 -> 104 | F12: ='WK22'!$F$12+'WK21'!$F$12+'WK23'!$F$12+'WK24'!$F$12 -> 0 | G12: ='WK22'!$G$12+'WK21'!$G$12+'WK23'!$G$12+'WK24'!$G$12 -> 7.6 | H12: ='WK22'!$H$12+'WK21'!$H$12+'WK23'!$H$12+'WK24'!$H$12 -> 0 | I12: ='WK22'!$I$12+'WK21'!$I$12+'WK23'!$I$12+'WK24'!$I$12 -> 0 | J12: ='WK22'!$J$12+'WK21'!$J$12+'WK23'!$J$12+'WK24'!$J$12 -> 8 | K12: ='WK22'!$N$12+'WK21'!$N$12+'WK23'!$N$12+'WK24'!$N$12 -> 0 | L12: ='WK22'!$P$12+'WK21'!$P$12+'WK23'!$P$12+'WK24'!$P$12 -> 0 | M12: ='WK22'!$Q$12+'WK21'!$Q$12+'WK23'!$Q$12 -> 1429.1565 | N12: ='WK24'!$Q$12 -> 524.128 | O12: =$N$12+$M$12 -> 1953.2845 | Q12: =(154.74+16)+(182.65+25.6)+(178.98+25.6)+(176.18+17.6)+(173.59+14.4)+(165.83+20.8) -> 1151.97
O14: ='WK24'!Q14 -> 121.76 | P14: Totaal:
A15: 3 | B15: =Periode!B15 -> Dennis Aarts | C15: =Periode!H15 -> UTA | D15: ='WK22'!D15+'WK21'!D15+'WK23'!D15+'WK24'!D15 -> 4 | E15: ='WK22'!E15+'WK21'!E15+'WK23'!E15+'WK24'!E15 -> 32 | F15: ='WK22'!F15+'WK21'!F15+'WK23'!F15+'WK24'!F15 -> 0 | G15: ='WK22'!G15+'WK21'!G15+'WK23'!G15+'WK24'!G15 -> 0 | H15: ='WK22'!H15+'WK21'!H15+'WK23'!H15+'WK24'!H15 -> 0 | I15: ='WK22'!I15+'WK21'!I15+'WK23'!I15+'WK24'!I15 -> 32 | J15: ='WK22'!J15+'WK21'!J15+'WK23'!J15+'WK24'!J15 -> 8 | K15: ='WK22'!N15+'WK21'!N15+'WK23'!N15+'WK24'!N15 -> 0 | L15: ='WK22'!P15+'WK21'!P15+'WK23'!P15+'WK24'!P15 -> 0 | M15: ='WK22'!Q15+'WK21'!Q15+'WK23'!Q15 -> 685.4364 | N15: ='WK24'!Q15 -> 1248.3644 | O15: =N15 -> 1248.3644 | P15: =O15+O14 -> 1370.1244 | Q15: =(13.2)+(16.5)+(15.4)+(14.3)+(12.1)+(4.4) -> 75.9 | R15: =-87.32-38.29+22.49+103.12 -> 0
A17: 4 | B17: =Periode!B17 -> Kay Sanders | C17: =Periode!H17 -> Bouw | D17: ='WK22'!D17+'WK21'!D17+'WK23'!D17+'WK24'!D17 -> 0 | E17: ='WK22'!E17+'WK21'!E17+'WK23'!E17+'WK24'!E17 -> 0 | F17: ='WK22'!F17+'WK21'!F17+'WK23'!F17+'WK24'!F17 -> 0 | G17: ='WK22'!G17+'WK21'!G17+'WK23'!G17+'WK24'!G17 -> 0 | H17: ='WK22'!H17+'WK21'!H17+'WK23'!H17+'WK24'!H17 -> 0 | I17: ='WK22'!I17+'WK21'!I17+'WK23'!I17+'WK24'!I17 -> 0 | J17: ='WK22'!J17+'WK21'!J17+'WK23'!J17+'WK24'!J17 -> 0 | K17: ='WK22'!N17+'WK21'!N17+'WK23'!N17+'WK24'!N17 -> 0 | L17: ='WK22'!P17+'WK21'!P17+'WK23'!P17+'WK24'!P17 -> 296.04 | M17: ='WK22'!Q17+'WK21'!Q17+'WK23'!Q17 -> 0 | N17: ='WK24'!Q17 -> 296.04 | O17: =M17+N17 -> 296.04
B20: =Periode!B20 -> Eric Snepvangers | C20: =Periode!H20 -> Bouw | D20: ='WK22'!$D$20+'WK21'!$D$20+'WK23'!$D$20+'WK24'!$D$20 -> 0 | E20: ='WK22'!$E$20+'WK21'!$E$20+'WK23'!$E$20+'WK24'!$E$20 -> 0 | F20: ='WK22'!$F$20+'WK21'!$F$20+'WK23'!$F$20+'WK24'!$F$20 -> 0 | G20: ='WK22'!$G$20+'WK21'!$G$20+'WK23'!$G$20+'WK24'!$G$20 -> 0 | H20: ='WK22'!$H$20+'WK21'!$H$20+'WK23'!$H$20+'WK24'!$H$20 -> 0 | I20: ='WK22'!$I$20+'WK21'!$I$20+'WK23'!$I$20+'WK24'!$I$20 -> 0 | J20: ='WK22'!$J$20+'WK21'!$J$20+'WK23'!$J$20+'WK24'!$J$20 -> 0 | K20: ='WK22'!$N$20+'WK21'!$N$20+'WK23'!$N$20+'WK24'!$N$20 -> 0 | L20: ='WK22'!$P$20+'WK21'!$P$20+'WK23'!$P$20+'WK24'!$P$20 -> 0 | M20: ='WK22'!$Q$20+'WK21'!$Q$20+'WK23'!$Q$20 -> 0 | N20: ='WK24'!$Q$20 -> 0 | O20: =M20+N20 -> 0 | P20: Vergoeding zorg € 20,67 | Q20: =(146.84+5.5)+(150.91+17.6)+(158.05+17.6)+(6.34+2.2) -> 505.04
C21: =Periode!$H$21 -> 0 | D21: ='WK22'!$D$21+'WK21'!$D$21+'WK23'!$D$21+'WK24'!$D$21 -> 0 | E21: ='WK22'!$E$21+'WK21'!$E$21+'WK23'!$E$21+'WK24'!$E$21 -> 0 | F21: ='WK22'!$F$21+'WK21'!$F$21+'WK23'!$F$21+'WK24'!$F$21 -> 0 | G21: ='WK22'!$G$21+'WK21'!$G$21+'WK23'!$G$21+'WK24'!$G$21 -> 0 | H21: ='WK22'!$H$21+'WK21'!$H$21+'WK23'!$H$21+'WK24'!$H$21 -> 0 | I21: ='WK22'!$I$21+'WK21'!$I$21+'WK23'!$I$21+'WK24'!$I$21 -> 0 | J21: ='WK22'!$J$21+'WK21'!$J$21+'WK23'!$J$21+'WK24'!$J$21 -> 0 | K21: ='WK22'!$N$21+'WK21'!$N$21+'WK23'!$N$21+'WK24'!$N$21 -> 0 | M21: ='WK22'!$Q$21+'WK21'!$Q$21+'WK23'!$Q$21 -> 0 | N21: ='WK24'!$Q$21 -> 0 | O21: =$M$21+$N$21 -> 0
C22: =Periode!H22 -> 0 | D22: ='WK22'!D22+'WK21'!D22+'WK23'!D22+'WK24'!D22 -> 0 | E22: ='WK22'!E22+'WK21'!E22+'WK23'!E22+'WK24'!E22 -> 0 | F22: ='WK22'!F22+'WK21'!F22+'WK23'!F22+'WK24'!F22 -> 0 | G22: ='WK22'!G22+'WK21'!G22+'WK23'!G22+'WK24'!G22 -> 0 | H22: ='WK22'!H22+'WK21'!H22+'WK23'!H22+'WK24'!H22 -> 0 | I22: ='WK22'!I22+'WK21'!I22+'WK23'!I22+'WK24'!I22 -> 0 | J22: ='WK22'!J22+'WK21'!J22+'WK23'!J22+'WK24'!J22 -> 0 | K22: ='WK22'!O22+'WK21'!O22+'WK23'!O22+'WK24'!O22 -> 0 | M22: ='WK22'!Q22+'WK21'!Q22+'WK23'!Q22 -> 0 | N22: ='WK24'!Q22 -> 0 | O22: =M22+N22 -> 0
A23: 5 | B23: =Periode!$B$23 -> Frank Stouthart | C23: =Periode!$H$23 -> Bouw | D23: ='WK22'!$D$23+'WK21'!$D$23+'WK23'!$D$23+'WK24'!$D$23 -> 18 | E23: ='WK22'!$E$23+'WK21'!$E$23+'WK23'!$E$23+'WK24'!$E$23 -> 141 | F23: ='WK22'!$F$23+'WK21'!$F$23+'WK23'!$F$23+'WK24'!$F$23 -> 8 | G23: ='WK22'!$G$23+'WK21'!$G$23+'WK23'!$G$23+'WK24'!$G$23 -> 0 | H23: ='WK22'!$H$23+'WK21'!$H$23+'WK23'!$H$23+'WK24'!$H$23 -> 0 | I23: ='WK22'!$I$23+'WK21'!$I$23+'WK23'!$I$23+'WK24'!$I$23 -> 0 | J23: ='WK22'!$J$23+'WK21'!$J$23+'WK23'!$J$23+'WK24'!$J$23 -> 8 | K23: ='WK22'!$N$23+'WK21'!$N$23+'WK23'!$N$23+'WK24'!$N$23 -> 1238 | L23: ='WK22'!$P$23+'WK21'!$P$23+'WK23'!$P$23+'WK24'!$P$23 -> 0 | M23: ='WK22'!$Q$23+'WK21'!$Q$23+'WK23'!$Q$23 -> 2323.5253 | N23: ='WK24'!$Q$23 -> 786.063 | O23: =$M$23+$N$23 -> 3109.5883 | P23: Vergoeding zorg € 20,67 | Q23: =(33.4+14.3)+(8.18+14.3)+(88.76+20.9)+(81.86+18.7)+(135.16+17.6)+(100.57+19.8) -> 553.53
A26: 6 | B26: =Periode!B26 -> Roy Rubeling | C26: =Periode!H26 -> Bouw | D26: ='WK22'!D26+'WK21'!D26+'WK23'!D26+'WK24'!D26 -> 14 | E26: ='WK22'!E26+'WK21'!E26+'WK23'!E26+'WK24'!E26 -> 112 | F26: ='WK22'!F26+'WK21'!F26+'WK23'!F26+'WK24'!F26 -> 0 | G26: ='WK22'!G26+'WK21'!G26+'WK23'!G26+'WK24'!G26 -> 0 | H26: ='WK22'!H26+'WK21'!H26+'WK23'!H26+'WK24'!H26 -> 0 | I26: ='WK22'!I26+'WK21'!I26+'WK23'!I26+'WK24'!I26 -> 0 | J26: ='WK22'!J26+'WK21'!J26+'WK23'!J26+'WK24'!J26 -> 8 | K26: ='WK22'!N26+'WK21'!N26+'WK23'!N26+'WK24'!N26 -> 1988 | L26: ='WK22'!P26+'WK21'!P26+'WK23'!P26+'WK24'!P26 -> 283.62 | M26: ='WK22'!Q26+'WK21'!Q26+'WK23'!Q26 -> 2043.8626 | N26: ='WK24'!Q26 -> 1042.66 | O26: =M26+N26 -> 3086.5226 | Q26: =(0.02+13.2)+(0.32+22)+(0)+(176.85+16.5)+(222.26+15.4)+(137.93+15.4) -> 619.88
A33: 7 | B33: =Periode!B33 -> Marco Govers | C33: =Periode!H33 -> UTA | D33: ='WK22'!D33+'WK21'!D33+'WK23'!D33+'WK24'!D33 -> 19 | E33: ='WK22'!E33+'WK21'!E33+'WK23'!E33+'WK24'!E33 -> 148.5 | F33: ='WK22'!F33+'WK21'!F33+'WK23'!F33+'WK24'!F33 -> 0 | G33: ='WK22'!G33+'WK21'!G33+'WK23'!G33+'WK24'!G33 -> 0 | H33: ='WK22'!H33+'WK21'!H33+'WK23'!H33+'WK24'!H33 -> 0 | I33: ='WK22'!I33+'WK21'!I33+'WK23'!I33+'WK24'!I33 -> 3.5 | J33: ='WK22'!J33+'WK21'!J33+'WK23'!J33+'WK24'!J33 -> 8 | K33: ='WK22'!N33+'WK21'!N33+'WK23'!N33+'WK24'!N33 -> 1482 | L33: ='WK22'!P33+'WK21'!P33+'WK23'!P33+'WK24'!P33 -> 0 | M33: ='WK22'!Q33+'WK21'!Q33+'WK23'!Q33 -> 2626.6552 | N33: ='WK24'!Q33 -> 883.69978 | O33: =M33+N33 -> 3510.355 | P33: Vergoeding zorg € 20,67 | Q33: =(306.1+15.4)+(155.56+11)+(189.13+22)+(140.87+20.9)+(181+18.7)+(125.51+20.9) -> 1207.07
A35: 8 | B35: =Periode!$B$35 -> Onno de Vries | C35: =Periode!$H$35 -> Bouw | D35: ='WK22'!$D$35+'WK21'!$D$35+'WK23'!$D$35+'WK24'!$D$35 -> 19 | E35: ='WK22'!$E$35+'WK21'!$E$35+'WK23'!$E$35+'WK24'!$E$35 -> 152 | F35: ='WK22'!$F$35+'WK21'!$F$35+'WK23'!$F$35+'WK24'!$F$35 -> 0 | G35: ='WK22'!$G$35+'WK21'!$G$35+'WK23'!$G$35+'WK24'!$G$35 -> 0 | H35: ='WK22'!$H$35+'WK21'!$H$35+'WK23'!$H$35+'WK24'!$H$35 -> 0 | I35: ='WK22'!$I$35+'WK21'!$I$35+'WK23'!$I$35+'WK24'!$I$35 -> 0 | J35: ='WK22'!$J$35+'WK21'!$J$35+'WK23'!$J$35+'WK24'!$J$35 -> 8 | K35: ='WK22'!$N$35+'WK21'!$N$35+'WK23'!$N$35+'WK24'!$N$35 -> 380 | L35: ='WK22'!$P$35+'WK21'!$P$35+'WK23'!$P$35+'WK24'!$P$35 -> 0 | M35: ='WK22'!$Q$35+'WK21'!$Q$35+'WK23'!$Q$35 -> 1974.9609 | N35: ='WK24'!$Q$35 -> 661.355 | O35: =$M$35+$N$35 -> 2636.3159 | P35: Totaal: | Q35: =(11)+(22)+(22)+(19.8)+(11)+(20.9) -> 106.7 | R35: =-29.88-48.5-155.87 -> -234.25
O36: ='WK24'!Q34 -> 13.59 | P36: =O35+O36 -> 2649.9059
A39: 9 | B39: =Periode!$B$39 -> Jan Levering | C39: =Periode!$H$39 -> UTA | D39: ='WK22'!$D$39+'WK21'!$D$39+'WK23'!$D$39+'WK24'!$D$39 -> 0 | E39: ='WK22'!$E$39+'WK21'!$E$39+'WK23'!$E$39+'WK24'!$E$39 -> 0 | F39: ='WK22'!$F$39+'WK21'!$F$39+'WK23'!$F$39+'WK24'!$F$39 -> 0 | G39: ='WK22'!$G$39+'WK21'!$G$39+'WK23'!$G$39+'WK24'!$G$39 -> 0 | H39: ='WK22'!$H$39+'WK21'!$H$39+'WK23'!$H$39+'WK24'!$H$39 -> 0 | I39: ='WK22'!$I$39+'WK21'!$I$39+'WK23'!$I$39+'WK24'!$I$39 -> 0 | J39: ='WK22'!$J$39+'WK21'!$J$39+'WK23'!$J$39+'WK24'!$J$39 -> 0 | K39: ='WK22'!$N$39+'WK21'!$N$39+'WK23'!$N$39+'WK24'!$N$39 -> 0 | L39: ='WK22'!$P$39+'WK21'!$P$39+'WK23'!$P$39+'WK24'!$P$39 -> 573.48 | M39: ='WK22'!$Q$39+'WK21'!$Q$39+'WK23'!$Q$39 -> 430.11 | N39: ='WK24'!$Q$39 -> 143.37 | O39: =$M$39+$N$39 -> 573.48 | P39: Vergoeding zorg € 20,67 | Q39: =(181.56+15.4)+(-0.15+17.6)+(115.54+9.9)+(-16.1)+(-107.28)+(0.13)+(0.13) -> 216.73 | R39: =-53.64+53.64 -> 0
O41: ='WK24'!Q41 -> 0 | P41: Totaal:
A42: 10 | B42: =Periode!$B$42 -> Alex van der Laan | C42: =Periode!$H$42 -> UTA | D42: ='WK22'!$D$42+'WK21'!$D$42+'WK23'!$D$42+'WK24'!$D$42 -> 7 | E42: ='WK22'!$E$42+'WK21'!$E$42+'WK23'!$E$42+'WK24'!$E$42 -> 52 | F42: ='WK22'!$F$42+'WK21'!$F$42+'WK23'!$F$42+'WK24'!$F$42 -> 64 | G42: ='WK22'!$G$42+'WK21'!$G$42+'WK23'!$G$42+'WK24'!$G$42 -> 0 | H42: ='WK22'!$H$42+'WK21'!$H$42+'WK23'!$H$42+'WK24'!$H$42 -> 24 | I42: ='WK22'!$I$42+'WK21'!$I$42+'WK23'!$I$42+'WK24'!$I$42 -> 8 | J42: ='WK22'!$J$42+'WK21'!$J$42+'WK23'!$J$42+'WK24'!$J$42 -> 8 | K42: ='WK22'!$N$42+'WK21'!$N$42+'WK23'!$N$42+'WK24'!$N$42 -> 0 | L42: ='WK22'!$P$42+'WK21'!$P$42+'WK23'!$P$42+'WK24'!$P$42 -> 0 | M42: ='WK22'!$Q$42+'WK21'!$Q$42+'WK23'!$Q$42 -> 1918.026 | N42: ='WK24'!$Q$42 -> 662.9953 | O42: =$M$42+$N$42 -> 2581.0213 | P42: =O42+O41 -> 2581.0213 | Q42: =(16.5)+(16.5)+(22)+(19.8)+(19.8)+(7.7) -> 102.3 | R42: =-33.25-9.75-48.21 -> -91.21
C43: =Periode!H43 -> 0 | D43: ='WK22'!D43+'WK21'!D43+'WK23'!D43+'WK24'!D43 -> 0 | E43: ='WK22'!E43+'WK21'!E43+'WK23'!E43+'WK24'!E43 -> 0 | F43: ='WK22'!F43+'WK21'!F43+'WK23'!F43+'WK24'!F43 -> 0 | G43: ='WK22'!G43+'WK21'!G43+'WK23'!G43+'WK24'!G43 -> 0 | H43: ='WK22'!H43+'WK21'!H43+'WK23'!H43+'WK24'!H43 -> 0 | I43: ='WK22'!I43+'WK21'!I43+'WK23'!I43+'WK24'!I43 -> 0 | J43: ='WK22'!J43+'WK21'!J43+'WK23'!J43+'WK24'!J43 -> 0 | K43: ='WK22'!O43+'WK21'!O43+'WK23'!O43+'WK24'!O43 -> 0 | M43: ='WK22'!Q43+'WK21'!Q43+'WK23'!Q43 -> 0 | P43: Vergoeding zorg € 20,67
O45: ='WK24'!Q45+'WK24'!Q44 -> 131.18 | P45: Totaal: | R45: Schuld TGN:
A46: 11 | B46: =Periode!B46 -> Shafieq Asgarali | C46: =Periode!H46 -> SAVG | D46: ='WK22'!D46+'WK21'!D46+'WK23'!D46+'WK24'!D46 -> 19 | E46: ='WK22'!E46+'WK21'!E46+'WK23'!E46+'WK24'!E46 -> 138.5 | F46: ='WK22'!F46+'WK21'!F46+'WK23'!F46+'WK24'!F46 -> 0 | G46: ='WK22'!G46+'WK21'!G46+'WK23'!G46+'WK24'!G46 -> 0 | H46: ='WK22'!H46+'WK21'!H46+'WK23'!H46+'WK24'!H46 -> 0 | I46: ='WK22'!I46+'WK21'!I46+'WK23'!I46+'WK24'!I46 -> 0 | J46: ='WK22'!J46+'WK21'!J46+'WK23'!J46+'WK24'!J46 -> 7.5 | K46: ='WK22'!N46+'WK21'!N46+'WK23'!N46+'WK24'!N46 -> 0 | L46: ='WK22'!P46+'WK21'!P46+'WK23'!P46+'WK24'!P46 -> 221.35 | M46: ='WK22'!Q46+'WK21'!Q46+'WK23'!Q46 -> 1505.4484 | N46: ='WK24'!Q46 -> 522.19531 | O46: =M46+N46 -> 2027.6437 | P46: =O46+O45+O44 -> 2158.8238 | Q46: =(140.7+22.4)+(190.23+30.4)+(150.75+24)+(167.5+27.2)+(170.85+27.2)+(185.59+30.4) -> 1167.22 | R46: 3650 | S46: 27-11-25 bet
O47: ='WK24'!Q47 -> 153.62 | P47: Totaal: | S47: Betaald aan loonbeslag:
A48: 12 | B48: =Periode!$B$48 -> Sander van den Hoek | C48: =Periode!$H$48 -> UTA | D48: ='WK22'!$D$48+'WK21'!$D$48+'WK23'!$D$48+'WK24'!$D$48 -> 10 | E48: ='WK22'!$E$48+'WK21'!$E$48+'WK23'!$E$48+'WK24'!$E$48 -> 76 | F48: ='WK22'!$F$48+'WK21'!$F$48+'WK23'!$F$48+'WK24'!$F$48 -> 0 | G48: ='WK22'!$G$48+'WK21'!$G$48+'WK23'!$G$48+'WK24'!$G$48 -> 66.6 | H48: ='WK22'!$H$48+'WK21'!$H$48+'WK23'!$H$48+'WK24'!$H$48 -> 0 | I48: ='WK22'!$I$48+'WK21'!$I$48+'WK23'!$I$48+'WK24'!$I$48 -> 0 | J48: ='WK22'!$J$48+'WK21'!$J$48+'WK23'!$J$48+'WK24'!$J$48 -> 0 | K48: ='WK22'!$N$48+'WK21'!$N$48+'WK23'!$N$48+'WK24'!$N$48 -> 560 | L48: ='WK22'!P48+'WK21'!P48+'WK23'!P48+'WK24'!P48 -> 113.6 | M48: ='WK22'!$Q$48+'WK21'!$Q$48+'WK23'!$Q$48 -> 1630.2289 | N48: ='WK24'!$Q$48 -> 672.97875 | O48: =$M$48+$N$48 -> 2303.2076 | P48: =O48+O47 -> 2456.8276 | Q48: =(127.4+15.4)+(182+22)+(182+22)+(163.8+19.8)+(145.6+17.6)+(91+11) -> 999.6 | S48: =(226.69+570.79)+(287.5+200.18+50.64)+(98.17+684.57)+(353.13+598.49)+(367.13+584.49)+(325.13+575.77)+(255.13+655.41)+(302.51+699.8) -> 6835.53
B51: =Periode!B51 -> Marcel van Zandwijk | C51: =Periode!H51 -> UTA | D51: ='WK22'!D51+'WK21'!D51+'WK23'!D51+'WK24'!D51 -> 0 | E51: ='WK22'!E51+'WK21'!E51+'WK23'!E51+'WK24'!E51 -> 0 | F51: ='WK22'!F51+'WK21'!F51+'WK23'!F51+'WK24'!F51 -> 0 | G51: ='WK22'!G51+'WK21'!G51+'WK23'!G51+'WK24'!G51 -> 0 | H51: ='WK22'!H51+'WK21'!H51+'WK23'!H51+'WK24'!H51 -> 0 | I51: ='WK22'!I51+'WK21'!I51+'WK23'!I51+'WK24'!I51 -> 0 | J51: ='WK22'!J51+'WK21'!J51+'WK23'!J51+'WK24'!J51 -> 0 | K51: ='WK22'!$N$51+'WK21'!$N$51+'WK23'!$N$51+'WK24'!$N$51 -> 0 | L51: ='WK22'!$P$51+'WK21'!$P$51+'WK23'!$P$51+'WK24'!$P$51 -> 0 | M51: ='WK22'!Q51+'WK21'!Q51+'WK23'!Q51 -> 0 | N51: ='WK24'!Q51 -> 0 | O51: =$M$51+$N$51 -> 0 | P51: Max 185,- P/periode betalen: | Q51: =(222.27)+(173.57)+(158.64)+192.62-26.89 -> 720.21
C52: =Periode!H52 -> 0 | D52: ='WK22'!D52+'WK21'!D52+'WK23'!D52+'WK24'!D52 -> 0 | E52: ='WK22'!E52+'WK21'!E52+'WK23'!E52+'WK24'!E52 -> 0 | F52: ='WK22'!F52+'WK21'!F52+'WK23'!F52+'WK24'!F52 -> 0 | G52: ='WK22'!G52+'WK21'!G52+'WK23'!G52+'WK24'!G52 -> 0 | H52: ='WK22'!H52+'WK21'!H52+'WK23'!H52+'WK24'!H52 -> 0 | I52: ='WK22'!I52+'WK21'!I52+'WK23'!I52+'WK24'!I52 -> 0 | J52: ='WK22'!J52+'WK21'!J52+'WK23'!J52+'WK24'!J52 -> 0 | K52: ='WK22'!O52+'WK21'!O52+'WK23'!O52+'WK24'!O52 -> 0 | M52: ='WK22'!Q52+'WK21'!Q52+'WK23'!Q52 -> 0 | N52: ='WK24'!Q52 -> 0 | O52: =M52+N52 -> 0
A53: 13 | B53: =Periode!$B$53 -> Ronald van Maanen | C53: =Periode!H53 -> Bouw | D53: ='WK22'!$D$53+'WK21'!$D$53+'WK23'!$D$53+'WK24'!$D$53 -> 19 | E53: ='WK22'!$E$53+'WK21'!$E$53+'WK23'!$E$53+'WK24'!$E$53 -> 149.5 | F53: ='WK22'!$F$53+'WK21'!$F$53+'WK23'!$F$53+'WK24'!$F$53 -> 0 | G53: ='WK22'!$G$53+'WK21'!$G$53+'WK23'!$G$53+'WK24'!$G$53 -> 0 | H53: ='WK22'!$H$53+'WK21'!$H$53+'WK23'!$H$53+'WK24'!$H$53 -> 0 | I53: ='WK22'!$I$53+'WK21'!$I$53+'WK23'!$I$53+'WK24'!$I$53 -> 0 | J53: ='WK22'!$J$53+'WK21'!$J$53+'WK23'!$J$53+'WK24'!$J$53 -> 8 | K53: ='WK22'!$N$53+'WK21'!$N$53+'WK23'!$N$53+'WK24'!$N$53 -> 1862 | L53: ='WK22'!$P$53+'WK21'!$P$53+'WK23'!$P$53+'WK24'!$P$53 -> 0 | M53: ='WK22'!$Q$53+'WK21'!$Q$53+'WK23'!$Q$53 -> 2542.5932 | N53: ='WK24'!$Q$53 -> 861.28438 | O53: =$M$53+$N$53 -> 3403.8776 | Q53: =(67.66+16.5)+(132.76+22)+(176.42+17.6)+(136.21+19.8)+(135.04+18.7)+(142.67+20.9) -> 906.26
O56: ='WK24'!Q56 -> 60.63 | P56: Totaal:
A57: 14 | B57: =Periode!B57 -> Erik Visser | C57: =Periode!H57 -> UTA | D57: ='WK22'!D57+'WK21'!D57+'WK23'!D57+'WK24'!D57 -> 17 | E57: ='WK22'!E57+'WK21'!E57+'WK23'!E57+'WK24'!E57 -> 125.5 | F57: ='WK22'!F57+'WK21'!F57+'WK23'!F57+'WK24'!F57 -> 16 | G57: ='WK22'!G57+'WK21'!G57+'WK23'!G57+'WK24'!G57 -> 0 | H57: ='WK22'!H57+'WK21'!H57+'WK23'!H57+'WK24'!H57 -> 0 | I57: ='WK22'!I57+'WK21'!I57+'WK23'!I57+'WK24'!I57 -> 0 | J57: ='WK22'!J57+'WK21'!J57+'WK23'!J57+'WK24'!J57 -> 8 | K57: ='WK22'!$N$57+'WK21'!$N$57+'WK23'!$N$57+'WK24'!$N$57 -> 1242 | L57: ='WK22'!$P$57+'WK21'!$P$57+'WK23'!$P$57+'WK24'!$P$57 -> 100.98 | M57: ='WK22'!Q57+'WK21'!Q57+'WK23'!Q57 -> 1865.6973 | N57: ='WK24'!Q57 -> 651.06692 | O57: =M57+N57 -> 2516.7643 | P57: =O57+O56 -> 2577.3943 | Q57: =(27.3)+(23.14)+(23.4)+(37.05)+(34.06)+(32.63) -> 177.58 | R57: =-69.26-27.4-13.31-43.58+153.55 -> 0
P59: Totaal:
B60: =Periode!B60 -> Dirk Nouwens | C60: =Periode!H60 -> UTA | D60: ='WK22'!D60+'WK21'!D60+'WK23'!D60+'WK24'!D60 -> 0 | E60: ='WK22'!E60+'WK21'!E60+'WK23'!E60+'WK24'!E60 -> 0 | F60: ='WK22'!F60+'WK21'!F60+'WK23'!F60+'WK24'!F60 -> 0 | G60: ='WK22'!G60+'WK21'!G60+'WK23'!G60+'WK24'!G60 -> 0 | H60: ='WK22'!H60+'WK21'!H60+'WK23'!H60+'WK24'!H60 -> 0 | I60: ='WK22'!I60+'WK21'!I60+'WK23'!I60+'WK24'!I60 -> 0 | J60: ='WK22'!J60+'WK21'!J60+'WK23'!J60+'WK24'!J60 -> 0 | K60: ='WK22'!N60+'WK21'!N60+'WK23'!N60+'WK24'!N60 -> 0 | L60: ='WK22'!P60+'WK21'!P60+'WK23'!P60+'WK24'!P60 -> 0 | M60: ='WK22'!Q60+'WK21'!Q60+'WK23'!Q60 -> 0 | N60: ='WK24'!Q60 -> 0 | O60: =M60+N60 -> 0 | P60: =O60+O59 -> 0 | Q60: =(4.39+12.1)+(15.4)+(6.6)+(7.7) -> 46.19 | R60: =-47.65-29.43+77.08 -> 0
O62: ='WK24'!Q62 -> 123.82 | P62: Totaal:
A63: 15 | B63: =Periode!B63 -> Youri Nouwens | C63: =Periode!H63 -> SAVG | D63: ='WK22'!D63+'WK21'!D63+'WK23'!D63+'WK24'!D63 -> 0 | E63: ='WK22'!E63+'WK21'!E63+'WK23'!E63+'WK24'!E63 -> 150 | F63: ='WK22'!F63+'WK21'!F63+'WK23'!F63+'WK24'!F63 -> 0 | G63: ='WK22'!G63+'WK21'!G63+'WK23'!G63+'WK24'!G63 -> 0 | H63: ='WK22'!H63+'WK21'!H63+'WK23'!H63+'WK24'!H63 -> 0 | I63: ='WK22'!I63+'WK21'!I63+'WK23'!I63+'WK24'!I63 -> 0 | J63: ='WK22'!J63+'WK21'!J63+'WK23'!J63+'WK24'!J63 -> 0 | K63: ='WK22'!$N$63+'WK21'!$N$63+'WK23'!$N$63+'WK24'!$N$63 -> 0 | L63: ='WK22'!$P$63+'WK21'!$P$63+'WK23'!$P$63+'WK24'!$P$63 -> 0 | M63: ='WK22'!Q63+'WK21'!Q63+'WK23'!Q63 -> 1391.8359 | N63: ='WK24'!Q63 -> 463.94531 | O63: =M63+N63 -> 1855.7812 | P63: =O63+O62+O64 -> 1979.6012 | Q63: =(150.02+24)+(179.56+30.4)+(95.14+16)+(67.67+11.2)+(0) -> 573.99
A70: 16 | B70: =Periode!B70 -> Marco Booij | C70: =Periode!H70 -> Schilder | D70: ='WK22'!D70+'WK21'!D70+'WK23'!D70+'WK24'!D70 -> 0 | E70: ='WK22'!E70+'WK21'!E70+'WK23'!E70+'WK24'!E70 -> 0 | F70: ='WK22'!F70+'WK21'!F70+'WK23'!F70+'WK24'!F70 -> 0 | G70: ='WK22'!G70+'WK21'!G70+'WK23'!G70+'WK24'!G70 -> 0 | H70: ='WK22'!H70+'WK21'!H70+'WK23'!H70+'WK24'!H70 -> 0 | I70: ='WK22'!I70+'WK21'!I70+'WK23'!I70+'WK24'!I70 -> 0 | J70: ='WK22'!J70+'WK21'!J70+'WK23'!J70+'WK24'!J70 -> 0 | K70: ='WK22'!$N$70+'WK21'!$N$70+'WK23'!$N$70+'WK24'!$N$70 -> 0 | L70: ='WK22'!$P$70+'WK21'!$P$70+'WK23'!$P$70+'WK24'!$P$70 -> 686.6 | M70: ='WK22'!Q70+'WK21'!Q70+'WK23'!Q70 -> 514.95 | N70: ='WK24'!Q70 -> 171.65 | O70: =M70+N70 -> 686.6
A74: 17 | B74: =Periode!B74 -> Kevin Schuiling | C74: =Periode!H74 -> Bouw | D74: ='WK22'!D74+'WK21'!D74+'WK23'!D74+'WK24'!D74 -> 18 | E74: ='WK22'!E74+'WK21'!E74+'WK23'!E74+'WK24'!E74 -> 139.5 | F74: ='WK22'!F74+'WK21'!F74+'WK23'!F74+'WK24'!F74 -> 0 | G74: ='WK22'!G74+'WK21'!G74+'WK23'!G74+'WK24'!G74 -> 0 | H74: ='WK22'!H74+'WK21'!H74+'WK23'!H74+'WK24'!H74 -> 0 | I74: ='WK22'!I74+'WK21'!I74+'WK23'!I74+'WK24'!I74 -> 0 | J74: ='WK22'!J74+'WK21'!J74+'WK23'!J74+'WK24'!J74 -> 8 | K74: ='WK22'!$N$74+'WK21'!$N$74+'WK23'!$N$74+'WK24'!$N$74 -> 2074 | L74: ='WK22'!$P$74+'WK21'!$P$74+'WK23'!$P$74+'WK24'!$P$74 -> 0 | M74: ='WK22'!Q74+'WK21'!Q74+'WK23'!Q74 -> 2027.3826 | N74: ='WK24'!Q74 -> 762.4 | O74: =M74+N74 -> 2789.7826 | P74: LET op inhouden tabelvoordeel ter inlossing geldlening | Q74: =(14.3)+(11)+(20.9)+(19.8)+(16.5)+(19.8) -> 102.3 | S74: Aflossing geldlening:
S75: =5000-158.29-126.98-305.82-281.58-358.95-358.23 -> 3410.15
A77: 18 | B77: =Periode!B77 -> Steven Lamers | C77: =Periode!H77 -> Bouw | D77: ='WK22'!D77+'WK21'!D77+'WK23'!D77+'WK24'!D77 -> 18 | E77: ='WK22'!E77+'WK21'!E77+'WK23'!E77+'WK24'!E77 -> 139.5 | F77: ='WK22'!F77+'WK21'!F77+'WK23'!F77+'WK24'!F77 -> 0 | G77: ='WK22'!G77+'WK21'!G77+'WK23'!G77+'WK24'!G77 -> 0 | H77: ='WK22'!H77+'WK21'!H77+'WK23'!H77+'WK24'!H77 -> 0 | I77: ='WK22'!I77+'WK21'!I77+'WK23'!I77+'WK24'!I77 -> 0 | J77: ='WK22'!J77+'WK21'!J77+'WK23'!J77+'WK24'!J77 -> 8 | K77: ='WK22'!$N$77+'WK21'!$N$77+'WK23'!$N$77+'WK24'!$N$77 -> 0 | L77: ='WK22'!$P$77+'WK21'!$P$77+'WK23'!$P$77+'WK24'!$P$77 -> -417 | M77: ='WK22'!Q77+'WK21'!Q77+'WK23'!Q77 -> 1640.1085 | N77: ='WK24'!Q77 -> 385.32 | O77: =M77+N77 -> 2025.4285 | P77: Totaal: | Q77: =(14.3)+(15.4)+(20.9)+(18.7)+(16.5)+(19.8) -> 105.6 | R77: =-113.83-91.51 -> -205.34
O78: ='WK24'!Q76 -> 60.43 | P78: =O77+O78 -> 2085.8585
R79: 80 | S79: Voorschot p-kosten Nijmegen (14-4)
A80: 19 | B80: =Periode!B80 -> Leo van Doorn | C80: =Periode!H80 -> UTA | D80: ='WK22'!D80+'WK21'!D80+'WK23'!D80+'WK24'!D80 -> 19 | E80: ='WK22'!E80+'WK21'!E80+'WK23'!E80+'WK24'!E80 -> 152 | F80: ='WK22'!F80+'WK21'!F80+'WK23'!F80+'WK24'!F80 -> 0 | G80: ='WK22'!G80+'WK21'!G80+'WK23'!G80+'WK24'!G80 -> 0 | H80: ='WK22'!H80+'WK21'!H80+'WK23'!H80+'WK24'!H80 -> 0 | I80: ='WK22'!I80+'WK21'!I80+'WK23'!I80+'WK24'!I80 -> 0 | J80: ='WK22'!J80+'WK21'!J80+'WK23'!J80+'WK24'!J80 -> 8 | K80: ='WK22'!N80+'WK21'!N80+'WK23'!N80+'WK24'!N80 -> 798 | L80: ='WK22'!P80+'WK21'!P80+'WK23'!P80+'WK24'!P80 -> 0 | M80: ='WK22'!Q80+'WK21'!Q80+'WK23'!Q80 -> 2296.2591 | N80: ='WK24'!Q80 -> 770.56 | O80: =M80+N80 -> 3066.8191 | Q80: =(200.6+16.5)+(166.17+20.9)+(197.18+18.7)+(178.38+20.9)+(187.82+13.2)+(170.56+20.9) -> 1211.81
A83: 20 | B83: =Periode!B83 -> Tobin van de Kuil | C83: =Periode!H83 -> Bouw | D83: ='WK22'!D83+'WK21'!D83+'WK23'!D83+'WK24'!D83 -> 9 | E83: ='WK22'!E83+'WK21'!E83+'WK23'!E83+'WK24'!E83 -> 69 | F83: ='WK22'!F83+'WK21'!F83+'WK23'!F83+'WK24'!F83 -> 7.5 | G83: ='WK22'!G83+'WK21'!G83+'WK23'!G83+'WK24'!G83 -> 0 | H83: ='WK22'!H83+'WK21'!H83+'WK23'!H83+'WK24'!H83 -> 0 | I83: ='WK22'!I83+'WK21'!I83+'WK23'!I83+'WK24'!I83 -> 0 | J83: ='WK22'!J83+'WK21'!J83+'WK23'!J83+'WK24'!J83 -> 8 | K83: ='WK22'!N83+'WK21'!N83+'WK23'!N83+'WK24'!N83 -> 768 | L83: ='WK22'!P83+'WK21'!P83+'WK23'!P83+'WK24'!P83 -> 0 | M83: ='WK22'!Q83+'WK21'!Q83+'WK23'!Q83 -> 974.14086 | N83: ='WK24'!Q83 -> 822.08513 | O83: =M83+N83 -> 1796.226 | P83: Totaal: | Q83: =(0)+(0)+(0)+(14.3)+(13.2)+(9.9) -> 37.4
O84: ='WK24'!Q82 -> 46.36 | P84: =O83+O84 -> 1842.586
A87: 21 | B87: =Periode!B87 -> Carlo Peetoom | C87: =Periode!H87 -> UTA | D87: ='WK22'!D87+'WK21'!D87+'WK23'!D87+'WK24'!D87 -> 15 | E87: ='WK22'!E87+'WK21'!E87+'WK23'!E87+'WK24'!E87 -> 120 | F87: ='WK22'!F87+'WK21'!F87+'WK23'!F87+'WK24'!F87 -> 0 | G87: ='WK22'!G87+'WK21'!G87+'WK23'!G87+'WK24'!G87 -> 0 | H87: ='WK22'!H87+'WK21'!H87+'WK23'!H87+'WK24'!H87 -> 0 | I87: ='WK22'!I87+'WK21'!I87+'WK23'!I87+'WK24'!I87 -> 0 | J87: ='WK22'!J87+'WK21'!J87+'WK23'!J87+'WK24'!J87 -> 8 | K87: ='WK22'!N87+'WK21'!N87+'WK23'!N87+'WK24'!N87 -> 1200 | L87: ='WK22'!P87+'WK21'!P87+'WK23'!P87+'WK24'!P87 -> 112.95 | M87: ='WK22'!Q87+'WK21'!Q87+'WK23'!Q87 -> 2337.8753 | N87: ='WK24'!Q87 -> 752.54 | O87: =M87+N87 -> 3090.4153 | Q87: =(262.12+13.2)+(180.21+17.6)+(191.36+13.2)+(212.35+15.4)+(211.21+15.4)+(75.64+16.5) -> 1224.19
A90: 22 | B90: =Periode!B90 -> Aries Provence | C90: =Periode!H90 -> UTA | D90: ='WK22'!D90+'WK21'!D90+'WK23'!D90+'WK24'!D90 -> 18 | E90: ='WK22'!E90+'WK21'!E90+'WK23'!E90+'WK24'!E90 -> 144 | F90: ='WK22'!F90+'WK21'!F90+'WK23'!F90+'WK24'!F90 -> 0 | G90: ='WK22'!G90+'WK21'!G90+'WK23'!G90+'WK24'!G90 -> 0 | H90: ='WK22'!H90+'WK21'!H90+'WK23'!H90+'WK24'!H90 -> 0 | I90: ='WK22'!I90+'WK21'!I90+'WK23'!I90+'WK24'!I90 -> 0 | J90: ='WK22'!J90+'WK21'!J90+'WK23'!J90+'WK24'!J90 -> 8 | K90: ='WK22'!N90+'WK21'!N90+'WK23'!N90+'WK24'!N90 -> 3060 | L90: ='WK22'!P90+'WK21'!P90+'WK23'!P90+'WK24'!P90 -> 13.6 | M90: ='WK22'!Q90+'WK21'!Q90+'WK23'!Q90 -> 2230.0279 | N90: ='WK24'!Q90 -> 812.845 | O90: =M90+N90 -> 3042.8729 | Q90: =(182.9+20.9)+(158.25+17.6) -> 379.65
A92: 23 | B92: =Periode!B92 -> Gregory de Graaf | C92: =Periode!H92 -> Bouw | D92: ='WK22'!D92+'WK21'!D92+'WK23'!D92+'WK24'!D92 -> 18 | E92: ='WK22'!E92+'WK21'!E92+'WK23'!E92+'WK24'!E92 -> 128.5 | F92: ='WK22'!F92+'WK21'!F92+'WK23'!F92+'WK24'!F92 -> 0 | G92: ='WK22'!G92+'WK21'!G92+'WK23'!G92+'WK24'!G92 -> 0 | H92: ='WK22'!H92+'WK21'!H92+'WK23'!H92+'WK24'!H92 -> 0 | I92: ='WK22'!I92+'WK21'!I92+'WK23'!I92+'WK24'!I92 -> 4 | J92: ='WK22'!J92+'WK21'!J92+'WK23'!J92+'WK24'!J92 -> 8 | K92: ='WK22'!N92+'WK21'!N92+'WK23'!N92+'WK24'!N92 -> 0 | L92: ='WK22'!P92+'WK21'!P92+'WK23'!P92+'WK24'!P92 -> 0 | M92: ='WK22'!Q92+'WK21'!Q92+'WK23'!Q92 -> 1979.6616 | N92: ='WK24'!Q92 -> 2586.6549 | O92: =N92 -> 2586.6549 | Q92: =(196.79+16.5)+(160.31+17.6)+(163.39+19.8) -> 574.39
B95: =Periode!B95 -> Joey Cuperus | R95: =5195-280-280-18.72-814.78 -> 3801.5 | S95: Voorschot 08-08-2025 € 5195,00
A99: 24 | B99: =Periode!B99 -> Eric de Jong | C99: =Periode!H99 -> UTA | D99: ='WK22'!D99+'WK21'!D99+'WK23'!D99+'WK24'!D99 -> 15 | E99: ='WK22'!E99+'WK21'!E99+'WK23'!E99+'WK24'!E99 -> 116.5 | F99: ='WK22'!F99+'WK21'!F99+'WK23'!F99+'WK24'!F99 -> 0 | G99: ='WK22'!G99+'WK21'!G99+'WK23'!G99+'WK24'!G99 -> 0 | H99: ='WK22'!H99+'WK21'!H99+'WK23'!H99+'WK24'!H99 -> 0 | I99: ='WK22'!I99+'WK21'!I99+'WK23'!I99+'WK24'!I99 -> 0 | J99: ='WK22'!J99+'WK21'!J99+'WK23'!J99+'WK24'!J99 -> 8 | K99: ='WK22'!N99+'WK21'!N99+'WK23'!N99+'WK24'!N99 -> 1410 | L99: ='WK22'!P99+'WK21'!P99+'WK23'!P99+'WK24'!P99 -> 0 | M99: ='WK22'!Q99+'WK21'!Q99+'WK23'!Q99 -> 2253.7286 | N99: ='WK24'!Q99 -> 954.90913 | O99: =M99+N99 -> 3208.6377 | Q99: =(209.05+11)+(192.09+18.7)+(183+18.7)+(174.66+15.4)+(168.49+16.5) -> 1007.59
A104: 25 | B104: =Periode!B104 -> Michel van der Mark | C104: =Periode!H104 -> Bouw | D104: ='WK22'!D104+'WK21'!D104+'WK23'!D104+'WK24'!D104 -> 14 | E104: ='WK22'!E104+'WK21'!E104+'WK23'!E104+'WK24'!E104 -> 112 | F104: ='WK22'!F104+'WK21'!F104+'WK23'!F104+'WK24'!F104 -> 0 | G104: ='WK22'!G104+'WK21'!G104+'WK23'!G104+'WK24'!G104 -> 28.8 | H104: ='WK22'!H104+'WK21'!H104+'WK23'!H104+'WK24'!H104 -> 0 | I104: ='WK22'!I104+'WK21'!I104+'WK23'!I104+'WK24'!I104 -> 0 | J104: ='WK22'!J104+'WK21'!J104+'WK23'!J104+'WK24'!J104 -> 8 | K104: ='WK22'!N104+'WK21'!N104+'WK23'!N104+'WK24'!N104 -> 0 | L104: ='WK22'!P104+'WK21'!P104+'WK23'!P104+'WK24'!P104 -> 0 | M104: ='WK22'!Q104+'WK21'!Q104+'WK23'!Q104 -> 1896.9381 | N104: ='WK24'!Q104 -> 705.18 | O104: =M104+N104 -> 2602.1181 | Q104: =(255.77+15.4)+(234.46+20.9)+(172.32+17.6)+(178.18+19.8)+(153.5+18.7)+(150.72+15.4) -> 1252.75
A110: 26 | B110: =Periode!B110 -> Jan Harteveld | C110: =Periode!H110 -> Bouw | D110: ='WK22'!D110+'WK21'!D110+'WK23'!D110+'WK24'!D110 -> 19 | E110: ='WK22'!E110+'WK21'!E110+'WK23'!E110+'WK24'!E110 -> 141 | F110: ='WK22'!F110+'WK21'!F110+'WK23'!F110+'WK24'!F110 -> 2.5 | G110: ='WK22'!G110+'WK21'!G110+'WK23'!G110+'WK24'!G110 -> 0 | H110: ='WK22'!H110+'WK21'!H110+'WK23'!H110+'WK24'!H110 -> 0 | I110: ='WK22'!I110+'WK21'!I110+'WK23'!I110+'WK24'!I110 -> 0 | J110: ='WK22'!J110+'WK21'!J110+'WK23'!J110+'WK24'!J110 -> 6.5 | K110: ='WK22'!N110+'WK21'!N110+'WK23'!N110+'WK24'!N110 -> 532 | L110: ='WK22'!P110+'WK21'!P110+'WK23'!P110+'WK24'!P110 -> 2.8 | M110: ='WK22'!Q110+'WK21'!Q110+'WK23'!Q110 -> 2324.9948 | N110: ='WK24'!Q110 -> 778.76562 | O110: =M110+N110 -> 3103.7604 | Q110: =(186.17+16.5)+(183.06+18.7)+(99.92+20.9)+(159.61+19.8)+(13.2)+(118.67+20.9) -> 857.43 | R110: =-25.06+25.06 -> 0
A116: 27 | B116: =Periode!B116 -> Asanty Raafenberg | C116: =Periode!H116 -> Bouw | D116: ='WK22'!D116+'WK21'!D116+'WK23'!D116+'WK24'!D116 -> 15 | E116: ='WK22'!E116+'WK21'!E116+'WK23'!E116+'WK24'!E116 -> 120 | F116: ='WK22'!F116+'WK21'!F116+'WK23'!F116+'WK24'!F116 -> 0 | G116: ='WK22'!G116+'WK21'!G116+'WK23'!G116+'WK24'!G116 -> 0 | H116: ='WK22'!H116+'WK21'!H116+'WK23'!H116+'WK24'!H116 -> 0 | I116: ='WK22'!I116+'WK21'!I116+'WK23'!I116+'WK24'!I116 -> 0 | J116: ='WK22'!J116+'WK21'!J116+'WK23'!J116+'WK24'!J116 -> 8 | K116: ='WK22'!N116+'WK21'!N116+'WK23'!N116+'WK24'!N116 -> 0 | L116: ='WK22'!P116+'WK21'!P116+'WK23'!P116+'WK24'!P116 -> -80.82 | M116: ='WK22'!Q116+'WK21'!Q116+'WK23'!Q116 -> 1368.238 | N116: ='WK24'!Q116 -> 2028.518 | O116: =N116 -> 2028.518 | Q116: =(232.68+15.4)+(180.73+19.8)+(192.61+19.8)+(155.45+20.9)+(176.83+17.6)+(20.63+16.5) -> 1068.93
A119: 28 | B119: =Periode!B119 -> Patrick Serlier | C119: =Periode!H119 -> Bouw | D119: ='WK22'!D119+'WK21'!D119+'WK23'!D119+'WK24'!D119 -> 19 | E119: ='WK22'!E119+'WK21'!E119+'WK23'!E119+'WK24'!E119 -> 151 | F119: ='WK22'!F119+'WK21'!F119+'WK23'!F119+'WK24'!F119 -> 0 | G119: ='WK22'!G119+'WK21'!G119+'WK23'!G119+'WK24'!G119 -> 0 | H119: ='WK22'!H119+'WK21'!H119+'WK23'!H119+'WK24'!H119 -> 0 | I119: ='WK22'!I119+'WK21'!I119+'WK23'!I119+'WK24'!I119 -> 0 | J119: ='WK22'!J119+'WK21'!J119+'WK23'!J119+'WK24'!J119 -> 8 | K119: ='WK22'!N119+'WK21'!N119+'WK23'!N119+'WK24'!N119 -> 0 | L119: ='WK22'!P119+'WK21'!P119+'WK23'!P119+'WK24'!P119 -> 0 | M119: ='WK22'!Q119+'WK21'!Q119+'WK23'!Q119 -> 2021.8713 | N119: ='WK24'!Q119 -> 658.58325 | O119: =M119+N119 -> 2680.4545 | Q119: =(14.3)+(29.72+22)+(20.41+22)+(20.21+20.9)+(24.78+18.7)+(15.09+20.9) -> 229.01 | R119: =-42.91+42.91 -> 0
A123: 29 | B123: =Periode!B123 -> Pieter van Houwelingen | C123: =Periode!H123 -> UTA | D123: ='WK22'!D123+'WK21'!D123+'WK23'!D123+'WK24'!D123 -> 18 | E123: ='WK22'!E123+'WK21'!E123+'WK23'!E123+'WK24'!E123 -> 138 | F123: ='WK22'!F123+'WK21'!F123+'WK23'!F123+'WK24'!F123 -> 0 | G123: ='WK22'!G123+'WK21'!G123+'WK23'!G123+'WK24'!G123 -> 0 | H123: ='WK22'!H123+'WK21'!H123+'WK23'!H123+'WK24'!H123 -> 6 | I123: ='WK22'!I123+'WK21'!I123+'WK23'!I123+'WK24'!I123 -> 0 | J123: ='WK22'!J123+'WK21'!J123+'WK23'!J123+'WK24'!J123 -> 8 | K123: ='WK22'!N123+'WK21'!N123+'WK23'!N123+'WK24'!N123 -> 1170 | L123: ='WK22'!P123+'WK21'!P123+'WK23'!P123+'WK24'!P123 -> 6.5 | M123: ='WK22'!Q123+'WK21'!Q123+'WK23'!Q123 -> 3198.5364 | N123: ='WK24'!Q123 -> 1079.5433 | O123: =M123+N123 -> 4278.0796 | P123: Vergoeding zorg € 20,67 | Q123: =(242.62+16.5)+(202.61+22)+(186.43+20.9)+(175.52+19.8)+(199.77+18.7)+(132.44+19.8) -> 1257.09
A125: 30 | B125: =Periode!B125 -> John van der Wel | C125: =Periode!H125 -> Bouw | D125: ='WK22'!D125+'WK21'!D125+'WK23'!D125+'WK24'!D125 -> 18 | E125: ='WK22'!E125+'WK21'!E125+'WK23'!E125+'WK24'!E125 -> 141.5 | F125: ='WK22'!F125+'WK21'!F125+'WK23'!F125+'WK24'!F125 -> 0 | G125: ='WK22'!G125+'WK21'!G125+'WK23'!G125+'WK24'!G125 -> 0 | H125: ='WK22'!H125+'WK21'!H125+'WK23'!H125+'WK24'!H125 -> 0 | I125: ='WK22'!I125+'WK21'!I125+'WK23'!I125+'WK24'!I125 -> 0 | J125: ='WK22'!J125+'WK21'!J125+'WK23'!J125+'WK24'!J125 -> 8 | K125: ='WK22'!N125+'WK21'!N125+'WK23'!N125+'WK24'!N125 -> 0 | L125: ='WK22'!P125+'WK21'!P125+'WK23'!P125+'WK24'!P125 -> -260.24 | M125: ='WK22'!Q125+'WK21'!Q125+'WK23'!Q125 -> 1569.6609 | N125: ='WK24'!Q125 -> 580.92 | O125: =M125+N125 -> 2150.5809 | P125: Totaal: | Q125: =(85.82+9.9)+(17.6)+(19.8) -> 133.12 | R125: =-28.59+26.24 -> -2.35
O126: ='WK24'!Q124 -> 0 | P126: =O125+O126 -> 2150.5809
A129: 31 | B129: =Periode!B129 -> Marcel Spruijt | C129: =Periode!H129 -> UTA | D129: ='WK22'!D129+'WK21'!D129+'WK23'!D129+'WK24'!D129 -> 19 | E129: ='WK22'!E129+'WK21'!E129+'WK23'!E129+'WK24'!E129 -> 152 | F129: ='WK22'!F129+'WK21'!F129+'WK23'!F129+'WK24'!F129 -> 0 | G129: ='WK22'!G129+'WK21'!G129+'WK23'!G129+'WK24'!G129 -> 0 | H129: ='WK22'!H129+'WK21'!H129+'WK23'!H129+'WK24'!H129 -> 0 | I129: ='WK22'!I129+'WK21'!I129+'WK23'!I129+'WK24'!I129 -> 0 | J129: ='WK22'!J129+'WK21'!J129+'WK23'!J129+'WK24'!J129 -> 8 | K129: ='WK22'!N129+'WK21'!N129+'WK23'!N129+'WK24'!N129 -> 0 | L129: ='WK22'!P129+'WK21'!P129+'WK23'!P129+'WK24'!P129 -> -21.14 | M129: ='WK22'!Q129+'WK21'!Q129+'WK23'!Q129 -> 2222.1978 | N129: ='WK24'!Q129 -> 751.94 | O129: =M129+N129 -> 2974.1378 | Q129: =(238.52+16.5)+(175.49+22)+(121.83+20.9)+(161.76+20.9)+(191.92+17.6)+(156.12+20.9) -> 1164.44
A131: 32 | B131: =Periode!B131 -> Michael Windhorst | C131: =Periode!H131 -> Bouw | D131: ='WK22'!D131+'WK21'!D131+'WK23'!D131+'WK24'!D131 -> 17 | E131: ='WK22'!E131+'WK21'!E131+'WK23'!E131+'WK24'!E131 -> 132 | F131: ='WK22'!F131+'WK21'!F131+'WK23'!F131+'WK24'!F131 -> 12.24 | G131: ='WK22'!G131+'WK21'!G131+'WK23'!G131+'WK24'!G131 -> 0 | H131: ='WK22'!H131+'WK21'!H131+'WK23'!H131+'WK24'!H131 -> 0 | I131: ='WK22'!I131+'WK21'!I131+'WK23'!I131+'WK24'!I131 -> 0 | J131: ='WK22'!J131+'WK21'!J131+'WK23'!J131+'WK24'!J131 -> 8 | K131: ='WK22'!N131+'WK21'!N131+'WK23'!N131+'WK24'!N131 -> 0 | L131: ='WK22'!P131+'WK21'!P131+'WK23'!P131+'WK24'!P131 -> 0 | M131: ='WK22'!Q131+'WK21'!Q131+'WK23'!Q131 -> 1750.9252 | N131: ='WK24'!Q131 -> 628 | O131: =M131+N131 -> 2378.9252 | P131: Let op: Bijtelling - welke tabel
Q132: =0+0+0+0+(3.3)+(49.63+18.7) -> 71.63
A134: 33 | B134: =Periode!B134 -> Remco van Doorne | C134: =Periode!H134 -> Bouw | D134: ='WK22'!D134+'WK21'!D134+'WK23'!D134+'WK24'!D134 -> 18 | E134: ='WK22'!E134+'WK21'!E134+'WK23'!E134+'WK24'!E134 -> 143 | F134: ='WK22'!F134+'WK21'!F134+'WK23'!F134+'WK24'!F134 -> 0 | G134: ='WK22'!G134+'WK21'!G134+'WK23'!G134+'WK24'!G134 -> 0 | H134: ='WK22'!H134+'WK21'!H134+'WK23'!H134+'WK24'!H134 -> 0 | I134: ='WK22'!I134+'WK21'!I134+'WK23'!I134+'WK24'!I134 -> 0 | J134: ='WK22'!J134+'WK21'!J134+'WK23'!J134+'WK24'!J134 -> 8 | K134: ='WK22'!N134+'WK21'!N134+'WK23'!N134+'WK24'!N134 -> 0 | L134: ='WK22'!P134+'WK21'!P134+'WK23'!P134+'WK24'!P134 -> 187.74 | M134: ='WK22'!Q134+'WK21'!Q134+'WK23'!Q134 -> 1641.0067 | N134: ='WK24'!Q134 -> 594.6425 | O134: =M134+N134 -> 2235.6492 | P134: Totaal: | Q134: =(0)+(0)+(0)+(73.53+9.9)+(147.06+19.8)+(147.06+19.8) -> 417.15
O135: ='WK24'!Q133 -> 40.77 | P135: =O134+O135 -> 2276.4192
A138: 34 | B138: =Periode!B138 -> Rob Valkenburg | C138: =Periode!H138 -> Bouw | D138: ='WK22'!D138+'WK21'!D138+'WK23'!D138+'WK24'!D138 -> 18 | E138: ='WK22'!E138+'WK21'!E138+'WK23'!E138+'WK24'!E138 -> 137 | F138: ='WK22'!F138+'WK21'!F138+'WK23'!F138+'WK24'!F138 -> 0 | G138: ='WK22'!G138+'WK21'!G138+'WK23'!G138+'WK24'!G138 -> 0 | H138: ='WK22'!H138+'WK21'!H138+'WK23'!H138+'WK24'!H138 -> 0 | I138: ='WK22'!I138+'WK21'!I138+'WK23'!I138+'WK24'!I138 -> 0 | J138: ='WK22'!J138+'WK21'!J138+'WK23'!J138+'WK24'!J138 -> 8 | K138: ='WK22'!N138+'WK21'!N138+'WK23'!N138+'WK24'!N138 -> 1260 | L138: ='WK22'!P138+'WK21'!P138+'WK23'!P138+'WK24'!P138 -> 0 | M138: ='WK22'!Q138+'WK21'!Q138+'WK23'!Q138 -> 2383.1385 | N138: ='WK24'!Q138 -> 618.18362 | O138: =M138+N138 -> 3001.3221 | Q138: =(151.5+15.4)+(291.22+17.6)+(189.68+20.9)+(14.3)+(16.5)+(19.8) -> 736.9 | R138: =-9.94-39.78+16.03 -> -33.69
A141: 35 | B141: =Periode!B141 -> Herman Vos | C141: =Periode!H141 -> Bouw | D141: ='WK22'!D141+'WK21'!D141+'WK23'!D141+'WK24'!D141 -> 18 | E141: ='WK22'!E141+'WK21'!E141+'WK23'!E141+'WK24'!E141 -> 144 | F141: ='WK22'!F141+'WK21'!F141+'WK23'!F141+'WK24'!F141 -> 0 | G141: ='WK22'!G141+'WK21'!G141+'WK23'!G141+'WK24'!G141 -> 0 | H141: ='WK22'!H141+'WK21'!H141+'WK23'!H141+'WK24'!H141 -> 8 | I141: ='WK22'!I141+'WK21'!I141+'WK23'!I141+'WK24'!I141 -> 0 | J141: ='WK22'!J141+'WK21'!J141+'WK23'!J141+'WK24'!J141 -> 8 | K141: ='WK22'!N141+'WK21'!N141+'WK23'!N141+'WK24'!N141 -> 0 | L141: ='WK22'!P141+'WK21'!P141+'WK23'!P141+'WK24'!P141 -> 13.16 | M141: ='WK22'!Q141+'WK21'!Q141+'WK23'!Q141 -> 2255.6852 | N141: ='WK24'!Q141 -> 750 | O141: =M141+N141 -> 3005.6852 | Q141: =(0)+(0)+(0)+(228.18+13.2)+(200.37+18.7)+(166.27+19.8) -> 646.52
A143: 36 | B143: =Periode!B143 -> Remco Groenendaal | C143: =Periode!H143 -> Bouw | D143: ='WK22'!D143+'WK21'!D143+'WK23'!D143+'WK24'!D143 -> 16 | E143: ='WK22'!E143+'WK21'!E143+'WK23'!E143+'WK24'!E143 -> 117.5 | F143: ='WK22'!F143+'WK21'!F143+'WK23'!F143+'WK24'!F143 -> 9 | G143: ='WK22'!G143+'WK21'!G143+'WK23'!G143+'WK24'!G143 -> 0 | H143: ='WK22'!H143+'WK21'!H143+'WK23'!H143+'WK24'!H143 -> 0 | I143: ='WK22'!I143+'WK21'!I143+'WK23'!I143+'WK24'!I143 -> 25.5 | J143: ='WK22'!J143+'WK21'!J143+'WK23'!J143+'WK24'!J143 -> 8 | K143: ='WK22'!N143+'WK21'!N143+'WK23'!N143+'WK24'!N143 -> 960 | L143: ='WK22'!P143+'WK21'!P143+'WK23'!P143+'WK24'!P143 -> -9 | M143: ='WK22'!Q143+'WK21'!Q143+'WK23'!Q143 -> 2317.2533 | N143: ='WK24'!Q143 -> 806.02 | O143: =M143+N143 -> 3123.2733 | Q143: =(0)+(8.8)+(4.4)+(14.3)+(17.6) -> 45.1 | R143: =-6.23-460.38-8.19-28.94+9.15 -> -494.59
A147: 37 | B147: =Periode!B147 -> Fred Termonen | C147: =Periode!H147 -> UTA | D147: ='WK22'!D147+'WK21'!D147+'WK23'!D147+'WK24'!D147 -> 9 | E147: ='WK22'!E147+'WK21'!E147+'WK23'!E147+'WK24'!E147 -> 72 | F147: ='WK22'!F147+'WK21'!F147+'WK23'!F147+'WK24'!F147 -> 16 | G147: ='WK22'!G147+'WK21'!G147+'WK23'!G147+'WK24'!G147 -> 0 | H147: ='WK22'!H147+'WK21'!H147+'WK23'!H147+'WK24'!H147 -> 0 | I147: ='WK22'!I147+'WK21'!I147+'WK23'!I147+'WK24'!I147 -> 0 | J147: ='WK22'!J147+'WK21'!J147+'WK23'!J147+'WK24'!J147 -> 8 | K147: ='WK22'!N147+'WK21'!N147+'WK23'!N147+'WK24'!N147 -> 0 | L147: ='WK22'!P147+'WK21'!P147+'WK23'!P147+'WK24'!P147 -> 0 | M147: ='WK22'!Q147+'WK21'!Q147+'WK23'!Q147 -> 1358.7371 | N147: ='WK24'!Q147 -> 456.672 | O147: =M147+N147 -> 1815.4091 | Q147: =(155.35+9.9)+(117.86+12.1)+(124.01+9.9)+(156.7+11)+(130.35+11)+(142.82+9.9) -> 890.89
A149: 38 | B149: =Periode!B149 -> Arnold Verstraten | C149: =Periode!H149 -> Bouw | D149: ='WK22'!D149+'WK21'!D149+'WK23'!D149+'WK24'!D149 -> 19 | E149: ='WK22'!E149+'WK21'!E149+'WK23'!E149+'WK24'!E149 -> 152 | F149: ='WK22'!F149+'WK21'!F149+'WK23'!F149+'WK24'!F149 -> 0 | G149: ='WK22'!G149+'WK21'!G149+'WK23'!G149+'WK24'!G149 -> 0 | H149: ='WK22'!H149+'WK21'!H149+'WK23'!H149+'WK24'!H149 -> 0 | I149: ='WK22'!I149+'WK21'!I149+'WK23'!I149+'WK24'!I149 -> 0 | J149: ='WK22'!J149+'WK21'!J149+'WK23'!J149+'WK24'!J149 -> 8 | K149: ='WK22'!N149+'WK21'!N149+'WK23'!N149+'WK24'!N149 -> 1026 | L149: ='WK22'!P149+'WK21'!P149+'WK23'!P149+'WK24'!P149 -> 0 | M149: ='WK22'!Q149+'WK21'!Q149+'WK23'!Q149 -> 2309.3018 | N149: ='WK24'!Q149 -> 776.02 | O149: =M149+N149 -> 3085.3218 | Q149: =(77.51+15.4)+(188.27+19.8)+(133.55+20.9)+(143.42+19.8)+(196.22+17.6)+(82.44+20.9)+(169.5+20.9) -> 1126.21
C155: =Periode!H155 -> 0 | D155: ='WK22'!D155+'WK21'!D155+'WK23'!D155+'WK24'!D155 -> 0 | E155: ='WK22'!E155+'WK21'!E155+'WK23'!E155+'WK24'!E155 -> 0 | F155: ='WK22'!F155+'WK21'!F155+'WK23'!F155+'WK24'!F155 -> 0 | G155: ='WK22'!G155+'WK21'!G155+'WK23'!G155+'WK24'!G155 -> 0 | H155: ='WK22'!H155+'WK21'!H155+'WK23'!H155+'WK24'!H155 -> 0 | I155: ='WK22'!I155+'WK21'!I155+'WK23'!I155+'WK24'!I155 -> 0 | J155: ='WK22'!J155+'WK21'!J155+'WK23'!J155+'WK24'!J155 -> 0 | K155: ='WK22'!N155+'WK21'!N155+'WK23'!N155+'WK24'!N155 -> 0 | L155: ='WK22'!P155+'WK21'!P155+'WK23'!P155+'WK24'!P155 -> 0 | M155: ='WK22'!Q155+'WK21'!Q155+'WK23'!Q155 -> 0 | N155: ='WK24'!Q155 -> 0 | O155: =M155+N155 -> 0 | Q155: =(2.08)+(7.93)+8.26 -> 18.27

Sheet Grondslag bouw & infra
B2: Recht | C2: Bouwplaatsm. Waarde | D2: UTA waarde | E2: Bron | F2: Opmerking
A3: Reserveringen | G3: Opmerking
A4: 20 vakantiedagen (18+ jaar oud) | C4: =20/B54 -> #DIV/0! | E4: art 3.1 | F4: Is de werknemer slechts een deel van het jaar bij de werkgever in dienst? Dan heeft hij recht op het aantal vakantiedagen naar rato van de duur van zijn arbeidsovereenkomst in dat jaar.
A5: Roostervrij | C5: 20 dagen | D5: 15 dagen | E5: 3.2
A6: Roostervrij ouderen | B6: t/m bouwjaar 1965 | E6: 3.3
A7: Vakantiegeld | B7: 8,33% t/m 30 Juni 2026, daarna 8% | E7: nbbu 36.a
A8: Feestdagen | B8: Christelijke feestdagen | E8: art. 3.4.1 | F8: De werkgever betaalt over deze feestdagen het vast overeengekomen loon of het salaris. | G8: Aantal dagen afhankelijk leeftijd
A9: Kort verzuim | B9: 3x (8) uur p/jaar, zorgverlof partner, dokter, suikerfeest etc. opnemen regelement | E9: art. 3.6.4 | F9: Recht opnemen in Arbeidsovereenkomst/UZB
A10: Reservering scholing | B10: 2 dagen = 0,77%
A12: BTER pensioen
A13: BPF
A14: Stipp plus (max 2jaar) | B14: 15,9% werkgever, 7,5% werknemer
A15: Compensatie BPF bij Stipp (max 2 jaar)
A16: WGA-hiaat | B16: Bij BPFbouw deelnemer niet van toepassing, nieuwkomer = risico | E16: art. 9.3.2.
A18: (alleen vakkracht) BTER premies | B18: NOTK eind december, nieuw stelsel
A19: BpfBouw Middelloon | B19: Volledig toepassen | E19: BTER-cao
A20: Arbeidsongeschiktheidpensioen | B20: Volledig toepassen | E20: BTER-cao
A21: Opleiding- en Ontwikkelingsfonds | B21: 1. Polis Collect. Ongevallenverzekering regelen | F21: Opleiding & Ontwikkelingsregeling Top Groep Nederland
B22: 2. SFU + aanvullen met regeling voor scholing en duurzame inzetbaarheid
A23: ST. aanvullingsfonds Bouw | B23: Alleen zwaarwerkregeling toepassen, overige is uitgesloten | E23: artikel 5 lid 2 BTER-cao. Financieringsreglement Aanvullingsfonds, artikel 2 lid 3: | G23: Doorbet / Verz. Uitzk. res. Periodiek uitbetaald / reserv.
A25: Individueel budget | B25: In 2026: | C25: 0.0451 | D25: 0.023 | E25: art. 4.14 / bijlage 4.2/ flyer fnv
B26: Individueel scholingsbudget in AOK zetten, (use it, or u lose it beleid) | C26: 0.0086
C27: =C25-C26 -> 0.0365 | D27: =D25-D26 -> 0.023 | G27: Indien reservering zou de RG FL+WDC zijn.
A29: Bruto toeslagen / Compensatie
A30: Roostervrij /senioren | C30: 0,4%
A31: Zorgverzekering | B31: bruto per 4 weken | C31: =22.39*12/13 -> 20.667692
A32: Reisuur | B32: bruto per uur | C32: € 18,95-20,02 p/uur
A34: Vergoedingen
A35: Handgereedschap timmerman | B35: netto per dag | C35: 0.96
A36: Handgereedschap metselaar | B36: netto per dag | C36: 0.68
A37: Werkkleding | B37: netto per dag | C37: Uitdelen, of vergoeden á €1,10 p/dag
A38: S3 schoenen | C38: Eenmalig per jaar € 125,- declaraarbaar in beleid
A39: Laarzen (bovenmatig) | B39: netto per dag | C39: 0.68
A40: Vakbond contributie
A42: Stipp pensioen grondslag | B42: = pensioengevend salaris – franchise (uurfranchise x pensioengevende uren) | E42: https://www.stippensioen.nl/werkgever/pensioenadministratie/pensioengevend-loon-en-pensioengrondslag-berekenen/
A43: Compensatie bouwpensioen | B43: =18.6182%-15.9% -> 0.027182
A44: Compensatie UTA | B44: =17.3596%-15.9% -> 0.014596
A45: Compensatie SAVG
A46: Urr franchiche stipp | B46: 9.24
H48: =262*8 -> 2096
A50: Werkdagen | B50: 261
A51: Feestdagen | B51: 6
A52: Netto werkbare dagen | B52: =B50-B51 -> 255

Sheet SAVG
C2: Recht | D2: Waarde | E2: Bron | F2: Opmerking
B3: Reserveringen
B4: 25 vakantiedagen (18+ jaar oud)
B5: Roostervrij | C5: 7 niet vrij opneembare ATV-dagen
B6: Roostervrij ouderen
B7: Vakantiegeld
B8: Feestdagen
B9: Kort verzuim
B11: Pensioen
B12: Stipp plus | C12: StiPP (nieuwe regeling): totale premie 23,4% (wg 15,9% / wn 7,5%).
B13: Compensatie BPF | C13: BPF Schilders 2026 (totaal) komt uit op 27,64% + 0,48% + 0,67% + 0,08% = 28,87%
B18: Voorzieningen
B19: PAGO | C19: Periodiek Arbeidsgezondheidskundig Onderzoek / Gezondheids- en Bodycheck | E19: USAG H5 art. 1 en art. 5
B20: Loopbaancheck (+40 jaar oud) | C20: inventariserend gesprek met loopbaancoach, met schriftelijk advies. (Referentie: USAG H5 art. 6). | E20: (Referentie: USAG H5 art. 6).
B21: Adviestraject | C21: vervolg op de loopbaancheck bestaande uit adviesgesprekken. | E21: (Referentie: USAG H5 art. 7).
B22: Collectieve ongevallenverzekering | D22: €33.000 overlijden / €66.000 volledige invaliditeit).
B23: SFU | C23: is extra
B31: Bruto toeslagen / Compensatie
B32: Reisuur | D32: Reisuren: na eerste 60 min/dag €10 bruto/uur
B36: Vergoedingen
B37: Reiskosten | D37: auto €0,30/km
B38: Uitrusting | D38: €1,60 per gewerkte dag
B39: Vakbond contributie | C39: o.b.v. bewijs betaling contributie | D39: volldig netto
